Workbook

Sheet Prospectos Resumen
A1: PRESOL — Prospectos | Resumen Ejecutivo
A2: Dirección · Filtrar por Categoría, Corredor o Ciudad · Completar libremente “Nota Dirección”
A4: TOTAL | C4: CLASE A | E4: CLASE B | G4: CLASE C | I4: TELÉFONOS OK | K4: A VERIFICAR
A5: =COUNTA(Prospectos!A2:A288) -> 287 | C5: =COUNTIF(Prospectos!F2:F288,"A") -> 162 | E5: =COUNTIF(Prospectos!F2:F288,"B") -> 110 | G5: =COUNTIF(Prospectos!F2:F288,"C") -> 15 | I5: =COUNTIF(Prospectos!L2:L288,"OK") -> 198 | K5: =COUNTIF(Prospectos!L2:L288,"<>OK") -> 89
A8: ID | B8: Clase | C8: Empresa | D8: Categoría comercial | E8: Corredor | F8: Ciudad | G8: Teléfonos | H8: Preguntar por | I8: Necesidad probable | J8: Prioridad de visita | K8: Nota Dirección
A9: RT-054 | B9: =IFERROR(INDEX(Prospectos!$F$2:$F$288,MATCH($A9,Prospectos!$A$2:$A$288,0)),"") -> A | C9: =IFERROR(INDEX(Prospectos!$H$2:$H$288,MATCH($A9,Prospectos!$A$2:$A$288,0)),"") -> Ascanelli S.A. | D9: =IFERROR(INDEX(Prospectos!$J$2:$J$288,MATCH($A9,Prospectos!$A$2:$A$288,0)),"") -> Maquinaria agrícola | E9: =IFERROR(INDEX(Prospectos!$C$2:$C$288,MATCH($A9,Prospectos!$A$2:$A$288,0)),"") -> Base Río Tercero | F9: =IFERROR(INDEX(Prospectos!$E$2:$E$288,MATCH($A9,Prospectos!$A$2:$A$288,0)),"") -> Río Tercero | G9: =IFERROR(INDEX(Prospectos!$K$2:$K$288,MATCH($A9,Prospectos!$A$2:$A$288,0)),"") -> 03571 423691 | H9: =IFERROR(INDEX(Prospectos!$M$2:$M$288,MATCH($A9,Prospectos!$A$2:$A$288,0)),"") -> logística / ventas / postventa | I9: =IFERROR(INDEX(Prospectos!$N$2:$N$288,MATCH($A9,Prospectos!$A$2:$A$288,0)),"") -> Despacho de implementos, tolvas, sembradoras, estructuras, equipos terminados y componentes de gran porte hacia concesionarios, clientes, ferias o campo. | J9: =IFERROR(INDEX(Prospectos!$AJ$2:$AJ$288,MATCH($A9,Prospectos!$A$2:$A$288,0)),"") -> Muy alta | K9: SERGIO ASCANELLI
A10: RT-001 | B10: =IFERROR(INDEX(Prospectos!$F$2:$F$288,MATCH($A10,Prospectos!$A$2:$A$288,0)),"") -> A | C10: =IFERROR(INDEX(Prospectos!$H$2:$H$288,MATCH($A10,Prospectos!$A$2:$A$288,0)),"") -> Hormicor | D10: =IFERROR(INDEX(Prospectos!$J$2:$J$288,MATCH($A10,Prospectos!$A$2:$A$288,0)),"") -> Hormigón, áridos y materiales | E10: =IFERROR(INDEX(Prospectos!$C$2:$C$288,MATCH($A10,Prospectos!$A$2:$A$288,0)),"") -> Base Río Tercero | F10: =IFERROR(INDEX(Prospectos!$E$2:$E$288,MATCH($A10,Prospectos!$A$2:$A$288,0)),"") -> Río Tercero | G10: =IFERROR(INDEX(Prospectos!$K$2:$K$288,MATCH($A10,Prospectos!$A$2:$A$288,0)),"") -> 03571 500888 / 03571 510066 | H10: =IFERROR(INDEX(Prospectos!$M$2:$M$288,MATCH($A10,Prospectos!$A$2:$A$288,0)),"") -> planta / mantenimiento | I10: =IFERROR(INDEX(Prospectos!$N$2:$N$288,MATCH($A10,Prospectos!$A$2:$A$288,0)),"") -> Movimiento de premoldeados, equipos de planta/cantera, bombas, moldes y cargas pesadas. | J10: =IFERROR(INDEX(Prospectos!$AJ$2:$AJ$288,MATCH($A10,Prospectos!$A$2:$A$288,0)),"") -> Muy alta
A11: RT-002 | B11: =IFERROR(INDEX(Prospectos!$F$2:$F$288,MATCH($A11,Prospectos!$A$2:$A$288,0)),"") -> A | C11: =IFERROR(INDEX(Prospectos!$H$2:$H$288,MATCH($A11,Prospectos!$A$2:$A$288,0)),"") -> Metalúrgica Monticelli | D11: =IFERROR(INDEX(Prospectos!$J$2:$J$288,MATCH($A11,Prospectos!$A$2:$A$288,0)),"") -> Maquinaria agrícola | E11: =IFERROR(INDEX(Prospectos!$C$2:$C$288,MATCH($A11,Prospectos!$A$2:$A$288,0)),"") -> Base Río Tercero | F11: =IFERROR(INDEX(Prospectos!$E$2:$E$288,MATCH($A11,Prospectos!$A$2:$A$288,0)),"") -> Río Tercero | G11: =IFERROR(INDEX(Prospectos!$K$2:$K$288,MATCH($A11,Prospectos!$A$2:$A$288,0)),"") -> +54 3571 613058 / +54 3571 613060 | H11: =IFERROR(INDEX(Prospectos!$M$2:$M$288,MATCH($A11,Prospectos!$A$2:$A$288,0)),"") -> logística / despacho / postventa | I11: =IFERROR(INDEX(Prospectos!$N$2:$N$288,MATCH($A11,Prospectos!$A$2:$A$288,0)),"") -> Traslado de maquinaria, implementos, equipos terminados y componentes de gran porte entre planta, cliente, obra o feria. | J11: =IFERROR(INDEX(Prospectos!$AJ$2:$AJ$288,MATCH($A11,Prospectos!$A$2:$A$288,0)),"") -> Muy alta | K11: GUILLERMO GOÑI
A12: RT-003 | B12: =IFERROR(INDEX(Prospectos!$F$2:$F$288,MATCH($A12,Prospectos!$A$2:$A$288,0)),"") -> A | C12: =IFERROR(INDEX(Prospectos!$H$2:$H$288,MATCH($A12,Prospectos!$A$2:$A$288,0)),"") -> Metalúrgica Novaretti | D12: =IFERROR(INDEX(Prospectos!$J$2:$J$288,MATCH($A12,Prospectos!$A$2:$A$288,0)),"") -> Metalúrgica y fabricación | E12: =IFERROR(INDEX(Prospectos!$C$2:$C$288,MATCH($A12,Prospectos!$A$2:$A$288,0)),"") -> Base Río Tercero | F12: =IFERROR(INDEX(Prospectos!$E$2:$E$288,MATCH($A12,Prospectos!$A$2:$A$288,0)),"") -> Río Tercero | G12: =IFERROR(INDEX(Prospectos!$K$2:$K$288,MATCH($A12,Prospectos!$A$2:$A$288,0)),"") -> 03571 414282 / 03571 606930 | H12: =IFERROR(INDEX(Prospectos!$M$2:$M$288,MATCH($A12,Prospectos!$A$2:$A$288,0)),"") -> despacho / producción | I12: =IFERROR(INDEX(Prospectos!$N$2:$N$288,MATCH($A12,Prospectos!$A$2:$A$288,0)),"") -> Despacho seguro de estructuras, carrozados, tanques, piezas industriales y equipos sobre plataforma. | J12: =IFERROR(INDEX(Prospectos!$AJ$2:$AJ$288,MATCH($A12,Prospectos!$A$2:$A$288,0)),"") -> Muy alta | K12: CRISTIAN NOVARETTI
A13: RT-004 | B13: =IFERROR(INDEX(Prospectos!$F$2:$F$288,MATCH($A13,Prospectos!$A$2:$A$288,0)),"") -> A | C13: =IFERROR(INDEX(Prospectos!$H$2:$H$288,MATCH($A13,Prospectos!$A$2:$A$288,0)),"") -> Metalúrgica Río Tercero S.A. | D13: =IFERROR(INDEX(Prospectos!$J$2:$J$288,MATCH($A13,Prospectos!$A$2:$A$288,0)),"") -> Metalúrgica y fabricación | E13: =IFERROR(INDEX(Prospectos!$C$2:$C$288,MATCH($A13,Prospectos!$A$2:$A$288,0)),"") -> Base Río Tercero | F13: =IFERROR(INDEX(Prospectos!$E$2:$E$288,MATCH($A13,Prospectos!$A$2:$A$288,0)),"") -> Río Tercero | G13: =IFERROR(INDEX(Prospectos!$K$2:$K$288,MATCH($A13,Prospectos!$A$2:$A$288,0)),"") -> 03571 430558 | H13: =IFERROR(INDEX(Prospectos!$M$2:$M$288,MATCH($A13,Prospectos!$A$2:$A$288,0)),"") -> despacho / producción | I13: =IFERROR(INDEX(Prospectos!$N$2:$N$288,MATCH($A13,Prospectos!$A$2:$A$288,0)),"") -> Traslado de equipos de planta, silos, repuestos pesados, balanzas, implementos y cargas especiales. | J13: =IFERROR(INDEX(Prospectos!$AJ$2:$AJ$288,MATCH($A13,Prospectos!$A$2:$A$288,0)),"") -> Muy alta | K13: FEDE SERRA
A14: RT-005 | B14: =IFERROR(INDEX(Prospectos!$F$2:$F$288,MATCH($A14,Prospectos!$A$2:$A$288,0)),"") -> A | C14: =IFERROR(INDEX(Prospectos!$H$2:$H$288,MATCH($A14,Prospectos!$A$2:$A$288,0)),"") -> NT Construcciones | D14: =IFERROR(INDEX(Prospectos!$J$2:$J$288,MATCH($A14,Prospectos!$A$2:$A$288,0)),"") -> Construcción y obra vial | E14: =IFERROR(INDEX(Prospectos!$C$2:$C$288,MATCH($A14,Prospectos!$A$2:$A$288,0)),"") -> Base Río Tercero | F14: =IFERROR(INDEX(Prospectos!$E$2:$E$288,MATCH($A14,Prospectos!$A$2:$A$288,0)),"") -> Río Tercero | G14: =IFERROR(INDEX(Prospectos!$K$2:$K$288,MATCH($A14,Prospectos!$A$2:$A$288,0)),"") -> +54 9 3571 597645 | H14: =IFERROR(INDEX(Prospectos!$M$2:$M$288,MATCH($A14,Prospectos!$A$2:$A$288,0)),"") -> operaciones / jefe de obra | I14: =IFERROR(INDEX(Prospectos!$N$2:$N$288,MATCH($A14,Prospectos!$A$2:$A$288,0)),"") -> Traslado de maquinaria, módulos de obrador, estructuras, equipos y cargas pesadas entre frentes. | J14: =IFERROR(INDEX(Prospectos!$AJ$2:$AJ$288,MATCH($A14,Prospectos!$A$2:$A$288,0)),"") -> Muy alta
A15: RT-064 | B15: =IFERROR(INDEX(Prospectos!$F$2:$F$288,MATCH($A15,Prospectos!$A$2:$A$288,0)),"") -> A | C15: =IFERROR(INDEX(Prospectos!$H$2:$H$288,MATCH($A15,Prospectos!$A$2:$A$288,0)),"") -> SALA / Agrotecnología Sala — Río Tercero | D15: =IFERROR(INDEX(Prospectos!$J$2:$J$288,MATCH($A15,Prospectos!$A$2:$A$288,0)),"") -> Maquinaria agrícola | E15: =IFERROR(INDEX(Prospectos!$C$2:$C$288,MATCH($A15,Prospectos!$A$2:$A$288,0)),"") -> Base Río Tercero | F15: =IFERROR(INDEX(Prospectos!$E$2:$E$288,MATCH($A15,Prospectos!$A$2:$A$288,0)),"") -> Río Tercero | G15: =IFERROR(INDEX(Prospectos!$K$2:$K$288,MATCH($A15,Prospectos!$A$2:$A$288,0)),"") -> +54 9 358 4843387 | H15: =IFERROR(INDEX(Prospectos!$M$2:$M$288,MATCH($A15,Prospectos!$A$2:$A$288,0)),"") -> logística / entregas / usados / postventa / gerente comercial | I15: =IFERROR(INDEX(Prospectos!$N$2:$N$288,MATCH($A15,Prospectos!$A$2:$A$288,0)),"") -> Entrega y retiro de tractores, cosechadoras, pulverizadoras, sembradoras e implementos; movimientos por ventas, canjes, usados, service, demostraciones y ferias. | J15: =IFERROR(INDEX(Prospectos!$AJ$2:$AJ$288,MATCH($A15,Prospectos!$A$2:$A$288,0)),"") -> Muy alta
A16: RT-006 | B16: =IFERROR(INDEX(Prospectos!$F$2:$F$288,MATCH($A16,Prospectos!$A$2:$A$288,0)),"") -> A | C16: =IFERROR(INDEX(Prospectos!$H$2:$H$288,MATCH($A16,Prospectos!$A$2:$A$288,0)),"") -> Sinfix SAS | D16: =IFERROR(INDEX(Prospectos!$J$2:$J$288,MATCH($A16,Prospectos!$A$2:$A$288,0)),"") -> Metalúrgica y fabricación | E16: =IFERROR(INDEX(Prospectos!$C$2:$C$288,MATCH($A16,Prospectos!$A$2:$A$288,0)),"") -> Base Río Tercero | F16: =IFERROR(INDEX(Prospectos!$E$2:$E$288,MATCH($A16,Prospectos!$A$2:$A$288,0)),"") -> Río Tercero | G16: =IFERROR(INDEX(Prospectos!$K$2:$K$288,MATCH($A16,Prospectos!$A$2:$A$288,0)),"") -> +54 9 3571 405077 | H16: =IFERROR(INDEX(Prospectos!$M$2:$M$288,MATCH($A16,Prospectos!$A$2:$A$288,0)),"") -> despacho / producción | I16: =IFERROR(INDEX(Prospectos!$N$2:$N$288,MATCH($A16,Prospectos!$A$2:$A$288,0)),"") -> Despacho de estructuras, piezas, equipos y conjuntos metalmecánicos de gran porte hacia obras o clientes. | J16: =IFERROR(INDEX(Prospectos!$AJ$2:$AJ$288,MATCH($A16,Prospectos!$A$2:$A$288,0)),"") -> Muy alta
A17: RT-007 | B17: =IFERROR(INDEX(Prospectos!$F$2:$F$288,MATCH($A17,Prospectos!$A$2:$A$288,0)),"") -> A | C17: =IFERROR(INDEX(Prospectos!$H$2:$H$288,MATCH($A17,Prospectos!$A$2:$A$288,0)),"") -> Suragro - Implementos Agrícolas | D17: =IFERROR(INDEX(Prospectos!$J$2:$J$288,MATCH($A17,Prospectos!$A$2:$A$288,0)),"") -> Maquinaria agrícola | E17: =IFERROR(INDEX(Prospectos!$C$2:$C$288,MATCH($A17,Prospectos!$A$2:$A$288,0)),"") -> Base Río Tercero | F17: =IFERROR(INDEX(Prospectos!$E$2:$E$288,MATCH($A17,Prospectos!$A$2:$A$288,0)),"") -> Río Tercero | G17: =IFERROR(INDEX(Prospectos!$K$2:$K$288,MATCH($A17,Prospectos!$A$2:$A$288,0)),"") -> 03571 424574 | H17: =IFERROR(INDEX(Prospectos!$M$2:$M$288,MATCH($A17,Prospectos!$A$2:$A$288,0)),"") -> logística / despacho / postventa | I17: =IFERROR(INDEX(Prospectos!$N$2:$N$288,MATCH($A17,Prospectos!$A$2:$A$288,0)),"") -> Traslado de maquinaria, implementos, equipos terminados y componentes de gran porte entre planta, cliente, obra o feria. | J17: =IFERROR(INDEX(Prospectos!$AJ$2:$AJ$288,MATCH($A17,Prospectos!$A$2:$A$288,0)),"") -> Muy alta
A18: RT-008 | B18: =IFERROR(INDEX(Prospectos!$F$2:$F$288,MATCH($A18,Prospectos!$A$2:$A$288,0)),"") -> A | C18: =IFERROR(INDEX(Prospectos!$H$2:$H$288,MATCH($A18,Prospectos!$A$2:$A$288,0)),"") -> Tres Eme S.A. | D18: =IFERROR(INDEX(Prospectos!$J$2:$J$288,MATCH($A18,Prospectos!$A$2:$A$288,0)),"") -> Agro, acopio y cooperativas | E18: =IFERROR(INDEX(Prospectos!$C$2:$C$288,MATCH($A18,Prospectos!$A$2:$A$288,0)),"") -> Base Río Tercero | F18: =IFERROR(INDEX(Prospectos!$E$2:$E$288,MATCH($A18,Prospectos!$A$2:$A$288,0)),"") -> Río Tercero | G18: =IFERROR(INDEX(Prospectos!$K$2:$K$288,MATCH($A18,Prospectos!$A$2:$A$288,0)),"") -> 03571 432190 / 03571 637720 | H18: =IFERROR(INDEX(Prospectos!$M$2:$M$288,MATCH($A18,Prospectos!$A$2:$A$288,0)),"") -> responsable de acopio / mantenimiento | I18: =IFERROR(INDEX(Prospectos!$N$2:$N$288,MATCH($A18,Prospectos!$A$2:$A$288,0)),"") -> Traslado de equipos de planta, silos, repuestos pesados, balanzas, implementos y cargas especiales. | J18: =IFERROR(INDEX(Prospectos!$AJ$2:$AJ$288,MATCH($A18,Prospectos!$A$2:$A$288,0)),"") -> Muy alta | K18: MATI MENGO
A19: RT-009 | B19: =IFERROR(INDEX(Prospectos!$F$2:$F$288,MATCH($A19,Prospectos!$A$2:$A$288,0)),"") -> A | C19: =IFERROR(INDEX(Prospectos!$H$2:$H$288,MATCH($A19,Prospectos!$A$2:$A$288,0)),"") -> Vial del Centro | D19: =IFERROR(INDEX(Prospectos!$J$2:$J$288,MATCH($A19,Prospectos!$A$2:$A$288,0)),"") -> Construcción y obra vial | E19: =IFERROR(INDEX(Prospectos!$C$2:$C$288,MATCH($A19,Prospectos!$A$2:$A$288,0)),"") -> Base Río Tercero | F19: =IFERROR(INDEX(Prospectos!$E$2:$E$288,MATCH($A19,Prospectos!$A$2:$A$288,0)),"") -> Río Tercero | G19: =IFERROR(INDEX(Prospectos!$K$2:$K$288,MATCH($A19,Prospectos!$A$2:$A$288,0)),"") -> 0351 6411413 | H19: =IFERROR(INDEX(Prospectos!$M$2:$M$288,MATCH($A19,Prospectos!$A$2:$A$288,0)),"") -> operaciones / entregas | I19: =IFERROR(INDEX(Prospectos!$N$2:$N$288,MATCH($A19,Prospectos!$A$2:$A$288,0)),"") -> Traslado de maquinaria, módulos de obrador, estructuras, equipos y cargas pesadas entre frentes. | J19: =IFERROR(INDEX(Prospectos!$AJ$2:$AJ$288,MATCH($A19,Prospectos!$A$2:$A$288,0)),"") -> Muy alta
A20: RT-010 | B20: =IFERROR(INDEX(Prospectos!$F$2:$F$288,MATCH($A20,Prospectos!$A$2:$A$288,0)),"") -> A | C20: =IFERROR(INDEX(Prospectos!$H$2:$H$288,MATCH($A20,Prospectos!$A$2:$A$288,0)),"") -> HORMIWORK S.A. | D20: =IFERROR(INDEX(Prospectos!$J$2:$J$288,MATCH($A20,Prospectos!$A$2:$A$288,0)),"") -> Hormigón, áridos y materiales | E20: =IFERROR(INDEX(Prospectos!$C$2:$C$288,MATCH($A20,Prospectos!$A$2:$A$288,0)),"") -> Base Río Tercero | F20: =IFERROR(INDEX(Prospectos!$E$2:$E$288,MATCH($A20,Prospectos!$A$2:$A$288,0)),"") -> Río Tercero | G20: =IFERROR(INDEX(Prospectos!$K$2:$K$288,MATCH($A20,Prospectos!$A$2:$A$288,0)),"") -> 03571 565662 (portería parque) | H20: =IFERROR(INDEX(Prospectos!$M$2:$M$288,MATCH($A20,Prospectos!$A$2:$A$288,0)),"") -> planta / despacho | I20: =IFERROR(INDEX(Prospectos!$N$2:$N$288,MATCH($A20,Prospectos!$A$2:$A$288,0)),"") -> Movimiento de premoldeados, moldes, equipos de planta y cargas pesadas asociadas a obra. | J20: =IFERROR(INDEX(Prospectos!$AJ$2:$AJ$288,MATCH($A20,Prospectos!$A$2:$A$288,0)),"") -> Alta
A21: RT-062 | B21: =IFERROR(INDEX(Prospectos!$F$2:$F$288,MATCH($A21,Prospectos!$A$2:$A$288,0)),"") -> A | C21: =IFERROR(INDEX(Prospectos!$H$2:$H$288,MATCH($A21,Prospectos!$A$2:$A$288,0)),"") -> Bartolomé Cerutti SRL — Río Tercero | D21: =IFERROR(INDEX(Prospectos!$J$2:$J$288,MATCH($A21,Prospectos!$A$2:$A$288,0)),"") -> Maquinaria agrícola | E21: =IFERROR(INDEX(Prospectos!$C$2:$C$288,MATCH($A21,Prospectos!$A$2:$A$288,0)),"") -> Base Río Tercero | F21: =IFERROR(INDEX(Prospectos!$E$2:$E$288,MATCH($A21,Prospectos!$A$2:$A$288,0)),"") -> Río Tercero | G21: =IFERROR(INDEX(Prospectos!$K$2:$K$288,MATCH($A21,Prospectos!$A$2:$A$288,0)),"") -> 03571 644022 | H21: =IFERROR(INDEX(Prospectos!$M$2:$M$288,MATCH($A21,Prospectos!$A$2:$A$288,0)),"") -> logística / ventas / postventa | I21: =IFERROR(INDEX(Prospectos!$N$2:$N$288,MATCH($A21,Prospectos!$A$2:$A$288,0)),"") -> Entrega y retiro de tractores, cosechadoras, pulverizadoras, sembradoras e implementos; movimientos por venta, service, canje, demostraciones o ferias. | J21: =IFERROR(INDEX(Prospectos!$AJ$2:$AJ$288,MATCH($A21,Prospectos!$A$2:$A$288,0)),"") -> Muy alta
A22: RT-055 | B22: =IFERROR(INDEX(Prospectos!$F$2:$F$288,MATCH($A22,Prospectos!$A$2:$A$288,0)),"") -> A | C22: =IFERROR(INDEX(Prospectos!$H$2:$H$288,MATCH($A22,Prospectos!$A$2:$A$288,0)),"") -> Conax | D22: =IFERROR(INDEX(Prospectos!$J$2:$J$288,MATCH($A22,Prospectos!$A$2:$A$288,0)),"") -> Maquinaria agrícola | E22: =IFERROR(INDEX(Prospectos!$C$2:$C$288,MATCH($A22,Prospectos!$A$2:$A$288,0)),"") -> Base Río Tercero | F22: =IFERROR(INDEX(Prospectos!$E$2:$E$288,MATCH($A22,Prospectos!$A$2:$A$288,0)),"") -> Río Tercero | G22: =IFERROR(INDEX(Prospectos!$K$2:$K$288,MATCH($A22,Prospectos!$A$2:$A$288,0)),"") -> +54 3571 348077 | H22: =IFERROR(INDEX(Prospectos!$M$2:$M$288,MATCH($A22,Prospectos!$A$2:$A$288,0)),"") -> logística / ventas / postventa | I22: =IFERROR(INDEX(Prospectos!$N$2:$N$288,MATCH($A22,Prospectos!$A$2:$A$288,0)),"") -> Entrega y retiro de tractores, cosechadoras, pulverizadoras, sembradoras e implementos; movimientos por venta, service, canje, demostraciones o ferias. | J22: =IFERROR(INDEX(Prospectos!$AJ$2:$AJ$288,MATCH($A22,Prospectos!$A$2:$A$288,0)),"") -> Muy alta | K22: GASPAR LOPEZ
A23: RT-056 | B23: =IFERROR(INDEX(Prospectos!$F$2:$F$288,MATCH($A23,Prospectos!$A$2:$A$288,0)),"") -> A | C23: =IFERROR(INDEX(Prospectos!$H$2:$H$288,MATCH($A23,Prospectos!$A$2:$A$288,0)),"") -> RSA Repuestos y Servicios | D23: =IFERROR(INDEX(Prospectos!$J$2:$J$288,MATCH($A23,Prospectos!$A$2:$A$288,0)),"") -> Maquinaria agrícola | E23: =IFERROR(INDEX(Prospectos!$C$2:$C$288,MATCH($A23,Prospectos!$A$2:$A$288,0)),"") -> Base Río Tercero | F23: =IFERROR(INDEX(Prospectos!$E$2:$E$288,MATCH($A23,Prospectos!$A$2:$A$288,0)),"") -> Río Tercero | G23: =IFERROR(INDEX(Prospectos!$K$2:$K$288,MATCH($A23,Prospectos!$A$2:$A$288,0)),"") -> +54 9 3571 538080 / +54 9 3571 578870 | H23: =IFERROR(INDEX(Prospectos!$M$2:$M$288,MATCH($A23,Prospectos!$A$2:$A$288,0)),"") -> logística / ventas / postventa | I23: =IFERROR(INDEX(Prospectos!$N$2:$N$288,MATCH($A23,Prospectos!$A$2:$A$288,0)),"") -> Entrega y retiro de tractores, cosechadoras, pulverizadoras, sembradoras e implementos; movimientos por venta, service, canje, demostraciones o ferias. | J23: =IFERROR(INDEX(Prospectos!$AJ$2:$AJ$288,MATCH($A23,Prospectos!$A$2:$A$288,0)),"") -> Muy alta
A24: RT-057 | B24: =IFERROR(INDEX(Prospectos!$F$2:$F$288,MATCH($A24,Prospectos!$A$2:$A$288,0)),"") -> A | C24: =IFERROR(INDEX(Prospectos!$H$2:$H$288,MATCH($A24,Prospectos!$A$2:$A$288,0)),"") -> Viejo Tala S.R.L. — Río Tercero | D24: =IFERROR(INDEX(Prospectos!$J$2:$J$288,MATCH($A24,Prospectos!$A$2:$A$288,0)),"") -> Maquinaria agrícola | E24: =IFERROR(INDEX(Prospectos!$C$2:$C$288,MATCH($A24,Prospectos!$A$2:$A$288,0)),"") -> Base Río Tercero | F24: =IFERROR(INDEX(Prospectos!$E$2:$E$288,MATCH($A24,Prospectos!$A$2:$A$288,0)),"") -> Río Tercero | G24: =IFERROR(INDEX(Prospectos!$K$2:$K$288,MATCH($A24,Prospectos!$A$2:$A$288,0)),"") -> 03571 643332 / +54 9 353 4221837 | H24: =IFERROR(INDEX(Prospectos!$M$2:$M$288,MATCH($A24,Prospectos!$A$2:$A$288,0)),"") -> logística / ventas / postventa | I24: =IFERROR(INDEX(Prospectos!$N$2:$N$288,MATCH($A24,Prospectos!$A$2:$A$288,0)),"") -> Entrega y retiro de tractores, cosechadoras, pulverizadoras, sembradoras e implementos; movimientos por venta, service, canje, demostraciones o ferias. | J24: =IFERROR(INDEX(Prospectos!$AJ$2:$AJ$288,MATCH($A24,Prospectos!$A$2:$A$288,0)),"") -> Muy alta | K24: VISTOR SEIA (HERNANDO) WALTER PAYOLA (RIO 3)
A25: RT-065 | B25: =IFERROR(INDEX(Prospectos!$F$2:$F$288,MATCH($A25,Prospectos!$A$2:$A$288,0)),"") -> A | C25: =IFERROR(INDEX(Prospectos!$H$2:$H$288,MATCH($A25,Prospectos!$A$2:$A$288,0)),"") -> Rino Maquinaria | D25: =IFERROR(INDEX(Prospectos!$J$2:$J$288,MATCH($A25,Prospectos!$A$2:$A$288,0)),"") -> Maquinaria agrícola | E25: =IFERROR(INDEX(Prospectos!$C$2:$C$288,MATCH($A25,Prospectos!$A$2:$A$288,0)),"") -> Base Río Tercero | F25: =IFERROR(INDEX(Prospectos!$E$2:$E$288,MATCH($A25,Prospectos!$A$2:$A$288,0)),"") -> Río Tercero | G25: =IFERROR(INDEX(Prospectos!$K$2:$K$288,MATCH($A25,Prospectos!$A$2:$A$288,0)),"") -> +54 9 3571 681323 | H25: =IFERROR(INDEX(Prospectos!$M$2:$M$288,MATCH($A25,Prospectos!$A$2:$A$288,0)),"") -> logística / entregas / usados / postventa / gerente comercial | I25: =IFERROR(INDEX(Prospectos!$N$2:$N$288,MATCH($A25,Prospectos!$A$2:$A$288,0)),"") -> Entrega y retiro de tractores, cosechadoras, pulverizadoras, sembradoras e implementos; movimientos por ventas, canjes, usados, service, demostraciones y ferias. | J25: =IFERROR(INDEX(Prospectos!$AJ$2:$AJ$288,MATCH($A25,Prospectos!$A$2:$A$288,0)),"") -> Alta
A26: RT-011 | B26: =IFERROR(INDEX(Prospectos!$F$2:$F$288,MATCH($A26,Prospectos!$A$2:$A$288,0)),"") -> A | C26: =IFERROR(INDEX(Prospectos!$H$2:$H$288,MATCH($A26,Prospectos!$A$2:$A$288,0)),"") -> Alpha Construcciones Industriales S.A. | D26: =IFERROR(INDEX(Prospectos!$J$2:$J$288,MATCH($A26,Prospectos!$A$2:$A$288,0)),"") -> Construcción y obra vial | E26: =IFERROR(INDEX(Prospectos!$C$2:$C$288,MATCH($A26,Prospectos!$A$2:$A$288,0)),"") -> Base Río Tercero | F26: =IFERROR(INDEX(Prospectos!$E$2:$E$288,MATCH($A26,Prospectos!$A$2:$A$288,0)),"") -> Río Tercero | G26: =IFERROR(INDEX(Prospectos!$K$2:$K$288,MATCH($A26,Prospectos!$A$2:$A$288,0)),"") -> A relevar | H26: =IFERROR(INDEX(Prospectos!$M$2:$M$288,MATCH($A26,Prospectos!$A$2:$A$288,0)),"") -> jefe de obra / operaciones | I26: =IFERROR(INDEX(Prospectos!$N$2:$N$288,MATCH($A26,Prospectos!$A$2:$A$288,0)),"") -> Traslado de maquinaria, módulos de obrador, estructuras y equipos entre depósitos y frentes de obra. | J26: =IFERROR(INDEX(Prospectos!$AJ$2:$AJ$288,MATCH($A26,Prospectos!$A$2:$A$288,0)),"") -> Alta
A27: RT-012 | B27: =IFERROR(INDEX(Prospectos!$F$2:$F$288,MATCH($A27,Prospectos!$A$2:$A$288,0)),"") -> A | C27: =IFERROR(INDEX(Prospectos!$H$2:$H$288,MATCH($A27,Prospectos!$A$2:$A$288,0)),"") -> Caon - Concesionario Oficial CASE IH | D27: =IFERROR(INDEX(Prospectos!$J$2:$J$288,MATCH($A27,Prospectos!$A$2:$A$288,0)),"") -> Maquinaria agrícola | E27: =IFERROR(INDEX(Prospectos!$C$2:$C$288,MATCH($A27,Prospectos!$A$2:$A$288,0)),"") -> Base Río Tercero | F27: =IFERROR(INDEX(Prospectos!$E$2:$E$288,MATCH($A27,Prospectos!$A$2:$A$288,0)),"") -> Río Tercero | G27: =IFERROR(INDEX(Prospectos!$K$2:$K$288,MATCH($A27,Prospectos!$A$2:$A$288,0)),"") -> 03571 682141 | H27: =IFERROR(INDEX(Prospectos!$M$2:$M$288,MATCH($A27,Prospectos!$A$2:$A$288,0)),"") -> logística / entregas / postventa | I27: =IFERROR(INDEX(Prospectos!$N$2:$N$288,MATCH($A27,Prospectos!$A$2:$A$288,0)),"") -> Traslado de maquinaria agrícola o vial entre sucursal, cliente, taller, campo y eventos. | J27: =IFERROR(INDEX(Prospectos!$AJ$2:$AJ$288,MATCH($A27,Prospectos!$A$2:$A$288,0)),"") -> Muy alta
A28: RT-013 | B28: =IFERROR(INDEX(Prospectos!$F$2:$F$288,MATCH($A28,Prospectos!$A$2:$A$288,0)),"") -> A | C28: =IFERROR(INDEX(Prospectos!$H$2:$H$288,MATCH($A28,Prospectos!$A$2:$A$288,0)),"") -> Cimat SRL | D28: =IFERROR(INDEX(Prospectos!$J$2:$J$288,MATCH($A28,Prospectos!$A$2:$A$288,0)),"") -> Maquinaria agrícola | E28: =IFERROR(INDEX(Prospectos!$C$2:$C$288,MATCH($A28,Prospectos!$A$2:$A$288,0)),"") -> Base Río Tercero | F28: =IFERROR(INDEX(Prospectos!$E$2:$E$288,MATCH($A28,Prospectos!$A$2:$A$288,0)),"") -> Río Tercero | G28: =IFERROR(INDEX(Prospectos!$K$2:$K$288,MATCH($A28,Prospectos!$A$2:$A$288,0)),"") -> 03571 422153 | H28: =IFERROR(INDEX(Prospectos!$M$2:$M$288,MATCH($A28,Prospectos!$A$2:$A$288,0)),"") -> logística / entregas / postventa | I28: =IFERROR(INDEX(Prospectos!$N$2:$N$288,MATCH($A28,Prospectos!$A$2:$A$288,0)),"") -> Traslado de maquinaria agrícola o vial entre sucursal, cliente, taller, campo y eventos. | J28: =IFERROR(INDEX(Prospectos!$AJ$2:$AJ$288,MATCH($A28,Prospectos!$A$2:$A$288,0)),"") -> Muy alta | K28: RAUL ARUTA
A29: RT-014 | B29: =IFERROR(INDEX(Prospectos!$F$2:$F$288,MATCH($A29,Prospectos!$A$2:$A$288,0)),"") -> A | C29: =IFERROR(INDEX(Prospectos!$H$2:$H$288,MATCH($A29,Prospectos!$A$2:$A$288,0)),"") -> D & M ESTRUCTURAS | D29: =IFERROR(INDEX(Prospectos!$J$2:$J$288,MATCH($A29,Prospectos!$A$2:$A$288,0)),"") -> Metalúrgica y fabricación | E29: =IFERROR(INDEX(Prospectos!$C$2:$C$288,MATCH($A29,Prospectos!$A$2:$A$288,0)),"") -> Base Río Tercero | F29: =IFERROR(INDEX(Prospectos!$E$2:$E$288,MATCH($A29,Prospectos!$A$2:$A$288,0)),"") -> Río Tercero | G29: =IFERROR(INDEX(Prospectos!$K$2:$K$288,MATCH($A29,Prospectos!$A$2:$A$288,0)),"") -> A relevar | H29: =IFERROR(INDEX(Prospectos!$M$2:$M$288,MATCH($A29,Prospectos!$A$2:$A$288,0)),"") -> despacho / producción | I29: =IFERROR(INDEX(Prospectos!$N$2:$N$288,MATCH($A29,Prospectos!$A$2:$A$288,0)),"") -> Despacho de estructuras, piezas, equipos y conjuntos metalmecánicos de gran porte hacia obras o clientes. | J29: =IFERROR(INDEX(Prospectos!$AJ$2:$AJ$288,MATCH($A29,Prospectos!$A$2:$A$288,0)),"") -> Alta | K29: PABLO PONCETI
A30: RT-015 | B30: =IFERROR(INDEX(Prospectos!$F$2:$F$288,MATCH($A30,Prospectos!$A$2:$A$288,0)),"") -> A | C30: =IFERROR(INDEX(Prospectos!$H$2:$H$288,MATCH($A30,Prospectos!$A$2:$A$288,0)),"") -> Duter S.A. | D30: =IFERROR(INDEX(Prospectos!$J$2:$J$288,MATCH($A30,Prospectos!$A$2:$A$288,0)),"") -> Maquinaria agrícola | E30: =IFERROR(INDEX(Prospectos!$C$2:$C$288,MATCH($A30,Prospectos!$A$2:$A$288,0)),"") -> Base Río Tercero | F30: =IFERROR(INDEX(Prospectos!$E$2:$E$288,MATCH($A30,Prospectos!$A$2:$A$288,0)),"") -> Río Tercero | G30: =IFERROR(INDEX(Prospectos!$K$2:$K$288,MATCH($A30,Prospectos!$A$2:$A$288,0)),"") -> 03571 565177 | H30: =IFERROR(INDEX(Prospectos!$M$2:$M$288,MATCH($A30,Prospectos!$A$2:$A$288,0)),"") -> logística / despacho / postventa | I30: =IFERROR(INDEX(Prospectos!$N$2:$N$288,MATCH($A30,Prospectos!$A$2:$A$288,0)),"") -> Traslado de maquinaria, implementos, equipos terminados y componentes de gran porte entre planta, cliente, obra o feria. | J30: =IFERROR(INDEX(Prospectos!$AJ$2:$AJ$288,MATCH($A30,Prospectos!$A$2:$A$288,0)),"") -> Muy alta
A31: RT-016 | B31: =IFERROR(INDEX(Prospectos!$F$2:$F$288,MATCH($A31,Prospectos!$A$2:$A$288,0)),"") -> A | C31: =IFERROR(INDEX(Prospectos!$H$2:$H$288,MATCH($A31,Prospectos!$A$2:$A$288,0)),"") -> ESISA | D31: =IFERROR(INDEX(Prospectos!$J$2:$J$288,MATCH($A31,Prospectos!$A$2:$A$288,0)),"") -> Módulos y contenedores | E31: =IFERROR(INDEX(Prospectos!$C$2:$C$288,MATCH($A31,Prospectos!$A$2:$A$288,0)),"") -> Base Río Tercero | F31: =IFERROR(INDEX(Prospectos!$E$2:$E$288,MATCH($A31,Prospectos!$A$2:$A$288,0)),"") -> Río Tercero | G31: =IFERROR(INDEX(Prospectos!$K$2:$K$288,MATCH($A31,Prospectos!$A$2:$A$288,0)),"") -> Portería parque: 03571 565662; mail esisaservicios@gmail.com | H31: =IFERROR(INDEX(Prospectos!$M$2:$M$288,MATCH($A31,Prospectos!$A$2:$A$288,0)),"") -> operaciones / entregas | I31: =IFERROR(INDEX(Prospectos!$N$2:$N$288,MATCH($A31,Prospectos!$A$2:$A$288,0)),"") -> Entrega, descarga y posicionamiento de módulos/containers en obra o cliente final. | J31: =IFERROR(INDEX(Prospectos!$AJ$2:$AJ$288,MATCH($A31,Prospectos!$A$2:$A$288,0)),"") -> Muy alta
A32: RT-017 | B32: =IFERROR(INDEX(Prospectos!$F$2:$F$288,MATCH($A32,Prospectos!$A$2:$A$288,0)),"") -> A | C32: =IFERROR(INDEX(Prospectos!$H$2:$H$288,MATCH($A32,Prospectos!$A$2:$A$288,0)),"") -> ISECO Construcción | D32: =IFERROR(INDEX(Prospectos!$J$2:$J$288,MATCH($A32,Prospectos!$A$2:$A$288,0)),"") -> Construcción y obra vial | E32: =IFERROR(INDEX(Prospectos!$C$2:$C$288,MATCH($A32,Prospectos!$A$2:$A$288,0)),"") -> Base Río Tercero | F32: =IFERROR(INDEX(Prospectos!$E$2:$E$288,MATCH($A32,Prospectos!$A$2:$A$288,0)),"") -> Río Tercero | G32: =IFERROR(INDEX(Prospectos!$K$2:$K$288,MATCH($A32,Prospectos!$A$2:$A$288,0)),"") -> +54 9 3571 551917 | H32: =IFERROR(INDEX(Prospectos!$M$2:$M$288,MATCH($A32,Prospectos!$A$2:$A$288,0)),"") -> jefe de obra / operaciones | I32: =IFERROR(INDEX(Prospectos!$N$2:$N$288,MATCH($A32,Prospectos!$A$2:$A$288,0)),"") -> Traslado de maquinaria, módulos de obrador, estructuras y equipos entre depósitos y frentes de obra. | J32: =IFERROR(INDEX(Prospectos!$AJ$2:$AJ$288,MATCH($A32,Prospectos!$A$2:$A$288,0)),"") -> Muy alta | K32: BETO
A33: RT-018 | B33: =IFERROR(INDEX(Prospectos!$F$2:$F$288,MATCH($A33,Prospectos!$A$2:$A$288,0)),"") -> A | C33: =IFERROR(INDEX(Prospectos!$H$2:$H$288,MATCH($A33,Prospectos!$A$2:$A$288,0)),"") -> Luzenti Hnos S.A. | D33: =IFERROR(INDEX(Prospectos!$J$2:$J$288,MATCH($A33,Prospectos!$A$2:$A$288,0)),"") -> Construcción y obra vial | E33: =IFERROR(INDEX(Prospectos!$C$2:$C$288,MATCH($A33,Prospectos!$A$2:$A$288,0)),"") -> Base Río Tercero | F33: =IFERROR(INDEX(Prospectos!$E$2:$E$288,MATCH($A33,Prospectos!$A$2:$A$288,0)),"") -> Río Tercero | G33: =IFERROR(INDEX(Prospectos!$K$2:$K$288,MATCH($A33,Prospectos!$A$2:$A$288,0)),"") -> 03584 860532 | H33: =IFERROR(INDEX(Prospectos!$M$2:$M$288,MATCH($A33,Prospectos!$A$2:$A$288,0)),"") -> jefe de obra / operaciones | I33: =IFERROR(INDEX(Prospectos!$N$2:$N$288,MATCH($A33,Prospectos!$A$2:$A$288,0)),"") -> Traslado de maquinaria, módulos de obrador, estructuras y equipos entre depósitos y frentes de obra. | J33: =IFERROR(INDEX(Prospectos!$AJ$2:$AJ$288,MATCH($A33,Prospectos!$A$2:$A$288,0)),"") -> Muy alta | K33: JORGE LUCENTI
A34: RT-019 | B34: =IFERROR(INDEX(Prospectos!$F$2:$F$288,MATCH($A34,Prospectos!$A$2:$A$288,0)),"") -> A | C34: =IFERROR(INDEX(Prospectos!$H$2:$H$288,MATCH($A34,Prospectos!$A$2:$A$288,0)),"") -> NEMETAL S.A.S | D34: =IFERROR(INDEX(Prospectos!$J$2:$J$288,MATCH($A34,Prospectos!$A$2:$A$288,0)),"") -> Maquinaria agrícola | E34: =IFERROR(INDEX(Prospectos!$C$2:$C$288,MATCH($A34,Prospectos!$A$2:$A$288,0)),"") -> Base Río Tercero | F34: =IFERROR(INDEX(Prospectos!$E$2:$E$288,MATCH($A34,Prospectos!$A$2:$A$288,0)),"") -> Río Tercero | G34: =IFERROR(INDEX(Prospectos!$K$2:$K$288,MATCH($A34,Prospectos!$A$2:$A$288,0)),"") -> 03571 550608 | H34: =IFERROR(INDEX(Prospectos!$M$2:$M$288,MATCH($A34,Prospectos!$A$2:$A$288,0)),"") -> despacho / producción | I34: =IFERROR(INDEX(Prospectos!$N$2:$N$288,MATCH($A34,Prospectos!$A$2:$A$288,0)),"") -> Despacho de estructuras, piezas, equipos y conjuntos metalmecánicos de gran porte hacia obras o clientes. | J34: =IFERROR(INDEX(Prospectos!$AJ$2:$AJ$288,MATCH($A34,Prospectos!$A$2:$A$288,0)),"") -> Muy alta
A35: RT-058 | B35: =IFERROR(INDEX(Prospectos!$F$2:$F$288,MATCH($A35,Prospectos!$A$2:$A$288,0)),"") -> A | C35: =IFERROR(INDEX(Prospectos!$H$2:$H$288,MATCH($A35,Prospectos!$A$2:$A$288,0)),"") -> Paulucci Máquinas Agrícolas | D35: =IFERROR(INDEX(Prospectos!$J$2:$J$288,MATCH($A35,Prospectos!$A$2:$A$288,0)),"") -> Maquinaria agrícola | E35: =IFERROR(INDEX(Prospectos!$C$2:$C$288,MATCH($A35,Prospectos!$A$2:$A$288,0)),"") -> Base Río Tercero | F35: =IFERROR(INDEX(Prospectos!$E$2:$E$288,MATCH($A35,Prospectos!$A$2:$A$288,0)),"") -> Río Tercero | G35: =IFERROR(INDEX(Prospectos!$K$2:$K$288,MATCH($A35,Prospectos!$A$2:$A$288,0)),"") -> 03571 424384 | H35: =IFERROR(INDEX(Prospectos!$M$2:$M$288,MATCH($A35,Prospectos!$A$2:$A$288,0)),"") -> logística / ventas / postventa | I35: =IFERROR(INDEX(Prospectos!$N$2:$N$288,MATCH($A35,Prospectos!$A$2:$A$288,0)),"") -> Entrega y retiro de tractores, cosechadoras, pulverizadoras, sembradoras e implementos; movimientos por venta, service, canje, demostraciones o ferias. | J35: =IFERROR(INDEX(Prospectos!$AJ$2:$AJ$288,MATCH($A35,Prospectos!$A$2:$A$288,0)),"") -> Alta | K35: WALTER PAULUCCI
A36: RT-059 | B36: =IFERROR(INDEX(Prospectos!$F$2:$F$288,MATCH($A36,Prospectos!$A$2:$A$288,0)),"") -> A | C36: =IFERROR(INDEX(Prospectos!$H$2:$H$288,MATCH($A36,Prospectos!$A$2:$A$288,0)),"") -> SAEMMA | D36: =IFERROR(INDEX(Prospectos!$J$2:$J$288,MATCH($A36,Prospectos!$A$2:$A$288,0)),"") -> Maquinaria agrícola | E36: =IFERROR(INDEX(Prospectos!$C$2:$C$288,MATCH($A36,Prospectos!$A$2:$A$288,0)),"") -> Base Río Tercero | F36: =IFERROR(INDEX(Prospectos!$E$2:$E$288,MATCH($A36,Prospectos!$A$2:$A$288,0)),"") -> Río Tercero | G36: =IFERROR(INDEX(Prospectos!$K$2:$K$288,MATCH($A36,Prospectos!$A$2:$A$288,0)),"") -> 03571 432338 | H36: =IFERROR(INDEX(Prospectos!$M$2:$M$288,MATCH($A36,Prospectos!$A$2:$A$288,0)),"") -> logística / ventas / postventa | I36: =IFERROR(INDEX(Prospectos!$N$2:$N$288,MATCH($A36,Prospectos!$A$2:$A$288,0)),"") -> Entrega y retiro de tractores, cosechadoras, pulverizadoras, sembradoras e implementos; movimientos por venta, service, canje, demostraciones o ferias. | J36: =IFERROR(INDEX(Prospectos!$AJ$2:$AJ$288,MATCH($A36,Prospectos!$A$2:$A$288,0)),"") -> Alta
A37: RT-020 | B37: =IFERROR(INDEX(Prospectos!$F$2:$F$288,MATCH($A37,Prospectos!$A$2:$A$288,0)),"") -> A | C37: =IFERROR(INDEX(Prospectos!$H$2:$H$288,MATCH($A37,Prospectos!$A$2:$A$288,0)),"") -> Sclauzero Metalúrgica | D37: =IFERROR(INDEX(Prospectos!$J$2:$J$288,MATCH($A37,Prospectos!$A$2:$A$288,0)),"") -> Metalúrgica y fabricación | E37: =IFERROR(INDEX(Prospectos!$C$2:$C$288,MATCH($A37,Prospectos!$A$2:$A$288,0)),"") -> Base Río Tercero | F37: =IFERROR(INDEX(Prospectos!$E$2:$E$288,MATCH($A37,Prospectos!$A$2:$A$288,0)),"") -> Río Tercero | G37: =IFERROR(INDEX(Prospectos!$K$2:$K$288,MATCH($A37,Prospectos!$A$2:$A$288,0)),"") -> 03571 414014 | H37: =IFERROR(INDEX(Prospectos!$M$2:$M$288,MATCH($A37,Prospectos!$A$2:$A$288,0)),"") -> despacho / producción | I37: =IFERROR(INDEX(Prospectos!$N$2:$N$288,MATCH($A37,Prospectos!$A$2:$A$288,0)),"") -> Despacho de estructuras, piezas, equipos y conjuntos metalmecánicos de gran porte hacia obras o clientes. | J37: =IFERROR(INDEX(Prospectos!$AJ$2:$AJ$288,MATCH($A37,Prospectos!$A$2:$A$288,0)),"") -> Muy alta | K37: GUILLERMO SCLAUSERO
A38: RT-060 | B38: =IFERROR(INDEX(Prospectos!$F$2:$F$288,MATCH($A38,Prospectos!$A$2:$A$288,0)),"") -> A | C38: =IFERROR(INDEX(Prospectos!$H$2:$H$288,MATCH($A38,Prospectos!$A$2:$A$288,0)),"") -> Barrax Argentina S.A. | D38: =IFERROR(INDEX(Prospectos!$J$2:$J$288,MATCH($A38,Prospectos!$A$2:$A$288,0)),"") -> Maquinaria agrícola | E38: =IFERROR(INDEX(Prospectos!$C$2:$C$288,MATCH($A38,Prospectos!$A$2:$A$288,0)),"") -> Base Río Tercero | F38: =IFERROR(INDEX(Prospectos!$E$2:$E$288,MATCH($A38,Prospectos!$A$2:$A$288,0)),"") -> Río Tercero | G38: =IFERROR(INDEX(Prospectos!$K$2:$K$288,MATCH($A38,Prospectos!$A$2:$A$288,0)),"") -> 03571 421774 / 03571 420576 | H38: =IFERROR(INDEX(Prospectos!$M$2:$M$288,MATCH($A38,Prospectos!$A$2:$A$288,0)),"") -> logística / ventas / postventa | I38: =IFERROR(INDEX(Prospectos!$N$2:$N$288,MATCH($A38,Prospectos!$A$2:$A$288,0)),"") -> Movimiento de agropartes, repuestos pesados, conjuntos y eventualmente implementos/equipos entre planta, concesionarios y clientes. | J38: =IFERROR(INDEX(Prospectos!$AJ$2:$AJ$288,MATCH($A38,Prospectos!$A$2:$A$288,0)),"") -> Alta
A39: RT-021 | B39: =IFERROR(INDEX(Prospectos!$F$2:$F$288,MATCH($A39,Prospectos!$A$2:$A$288,0)),"") -> A | C39: =IFERROR(INDEX(Prospectos!$H$2:$H$288,MATCH($A39,Prospectos!$A$2:$A$288,0)),"") -> IMBAL S.A. | D39: =IFERROR(INDEX(Prospectos!$J$2:$J$288,MATCH($A39,Prospectos!$A$2:$A$288,0)),"") -> Metalúrgica y fabricación | E39: =IFERROR(INDEX(Prospectos!$C$2:$C$288,MATCH($A39,Prospectos!$A$2:$A$288,0)),"") -> Base Río Tercero | F39: =IFERROR(INDEX(Prospectos!$E$2:$E$288,MATCH($A39,Prospectos!$A$2:$A$288,0)),"") -> Río Tercero | G39: =IFERROR(INDEX(Prospectos!$K$2:$K$288,MATCH($A39,Prospectos!$A$2:$A$288,0)),"") -> A relevar en terreno | H39: =IFERROR(INDEX(Prospectos!$M$2:$M$288,MATCH($A39,Prospectos!$A$2:$A$288,0)),"") -> despacho / producción | I39: =IFERROR(INDEX(Prospectos!$N$2:$N$288,MATCH($A39,Prospectos!$A$2:$A$288,0)),"") -> Despacho seguro de estructuras, carrozados, tanques, piezas industriales y equipos sobre plataforma. | J39: =IFERROR(INDEX(Prospectos!$AJ$2:$AJ$288,MATCH($A39,Prospectos!$A$2:$A$288,0)),"") -> Alta | K39: DANIEL BALATORE
A40: RT-022 | B40: =IFERROR(INDEX(Prospectos!$F$2:$F$288,MATCH($A40,Prospectos!$A$2:$A$288,0)),"") -> B | C40: =IFERROR(INDEX(Prospectos!$H$2:$H$288,MATCH($A40,Prospectos!$A$2:$A$288,0)),"") -> J.A.F. Plásticos Reforzados | D40: =IFERROR(INDEX(Prospectos!$J$2:$J$288,MATCH($A40,Prospectos!$A$2:$A$288,0)),"") -> PRFV y plásticos | E40: =IFERROR(INDEX(Prospectos!$C$2:$C$288,MATCH($A40,Prospectos!$A$2:$A$288,0)),"") -> Base Río Tercero | F40: =IFERROR(INDEX(Prospectos!$E$2:$E$288,MATCH($A40,Prospectos!$A$2:$A$288,0)),"") -> Río Tercero | G40: =IFERROR(INDEX(Prospectos!$K$2:$K$288,MATCH($A40,Prospectos!$A$2:$A$288,0)),"") -> 3571 533624 / 3571 579801 / portería parque 03571 565662 | H40: =IFERROR(INDEX(Prospectos!$M$2:$M$288,MATCH($A40,Prospectos!$A$2:$A$288,0)),"") -> producción / logística | I40: =IFERROR(INDEX(Prospectos!$N$2:$N$288,MATCH($A40,Prospectos!$A$2:$A$288,0)),"") -> Retiro, traslado y descarga de piletas/fibra o piezas voluminosas livianas, con cuidado de maniobra. | J40: =IFERROR(INDEX(Prospectos!$AJ$2:$AJ$288,MATCH($A40,Prospectos!$A$2:$A$288,0)),"") -> Alta
A41: RT-023 | B41: =IFERROR(INDEX(Prospectos!$F$2:$F$288,MATCH($A41,Prospectos!$A$2:$A$288,0)),"") -> B | C41: =IFERROR(INDEX(Prospectos!$H$2:$H$288,MATCH($A41,Prospectos!$A$2:$A$288,0)),"") -> Tecnipiscinas | D41: =IFERROR(INDEX(Prospectos!$J$2:$J$288,MATCH($A41,Prospectos!$A$2:$A$288,0)),"") -> PRFV y plásticos | E41: =IFERROR(INDEX(Prospectos!$C$2:$C$288,MATCH($A41,Prospectos!$A$2:$A$288,0)),"") -> Base Río Tercero | F41: =IFERROR(INDEX(Prospectos!$E$2:$E$288,MATCH($A41,Prospectos!$A$2:$A$288,0)),"") -> Río Tercero | G41: =IFERROR(INDEX(Prospectos!$K$2:$K$288,MATCH($A41,Prospectos!$A$2:$A$288,0)),"") -> +54 3571 412563 | H41: =IFERROR(INDEX(Prospectos!$M$2:$M$288,MATCH($A41,Prospectos!$A$2:$A$288,0)),"") -> ventas / logística / dueño | I41: =IFERROR(INDEX(Prospectos!$N$2:$N$288,MATCH($A41,Prospectos!$A$2:$A$288,0)),"") -> Retiro, traslado y descarga de piletas/fibra o piezas voluminosas livianas, con cuidado de maniobra. | J41: =IFERROR(INDEX(Prospectos!$AJ$2:$AJ$288,MATCH($A41,Prospectos!$A$2:$A$288,0)),"") -> Alta
A42: RT-024 | B42: =IFERROR(INDEX(Prospectos!$F$2:$F$288,MATCH($A42,Prospectos!$A$2:$A$288,0)),"") -> B | C42: =IFERROR(INDEX(Prospectos!$H$2:$H$288,MATCH($A42,Prospectos!$A$2:$A$288,0)),"") -> Indusplast Río Tercero | D42: =IFERROR(INDEX(Prospectos!$J$2:$J$288,MATCH($A42,Prospectos!$A$2:$A$288,0)),"") -> PRFV y plásticos | E42: =IFERROR(INDEX(Prospectos!$C$2:$C$288,MATCH($A42,Prospectos!$A$2:$A$288,0)),"") -> Base Río Tercero | F42: =IFERROR(INDEX(Prospectos!$E$2:$E$288,MATCH($A42,Prospectos!$A$2:$A$288,0)),"") -> Río Tercero | G42: =IFERROR(INDEX(Prospectos!$K$2:$K$288,MATCH($A42,Prospectos!$A$2:$A$288,0)),"") -> +54 3571 57-5556 | H42: =IFERROR(INDEX(Prospectos!$M$2:$M$288,MATCH($A42,Prospectos!$A$2:$A$288,0)),"") -> ventas / dueño | I42: =IFERROR(INDEX(Prospectos!$N$2:$N$288,MATCH($A42,Prospectos!$A$2:$A$288,0)),"") -> Retiro, traslado y descarga de piletas/fibra o piezas voluminosas livianas, con cuidado de maniobra. | J42: =IFERROR(INDEX(Prospectos!$AJ$2:$AJ$288,MATCH($A42,Prospectos!$A$2:$A$288,0)),"") -> Alta
A43: RT-025 | B43: =IFERROR(INDEX(Prospectos!$F$2:$F$288,MATCH($A43,Prospectos!$A$2:$A$288,0)),"") -> B | C43: =IFERROR(INDEX(Prospectos!$H$2:$H$288,MATCH($A43,Prospectos!$A$2:$A$288,0)),"") -> AGROTRAZIONE S.A.S | D43: =IFERROR(INDEX(Prospectos!$J$2:$J$288,MATCH($A43,Prospectos!$A$2:$A$288,0)),"") -> Maquinaria agrícola | E43: =IFERROR(INDEX(Prospectos!$C$2:$C$288,MATCH($A43,Prospectos!$A$2:$A$288,0)),"") -> Base Río Tercero | F43: =IFERROR(INDEX(Prospectos!$E$2:$E$288,MATCH($A43,Prospectos!$A$2:$A$288,0)),"") -> Río Tercero | G43: =IFERROR(INDEX(Prospectos!$K$2:$K$288,MATCH($A43,Prospectos!$A$2:$A$288,0)),"") -> 03571 528350 | H43: =IFERROR(INDEX(Prospectos!$M$2:$M$288,MATCH($A43,Prospectos!$A$2:$A$288,0)),"") -> logística / entregas / postventa | I43: =IFERROR(INDEX(Prospectos!$N$2:$N$288,MATCH($A43,Prospectos!$A$2:$A$288,0)),"") -> Traslado de maquinaria agrícola o vial entre sucursal, cliente, taller, campo y eventos. | J43: =IFERROR(INDEX(Prospectos!$AJ$2:$AJ$288,MATCH($A43,Prospectos!$A$2:$A$288,0)),"") -> Alta
A44: RT-026 | B44: =IFERROR(INDEX(Prospectos!$F$2:$F$288,MATCH($A44,Prospectos!$A$2:$A$288,0)),"") -> B | C44: =IFERROR(INDEX(Prospectos!$H$2:$H$288,MATCH($A44,Prospectos!$A$2:$A$288,0)),"") -> Cementados Juan Nadalin e Hijos S.A. | D44: =IFERROR(INDEX(Prospectos!$J$2:$J$288,MATCH($A44,Prospectos!$A$2:$A$288,0)),"") -> Agroindustria y alimentos | E44: =IFERROR(INDEX(Prospectos!$C$2:$C$288,MATCH($A44,Prospectos!$A$2:$A$288,0)),"") -> Base Río Tercero | F44: =IFERROR(INDEX(Prospectos!$E$2:$E$288,MATCH($A44,Prospectos!$A$2:$A$288,0)),"") -> Río Tercero | G44: =IFERROR(INDEX(Prospectos!$K$2:$K$288,MATCH($A44,Prospectos!$A$2:$A$288,0)),"") -> 03571 420931 | H44: =IFERROR(INDEX(Prospectos!$M$2:$M$288,MATCH($A44,Prospectos!$A$2:$A$288,0)),"") -> logística / despacho / postventa | I44: =IFERROR(INDEX(Prospectos!$N$2:$N$288,MATCH($A44,Prospectos!$A$2:$A$288,0)),"") -> Traslado de maquinaria, implementos, equipos terminados y componentes de gran porte entre planta, cliente, obra o feria. | J44: =IFERROR(INDEX(Prospectos!$AJ$2:$AJ$288,MATCH($A44,Prospectos!$A$2:$A$288,0)),"") -> Alta | K44: JUANJO NADALIN
A45: RT-027 | B45: =IFERROR(INDEX(Prospectos!$F$2:$F$288,MATCH($A45,Prospectos!$A$2:$A$288,0)),"") -> B | C45: =IFERROR(INDEX(Prospectos!$H$2:$H$288,MATCH($A45,Prospectos!$A$2:$A$288,0)),"") -> Cementados Río Tercero | D45: =IFERROR(INDEX(Prospectos!$J$2:$J$288,MATCH($A45,Prospectos!$A$2:$A$288,0)),"") -> Agroindustria y alimentos | E45: =IFERROR(INDEX(Prospectos!$C$2:$C$288,MATCH($A45,Prospectos!$A$2:$A$288,0)),"") -> Base Río Tercero | F45: =IFERROR(INDEX(Prospectos!$E$2:$E$288,MATCH($A45,Prospectos!$A$2:$A$288,0)),"") -> Río Tercero | G45: =IFERROR(INDEX(Prospectos!$K$2:$K$288,MATCH($A45,Prospectos!$A$2:$A$288,0)),"") -> 03571 319490 | H45: =IFERROR(INDEX(Prospectos!$M$2:$M$288,MATCH($A45,Prospectos!$A$2:$A$288,0)),"") -> logística / despacho / postventa | I45: =IFERROR(INDEX(Prospectos!$N$2:$N$288,MATCH($A45,Prospectos!$A$2:$A$288,0)),"") -> Traslado de maquinaria, implementos, equipos terminados y componentes de gran porte entre planta, cliente, obra o feria. | J45: =IFERROR(INDEX(Prospectos!$AJ$2:$AJ$288,MATCH($A45,Prospectos!$A$2:$A$288,0)),"") -> Alta
A46: RT-028 | B46: =IFERROR(INDEX(Prospectos!$F$2:$F$288,MATCH($A46,Prospectos!$A$2:$A$288,0)),"") -> B | C46: =IFERROR(INDEX(Prospectos!$H$2:$H$288,MATCH($A46,Prospectos!$A$2:$A$288,0)),"") -> Hidrobull | D46: =IFERROR(INDEX(Prospectos!$J$2:$J$288,MATCH($A46,Prospectos!$A$2:$A$288,0)),"") -> Industria y mantenimiento | E46: =IFERROR(INDEX(Prospectos!$C$2:$C$288,MATCH($A46,Prospectos!$A$2:$A$288,0)),"") -> Base Río Tercero | F46: =IFERROR(INDEX(Prospectos!$E$2:$E$288,MATCH($A46,Prospectos!$A$2:$A$288,0)),"") -> Río Tercero | G46: =IFERROR(INDEX(Prospectos!$K$2:$K$288,MATCH($A46,Prospectos!$A$2:$A$288,0)),"") -> 03571 549612 | H46: =IFERROR(INDEX(Prospectos!$M$2:$M$288,MATCH($A46,Prospectos!$A$2:$A$288,0)),"") -> responsable de logística/compras | I46: =IFERROR(INDEX(Prospectos!$N$2:$N$288,MATCH($A46,Prospectos!$A$2:$A$288,0)),"") -> Movimientos especiales de mantenimiento, repuestos pesados y mudanzas internas de equipos. | J46: =IFERROR(INDEX(Prospectos!$AJ$2:$AJ$288,MATCH($A46,Prospectos!$A$2:$A$288,0)),"") -> Alta | K46: DAVID BELAZQUE
A47: RT-029 | B47: =IFERROR(INDEX(Prospectos!$F$2:$F$288,MATCH($A47,Prospectos!$A$2:$A$288,0)),"") -> B | C47: =IFERROR(INDEX(Prospectos!$H$2:$H$288,MATCH($A47,Prospectos!$A$2:$A$288,0)),"") -> MetalMec S.R.L. | D47: =IFERROR(INDEX(Prospectos!$J$2:$J$288,MATCH($A47,Prospectos!$A$2:$A$288,0)),"") -> Industria y mantenimiento | E47: =IFERROR(INDEX(Prospectos!$C$2:$C$288,MATCH($A47,Prospectos!$A$2:$A$288,0)),"") -> Base Río Tercero | F47: =IFERROR(INDEX(Prospectos!$E$2:$E$288,MATCH($A47,Prospectos!$A$2:$A$288,0)),"") -> Río Tercero | G47: =IFERROR(INDEX(Prospectos!$K$2:$K$288,MATCH($A47,Prospectos!$A$2:$A$288,0)),"") -> 03571 681577 / 03571 506656 | H47: =IFERROR(INDEX(Prospectos!$M$2:$M$288,MATCH($A47,Prospectos!$A$2:$A$288,0)),"") -> despacho / producción | I47: =IFERROR(INDEX(Prospectos!$N$2:$N$288,MATCH($A47,Prospectos!$A$2:$A$288,0)),"") -> Movimientos especiales de mantenimiento, repuestos pesados y mudanzas internas de equipos. | J47: =IFERROR(INDEX(Prospectos!$AJ$2:$AJ$288,MATCH($A47,Prospectos!$A$2:$A$288,0)),"") -> Alta | K47: FEDE SERRA
A48: RT-030 | B48: =IFERROR(INDEX(Prospectos!$F$2:$F$288,MATCH($A48,Prospectos!$A$2:$A$288,0)),"") -> B | C48: =IFERROR(INDEX(Prospectos!$H$2:$H$288,MATCH($A48,Prospectos!$A$2:$A$288,0)),"") -> Oleos San José S.R.L. | D48: =IFERROR(INDEX(Prospectos!$J$2:$J$288,MATCH($A48,Prospectos!$A$2:$A$288,0)),"") -> Agroindustria y alimentos | E48: =IFERROR(INDEX(Prospectos!$C$2:$C$288,MATCH($A48,Prospectos!$A$2:$A$288,0)),"") -> Base Río Tercero | F48: =IFERROR(INDEX(Prospectos!$E$2:$E$288,MATCH($A48,Prospectos!$A$2:$A$288,0)),"") -> Río Tercero | G48: =IFERROR(INDEX(Prospectos!$K$2:$K$288,MATCH($A48,Prospectos!$A$2:$A$288,0)),"") -> 03571 692471 / 03571 640630 | H48: =IFERROR(INDEX(Prospectos!$M$2:$M$288,MATCH($A48,Prospectos!$A$2:$A$288,0)),"") -> responsable de acopio / mantenimiento | I48: =IFERROR(INDEX(Prospectos!$N$2:$N$288,MATCH($A48,Prospectos!$A$2:$A$288,0)),"") -> Movimientos especiales de mantenimiento, repuestos pesados y mudanzas internas de equipos. | J48: =IFERROR(INDEX(Prospectos!$AJ$2:$AJ$288,MATCH($A48,Prospectos!$A$2:$A$288,0)),"") -> Alta
A49: RT-031 | B49: =IFERROR(INDEX(Prospectos!$F$2:$F$288,MATCH($A49,Prospectos!$A$2:$A$288,0)),"") -> B | C49: =IFERROR(INDEX(Prospectos!$H$2:$H$288,MATCH($A49,Prospectos!$A$2:$A$288,0)),"") -> Premolfran Premoldeados by d'Eco | D49: =IFERROR(INDEX(Prospectos!$J$2:$J$288,MATCH($A49,Prospectos!$A$2:$A$288,0)),"") -> Hormigón, áridos y materiales | E49: =IFERROR(INDEX(Prospectos!$C$2:$C$288,MATCH($A49,Prospectos!$A$2:$A$288,0)),"") -> Base Río Tercero | F49: =IFERROR(INDEX(Prospectos!$E$2:$E$288,MATCH($A49,Prospectos!$A$2:$A$288,0)),"") -> Río Tercero | G49: =IFERROR(INDEX(Prospectos!$K$2:$K$288,MATCH($A49,Prospectos!$A$2:$A$288,0)),"") -> 03571 327594 | H49: =IFERROR(INDEX(Prospectos!$M$2:$M$288,MATCH($A49,Prospectos!$A$2:$A$288,0)),"") -> planta / despacho | I49: =IFERROR(INDEX(Prospectos!$N$2:$N$288,MATCH($A49,Prospectos!$A$2:$A$288,0)),"") -> Movimiento de premoldeados, moldes, equipos de planta y cargas pesadas asociadas a obra. | J49: =IFERROR(INDEX(Prospectos!$AJ$2:$AJ$288,MATCH($A49,Prospectos!$A$2:$A$288,0)),"") -> Alta
A50: RT-032 | B50: =IFERROR(INDEX(Prospectos!$F$2:$F$288,MATCH($A50,Prospectos!$A$2:$A$288,0)),"") -> B | C50: =IFERROR(INDEX(Prospectos!$H$2:$H$288,MATCH($A50,Prospectos!$A$2:$A$288,0)),"") -> Río Metal | D50: =IFERROR(INDEX(Prospectos!$J$2:$J$288,MATCH($A50,Prospectos!$A$2:$A$288,0)),"") -> Metalúrgica y fabricación | E50: =IFERROR(INDEX(Prospectos!$C$2:$C$288,MATCH($A50,Prospectos!$A$2:$A$288,0)),"") -> Base Río Tercero | F50: =IFERROR(INDEX(Prospectos!$E$2:$E$288,MATCH($A50,Prospectos!$A$2:$A$288,0)),"") -> Río Tercero | G50: =IFERROR(INDEX(Prospectos!$K$2:$K$288,MATCH($A50,Prospectos!$A$2:$A$288,0)),"") -> +54 9 3571 52-9444 | H50: =IFERROR(INDEX(Prospectos!$M$2:$M$288,MATCH($A50,Prospectos!$A$2:$A$288,0)),"") -> despacho / producción | I50: =IFERROR(INDEX(Prospectos!$N$2:$N$288,MATCH($A50,Prospectos!$A$2:$A$288,0)),"") -> Despacho seguro de estructuras, carrozados, tanques, piezas industriales y equipos sobre plataforma. | J50: =IFERROR(INDEX(Prospectos!$AJ$2:$AJ$288,MATCH($A50,Prospectos!$A$2:$A$288,0)),"") -> Alta
A51: RT-033 | B51: =IFERROR(INDEX(Prospectos!$F$2:$F$288,MATCH($A51,Prospectos!$A$2:$A$288,0)),"") -> B | C51: =IFERROR(INDEX(Prospectos!$H$2:$H$288,MATCH($A51,Prospectos!$A$2:$A$288,0)),"") -> SILMAR Industrial | D51: =IFERROR(INDEX(Prospectos!$J$2:$J$288,MATCH($A51,Prospectos!$A$2:$A$288,0)),"") -> Metalúrgica y fabricación | E51: =IFERROR(INDEX(Prospectos!$C$2:$C$288,MATCH($A51,Prospectos!$A$2:$A$288,0)),"") -> Base Río Tercero | F51: =IFERROR(INDEX(Prospectos!$E$2:$E$288,MATCH($A51,Prospectos!$A$2:$A$288,0)),"") -> Río Tercero | G51: =IFERROR(INDEX(Prospectos!$K$2:$K$288,MATCH($A51,Prospectos!$A$2:$A$288,0)),"") -> 03571 411073 | H51: =IFERROR(INDEX(Prospectos!$M$2:$M$288,MATCH($A51,Prospectos!$A$2:$A$288,0)),"") -> mantenimiento / despacho | I51: =IFERROR(INDEX(Prospectos!$N$2:$N$288,MATCH($A51,Prospectos!$A$2:$A$288,0)),"") -> Movimientos especiales de mantenimiento, repuestos pesados, equipos y mudanzas internas o entre plantas. | J51: =IFERROR(INDEX(Prospectos!$AJ$2:$AJ$288,MATCH($A51,Prospectos!$A$2:$A$288,0)),"") -> Alta
A52: RT-034 | B52: =IFERROR(INDEX(Prospectos!$F$2:$F$288,MATCH($A52,Prospectos!$A$2:$A$288,0)),"") -> B | C52: =IFERROR(INDEX(Prospectos!$H$2:$H$288,MATCH($A52,Prospectos!$A$2:$A$288,0)),"") -> TALFUND S.A. | D52: =IFERROR(INDEX(Prospectos!$J$2:$J$288,MATCH($A52,Prospectos!$A$2:$A$288,0)),"") -> Metalúrgica y fabricación | E52: =IFERROR(INDEX(Prospectos!$C$2:$C$288,MATCH($A52,Prospectos!$A$2:$A$288,0)),"") -> Base Río Tercero | F52: =IFERROR(INDEX(Prospectos!$E$2:$E$288,MATCH($A52,Prospectos!$A$2:$A$288,0)),"") -> Río Tercero | G52: =IFERROR(INDEX(Prospectos!$K$2:$K$288,MATCH($A52,Prospectos!$A$2:$A$288,0)),"") -> 03571 690418 / 03571 642555 | H52: =IFERROR(INDEX(Prospectos!$M$2:$M$288,MATCH($A52,Prospectos!$A$2:$A$288,0)),"") -> despacho / producción | I52: =IFERROR(INDEX(Prospectos!$N$2:$N$288,MATCH($A52,Prospectos!$A$2:$A$288,0)),"") -> Despacho de estructuras, piezas, equipos y conjuntos metalmecánicos de gran porte hacia obras o clientes. | J52: =IFERROR(INDEX(Prospectos!$AJ$2:$AJ$288,MATCH($A52,Prospectos!$A$2:$A$288,0)),"") -> Alta
A53: RT-035 | B53: =IFERROR(INDEX(Prospectos!$F$2:$F$288,MATCH($A53,Prospectos!$A$2:$A$288,0)),"") -> B | C53: =IFERROR(INDEX(Prospectos!$H$2:$H$288,MATCH($A53,Prospectos!$A$2:$A$288,0)),"") -> Tello SRL Premoldeados de Hormigón | D53: =IFERROR(INDEX(Prospectos!$J$2:$J$288,MATCH($A53,Prospectos!$A$2:$A$288,0)),"") -> Hormigón, áridos y materiales | E53: =IFERROR(INDEX(Prospectos!$C$2:$C$288,MATCH($A53,Prospectos!$A$2:$A$288,0)),"") -> Base Río Tercero | F53: =IFERROR(INDEX(Prospectos!$E$2:$E$288,MATCH($A53,Prospectos!$A$2:$A$288,0)),"") -> Río Tercero | G53: =IFERROR(INDEX(Prospectos!$K$2:$K$288,MATCH($A53,Prospectos!$A$2:$A$288,0)),"") -> 0351 4576859 | H53: =IFERROR(INDEX(Prospectos!$M$2:$M$288,MATCH($A53,Prospectos!$A$2:$A$288,0)),"") -> planta / despacho | I53: =IFERROR(INDEX(Prospectos!$N$2:$N$288,MATCH($A53,Prospectos!$A$2:$A$288,0)),"") -> Movimiento de premoldeados, moldes, equipos de planta y cargas pesadas asociadas a obra. | J53: =IFERROR(INDEX(Prospectos!$AJ$2:$AJ$288,MATCH($A53,Prospectos!$A$2:$A$288,0)),"") -> Alta
A54: RT-061 | B54: =IFERROR(INDEX(Prospectos!$F$2:$F$288,MATCH($A54,Prospectos!$A$2:$A$288,0)),"") -> B | C54: =IFERROR(INDEX(Prospectos!$H$2:$H$288,MATCH($A54,Prospectos!$A$2:$A$288,0)),"") -> Formia Repuestos | D54: =IFERROR(INDEX(Prospectos!$J$2:$J$288,MATCH($A54,Prospectos!$A$2:$A$288,0)),"") -> Maquinaria agrícola | E54: =IFERROR(INDEX(Prospectos!$C$2:$C$288,MATCH($A54,Prospectos!$A$2:$A$288,0)),"") -> Base Río Tercero | F54: =IFERROR(INDEX(Prospectos!$E$2:$E$288,MATCH($A54,Prospectos!$A$2:$A$288,0)),"") -> Río Tercero | G54: =IFERROR(INDEX(Prospectos!$K$2:$K$288,MATCH($A54,Prospectos!$A$2:$A$288,0)),"") -> 03571 422102 | H54: =IFERROR(INDEX(Prospectos!$M$2:$M$288,MATCH($A54,Prospectos!$A$2:$A$288,0)),"") -> logística / ventas / postventa | I54: =IFERROR(INDEX(Prospectos!$N$2:$N$288,MATCH($A54,Prospectos!$A$2:$A$288,0)),"") -> Movimiento de agropartes, repuestos pesados, conjuntos y eventualmente implementos/equipos entre planta, concesionarios y clientes. | J54: =IFERROR(INDEX(Prospectos!$AJ$2:$AJ$288,MATCH($A54,Prospectos!$A$2:$A$288,0)),"") -> Media
A55: RT-063 | B55: =IFERROR(INDEX(Prospectos!$F$2:$F$288,MATCH($A55,Prospectos!$A$2:$A$288,0)),"") -> B | C55: =IFERROR(INDEX(Prospectos!$H$2:$H$288,MATCH($A55,Prospectos!$A$2:$A$288,0)),"") -> Hidráulica Río Tercero | D55: =IFERROR(INDEX(Prospectos!$J$2:$J$288,MATCH($A55,Prospectos!$A$2:$A$288,0)),"") -> Maquinaria agrícola | E55: =IFERROR(INDEX(Prospectos!$C$2:$C$288,MATCH($A55,Prospectos!$A$2:$A$288,0)),"") -> Base Río Tercero | F55: =IFERROR(INDEX(Prospectos!$E$2:$E$288,MATCH($A55,Prospectos!$A$2:$A$288,0)),"") -> Río Tercero | G55: =IFERROR(INDEX(Prospectos!$K$2:$K$288,MATCH($A55,Prospectos!$A$2:$A$288,0)),"") -> 03571 432041 | H55: =IFERROR(INDEX(Prospectos!$M$2:$M$288,MATCH($A55,Prospectos!$A$2:$A$288,0)),"") -> logística / ventas / postventa | I55: =IFERROR(INDEX(Prospectos!$N$2:$N$288,MATCH($A55,Prospectos!$A$2:$A$288,0)),"") -> Movimiento de agropartes, repuestos pesados, conjuntos y eventualmente implementos/equipos entre planta, concesionarios y clientes. | J55: =IFERROR(INDEX(Prospectos!$AJ$2:$AJ$288,MATCH($A55,Prospectos!$A$2:$A$288,0)),"") -> Media
A56: RT-036 | B56: =IFERROR(INDEX(Prospectos!$F$2:$F$288,MATCH($A56,Prospectos!$A$2:$A$288,0)),"") -> B | C56: =IFERROR(INDEX(Prospectos!$H$2:$H$288,MATCH($A56,Prospectos!$A$2:$A$288,0)),"") -> Baudino Hnos. | D56: =IFERROR(INDEX(Prospectos!$J$2:$J$288,MATCH($A56,Prospectos!$A$2:$A$288,0)),"") -> Metalúrgica y fabricación | E56: =IFERROR(INDEX(Prospectos!$C$2:$C$288,MATCH($A56,Prospectos!$A$2:$A$288,0)),"") -> Base Río Tercero | F56: =IFERROR(INDEX(Prospectos!$E$2:$E$288,MATCH($A56,Prospectos!$A$2:$A$288,0)),"") -> Río Tercero | G56: =IFERROR(INDEX(Prospectos!$K$2:$K$288,MATCH($A56,Prospectos!$A$2:$A$288,0)),"") -> 03571 15600693 / 3571 457279 / 3571 458732 | H56: =IFERROR(INDEX(Prospectos!$M$2:$M$288,MATCH($A56,Prospectos!$A$2:$A$288,0)),"") -> despacho / producción | I56: =IFERROR(INDEX(Prospectos!$N$2:$N$288,MATCH($A56,Prospectos!$A$2:$A$288,0)),"") -> Despacho seguro de estructuras, carrozados, tanques, piezas industriales y equipos sobre plataforma. | J56: =IFERROR(INDEX(Prospectos!$AJ$2:$AJ$288,MATCH($A56,Prospectos!$A$2:$A$288,0)),"") -> Media | K56: DIEGO BAUDINO
A57: RT-037 | B57: =IFERROR(INDEX(Prospectos!$F$2:$F$288,MATCH($A57,Prospectos!$A$2:$A$288,0)),"") -> B | C57: =IFERROR(INDEX(Prospectos!$H$2:$H$288,MATCH($A57,Prospectos!$A$2:$A$288,0)),"") -> Charrúa Implementos Agrícolas | D57: =IFERROR(INDEX(Prospectos!$J$2:$J$288,MATCH($A57,Prospectos!$A$2:$A$288,0)),"") -> Maquinaria agrícola | E57: =IFERROR(INDEX(Prospectos!$C$2:$C$288,MATCH($A57,Prospectos!$A$2:$A$288,0)),"") -> Base Río Tercero | F57: =IFERROR(INDEX(Prospectos!$E$2:$E$288,MATCH($A57,Prospectos!$A$2:$A$288,0)),"") -> Río Tercero | G57: =IFERROR(INDEX(Prospectos!$K$2:$K$288,MATCH($A57,Prospectos!$A$2:$A$288,0)),"") -> 03571 619149 / 03571 503663 (a confirmar) / +54 9 3571 61 9149 / +54 9 3571 31 0086 | H57: =IFERROR(INDEX(Prospectos!$M$2:$M$288,MATCH($A57,Prospectos!$A$2:$A$288,0)),"") -> responsable de acopio / mantenimiento | I57: =IFERROR(INDEX(Prospectos!$N$2:$N$288,MATCH($A57,Prospectos!$A$2:$A$288,0)),"") -> Movimientos especiales de mantenimiento, repuestos pesados y mudanzas internas de equipos. | J57: =IFERROR(INDEX(Prospectos!$AJ$2:$AJ$288,MATCH($A57,Prospectos!$A$2:$A$288,0)),"") -> Media
A58: RT-038 | B58: =IFERROR(INDEX(Prospectos!$F$2:$F$288,MATCH($A58,Prospectos!$A$2:$A$288,0)),"") -> B | C58: =IFERROR(INDEX(Prospectos!$H$2:$H$288,MATCH($A58,Prospectos!$A$2:$A$288,0)),"") -> HIDROSERVIS | D58: =IFERROR(INDEX(Prospectos!$J$2:$J$288,MATCH($A58,Prospectos!$A$2:$A$288,0)),"") -> Metalúrgica y fabricación | E58: =IFERROR(INDEX(Prospectos!$C$2:$C$288,MATCH($A58,Prospectos!$A$2:$A$288,0)),"") -> Base Río Tercero | F58: =IFERROR(INDEX(Prospectos!$E$2:$E$288,MATCH($A58,Prospectos!$A$2:$A$288,0)),"") -> Río Tercero | G58: =IFERROR(INDEX(Prospectos!$K$2:$K$288,MATCH($A58,Prospectos!$A$2:$A$288,0)),"") -> Portería parque: 03571 565662 | H58: =IFERROR(INDEX(Prospectos!$M$2:$M$288,MATCH($A58,Prospectos!$A$2:$A$288,0)),"") -> responsable de logística/compras | I58: =IFERROR(INDEX(Prospectos!$N$2:$N$288,MATCH($A58,Prospectos!$A$2:$A$288,0)),"") -> Movimientos especiales de mantenimiento, repuestos pesados y mudanzas internas de equipos. | J58: =IFERROR(INDEX(Prospectos!$AJ$2:$AJ$288,MATCH($A58,Prospectos!$A$2:$A$288,0)),"") -> Media
A59: RT-039 | B59: =IFERROR(INDEX(Prospectos!$F$2:$F$288,MATCH($A59,Prospectos!$A$2:$A$288,0)),"") -> B | C59: =IFERROR(INDEX(Prospectos!$H$2:$H$288,MATCH($A59,Prospectos!$A$2:$A$288,0)),"") -> Hormilas S.A. | D59: =IFERROR(INDEX(Prospectos!$J$2:$J$288,MATCH($A59,Prospectos!$A$2:$A$288,0)),"") -> Hormigón, áridos y materiales | E59: =IFERROR(INDEX(Prospectos!$C$2:$C$288,MATCH($A59,Prospectos!$A$2:$A$288,0)),"") -> Base Río Tercero | F59: =IFERROR(INDEX(Prospectos!$E$2:$E$288,MATCH($A59,Prospectos!$A$2:$A$288,0)),"") -> Río Tercero | G59: =IFERROR(INDEX(Prospectos!$K$2:$K$288,MATCH($A59,Prospectos!$A$2:$A$288,0)),"") -> 03571 573231 (a confirmar) | H59: =IFERROR(INDEX(Prospectos!$M$2:$M$288,MATCH($A59,Prospectos!$A$2:$A$288,0)),"") -> operaciones / planta | I59: =IFERROR(INDEX(Prospectos!$N$2:$N$288,MATCH($A59,Prospectos!$A$2:$A$288,0)),"") -> Movimiento de premoldeados, equipos de planta/cantera, bombas, moldes y cargas pesadas. | J59: =IFERROR(INDEX(Prospectos!$AJ$2:$AJ$288,MATCH($A59,Prospectos!$A$2:$A$288,0)),"") -> Media
A60: RT-040 | B60: =IFERROR(INDEX(Prospectos!$F$2:$F$288,MATCH($A60,Prospectos!$A$2:$A$288,0)),"") -> B | C60: =IFERROR(INDEX(Prospectos!$H$2:$H$288,MATCH($A60,Prospectos!$A$2:$A$288,0)),"") -> MoliCor | D60: =IFERROR(INDEX(Prospectos!$J$2:$J$288,MATCH($A60,Prospectos!$A$2:$A$288,0)),"") -> Metalúrgica y fabricación | E60: =IFERROR(INDEX(Prospectos!$C$2:$C$288,MATCH($A60,Prospectos!$A$2:$A$288,0)),"") -> Base Río Tercero | F60: =IFERROR(INDEX(Prospectos!$E$2:$E$288,MATCH($A60,Prospectos!$A$2:$A$288,0)),"") -> Río Tercero | G60: =IFERROR(INDEX(Prospectos!$K$2:$K$288,MATCH($A60,Prospectos!$A$2:$A$288,0)),"") -> A relevar vía parque | H60: =IFERROR(INDEX(Prospectos!$M$2:$M$288,MATCH($A60,Prospectos!$A$2:$A$288,0)),"") -> despacho / producción | I60: =IFERROR(INDEX(Prospectos!$N$2:$N$288,MATCH($A60,Prospectos!$A$2:$A$288,0)),"") -> Despacho de estructuras, piezas, equipos y conjuntos metalmecánicos de gran porte hacia obras o clientes. | J60: =IFERROR(INDEX(Prospectos!$AJ$2:$AJ$288,MATCH($A60,Prospectos!$A$2:$A$288,0)),"") -> Media
A61: RT-041 | B61: =IFERROR(INDEX(Prospectos!$F$2:$F$288,MATCH($A61,Prospectos!$A$2:$A$288,0)),"") -> B | C61: =IFERROR(INDEX(Prospectos!$H$2:$H$288,MATCH($A61,Prospectos!$A$2:$A$288,0)),"") -> Taller RS S.A. | D61: =IFERROR(INDEX(Prospectos!$J$2:$J$288,MATCH($A61,Prospectos!$A$2:$A$288,0)),"") -> Industria y mantenimiento | E61: =IFERROR(INDEX(Prospectos!$C$2:$C$288,MATCH($A61,Prospectos!$A$2:$A$288,0)),"") -> Base Río Tercero | F61: =IFERROR(INDEX(Prospectos!$E$2:$E$288,MATCH($A61,Prospectos!$A$2:$A$288,0)),"") -> Río Tercero | G61: =IFERROR(INDEX(Prospectos!$K$2:$K$288,MATCH($A61,Prospectos!$A$2:$A$288,0)),"") -> 03571 422065 | H61: =IFERROR(INDEX(Prospectos!$M$2:$M$288,MATCH($A61,Prospectos!$A$2:$A$288,0)),"") -> mantenimiento / despacho | I61: =IFERROR(INDEX(Prospectos!$N$2:$N$288,MATCH($A61,Prospectos!$A$2:$A$288,0)),"") -> Movimientos especiales de mantenimiento, repuestos pesados, equipos y mudanzas internas o entre plantas. | J61: =IFERROR(INDEX(Prospectos!$AJ$2:$AJ$288,MATCH($A61,Prospectos!$A$2:$A$288,0)),"") -> Alta
A62: RT-042 | B62: =IFERROR(INDEX(Prospectos!$F$2:$F$288,MATCH($A62,Prospectos!$A$2:$A$288,0)),"") -> B | C62: =IFERROR(INDEX(Prospectos!$H$2:$H$288,MATCH($A62,Prospectos!$A$2:$A$288,0)),"") -> Atanor / Albaugh | D62: =IFERROR(INDEX(Prospectos!$J$2:$J$288,MATCH($A62,Prospectos!$A$2:$A$288,0)),"") -> Agro, acopio y cooperativas | E62: =IFERROR(INDEX(Prospectos!$C$2:$C$288,MATCH($A62,Prospectos!$A$2:$A$288,0)),"") -> Base Río Tercero | F62: =IFERROR(INDEX(Prospectos!$E$2:$E$288,MATCH($A62,Prospectos!$A$2:$A$288,0)),"") -> Río Tercero | G62: =IFERROR(INDEX(Prospectos!$K$2:$K$288,MATCH($A62,Prospectos!$A$2:$A$288,0)),"") -> A relevar | H62: =IFERROR(INDEX(Prospectos!$M$2:$M$288,MATCH($A62,Prospectos!$A$2:$A$288,0)),"") -> responsable de acopio / mantenimiento | I62: =IFERROR(INDEX(Prospectos!$N$2:$N$288,MATCH($A62,Prospectos!$A$2:$A$288,0)),"") -> Traslado de equipos de planta, silos, repuestos pesados, balanzas, implementos y cargas especiales. | J62: =IFERROR(INDEX(Prospectos!$AJ$2:$AJ$288,MATCH($A62,Prospectos!$A$2:$A$288,0)),"") -> Media | K62: MARCOS PALOMBARINI (GERENTE DE MANTENIMIENTO) JOSE ROSSO (JEFE DE PLANTA CLORO SODA)
A63: RT-043 | B63: =IFERROR(INDEX(Prospectos!$F$2:$F$288,MATCH($A63,Prospectos!$A$2:$A$288,0)),"") -> B | C63: =IFERROR(INDEX(Prospectos!$H$2:$H$288,MATCH($A63,Prospectos!$A$2:$A$288,0)),"") -> Bravo Gustavo y Guillermo | D63: =IFERROR(INDEX(Prospectos!$J$2:$J$288,MATCH($A63,Prospectos!$A$2:$A$288,0)),"") -> Hormigón, áridos y materiales | E63: =IFERROR(INDEX(Prospectos!$C$2:$C$288,MATCH($A63,Prospectos!$A$2:$A$288,0)),"") -> Base Río Tercero | F63: =IFERROR(INDEX(Prospectos!$E$2:$E$288,MATCH($A63,Prospectos!$A$2:$A$288,0)),"") -> Río Tercero | G63: =IFERROR(INDEX(Prospectos!$K$2:$K$288,MATCH($A63,Prospectos!$A$2:$A$288,0)),"") -> A relevar vía parque | H63: =IFERROR(INDEX(Prospectos!$M$2:$M$288,MATCH($A63,Prospectos!$A$2:$A$288,0)),"") -> planta / despacho | I63: =IFERROR(INDEX(Prospectos!$N$2:$N$288,MATCH($A63,Prospectos!$A$2:$A$288,0)),"") -> Movimiento de premoldeados, equipos de planta/cantera, bombas, moldes y cargas pesadas. | J63: =IFERROR(INDEX(Prospectos!$AJ$2:$AJ$288,MATCH($A63,Prospectos!$A$2:$A$288,0)),"") -> Media
A64: RT-044 | B64: =IFERROR(INDEX(Prospectos!$F$2:$F$288,MATCH($A64,Prospectos!$A$2:$A$288,0)),"") -> B | C64: =IFERROR(INDEX(Prospectos!$H$2:$H$288,MATCH($A64,Prospectos!$A$2:$A$288,0)),"") -> Construcciones Sermanter S.R.L. | D64: =IFERROR(INDEX(Prospectos!$J$2:$J$288,MATCH($A64,Prospectos!$A$2:$A$288,0)),"") -> Metalúrgica y fabricación | E64: =IFERROR(INDEX(Prospectos!$C$2:$C$288,MATCH($A64,Prospectos!$A$2:$A$288,0)),"") -> Base Río Tercero | F64: =IFERROR(INDEX(Prospectos!$E$2:$E$288,MATCH($A64,Prospectos!$A$2:$A$288,0)),"") -> Río Tercero | G64: =IFERROR(INDEX(Prospectos!$K$2:$K$288,MATCH($A64,Prospectos!$A$2:$A$288,0)),"") -> A relevar vía parque | H64: =IFERROR(INDEX(Prospectos!$M$2:$M$288,MATCH($A64,Prospectos!$A$2:$A$288,0)),"") -> jefe de obra / mantenimiento | I64: =IFERROR(INDEX(Prospectos!$N$2:$N$288,MATCH($A64,Prospectos!$A$2:$A$288,0)),"") -> Despacho seguro de estructuras, carrozados, tanques, piezas industriales y equipos sobre plataforma. | J64: =IFERROR(INDEX(Prospectos!$AJ$2:$AJ$288,MATCH($A64,Prospectos!$A$2:$A$288,0)),"") -> Media | K64: ROLANDO RAMELLO
A65: RT-045 | B65: =IFERROR(INDEX(Prospectos!$F$2:$F$288,MATCH($A65,Prospectos!$A$2:$A$288,0)),"") -> B | C65: =IFERROR(INDEX(Prospectos!$H$2:$H$288,MATCH($A65,Prospectos!$A$2:$A$288,0)),"") -> Fabri-Mec | D65: =IFERROR(INDEX(Prospectos!$J$2:$J$288,MATCH($A65,Prospectos!$A$2:$A$288,0)),"") -> Metalúrgica y fabricación | E65: =IFERROR(INDEX(Prospectos!$C$2:$C$288,MATCH($A65,Prospectos!$A$2:$A$288,0)),"") -> Base Río Tercero | F65: =IFERROR(INDEX(Prospectos!$E$2:$E$288,MATCH($A65,Prospectos!$A$2:$A$288,0)),"") -> Río Tercero | G65: =IFERROR(INDEX(Prospectos!$K$2:$K$288,MATCH($A65,Prospectos!$A$2:$A$288,0)),"") -> 03571 412302 / 03571 579685 | H65: =IFERROR(INDEX(Prospectos!$M$2:$M$288,MATCH($A65,Prospectos!$A$2:$A$288,0)),"") -> despacho / producción | I65: =IFERROR(INDEX(Prospectos!$N$2:$N$288,MATCH($A65,Prospectos!$A$2:$A$288,0)),"") -> Movimientos especiales de mantenimiento, repuestos pesados y mudanzas internas de equipos. | J65: =IFERROR(INDEX(Prospectos!$AJ$2:$AJ$288,MATCH($A65,Prospectos!$A$2:$A$288,0)),"") -> Media
A66: RT-046 | B66: =IFERROR(INDEX(Prospectos!$F$2:$F$288,MATCH($A66,Prospectos!$A$2:$A$288,0)),"") -> B | C66: =IFERROR(INDEX(Prospectos!$H$2:$H$288,MATCH($A66,Prospectos!$A$2:$A$288,0)),"") -> Fábrica Militar Río Tercero | D66: =IFERROR(INDEX(Prospectos!$J$2:$J$288,MATCH($A66,Prospectos!$A$2:$A$288,0)),"") -> Metalúrgica y fabricación | E66: =IFERROR(INDEX(Prospectos!$C$2:$C$288,MATCH($A66,Prospectos!$A$2:$A$288,0)),"") -> Base Río Tercero | F66: =IFERROR(INDEX(Prospectos!$E$2:$E$288,MATCH($A66,Prospectos!$A$2:$A$288,0)),"") -> Río Tercero | G66: =IFERROR(INDEX(Prospectos!$K$2:$K$288,MATCH($A66,Prospectos!$A$2:$A$288,0)),"") -> A relevar | H66: =IFERROR(INDEX(Prospectos!$M$2:$M$288,MATCH($A66,Prospectos!$A$2:$A$288,0)),"") -> despacho / producción | I66: =IFERROR(INDEX(Prospectos!$N$2:$N$288,MATCH($A66,Prospectos!$A$2:$A$288,0)),"") -> Despacho seguro de estructuras, carrozados, tanques, piezas industriales y equipos sobre plataforma. | J66: =IFERROR(INDEX(Prospectos!$AJ$2:$AJ$288,MATCH($A66,Prospectos!$A$2:$A$288,0)),"") -> Media
A67: RT-047 | B67: =IFERROR(INDEX(Prospectos!$F$2:$F$288,MATCH($A67,Prospectos!$A$2:$A$288,0)),"") -> B | C67: =IFERROR(INDEX(Prospectos!$H$2:$H$288,MATCH($A67,Prospectos!$A$2:$A$288,0)),"") -> LiftingMach S.A. | D67: =IFERROR(INDEX(Prospectos!$J$2:$J$288,MATCH($A67,Prospectos!$A$2:$A$288,0)),"") -> Industria y mantenimiento | E67: =IFERROR(INDEX(Prospectos!$C$2:$C$288,MATCH($A67,Prospectos!$A$2:$A$288,0)),"") -> Base Río Tercero | F67: =IFERROR(INDEX(Prospectos!$E$2:$E$288,MATCH($A67,Prospectos!$A$2:$A$288,0)),"") -> Río Tercero | G67: =IFERROR(INDEX(Prospectos!$K$2:$K$288,MATCH($A67,Prospectos!$A$2:$A$288,0)),"") -> A relevar vía parque | H67: =IFERROR(INDEX(Prospectos!$M$2:$M$288,MATCH($A67,Prospectos!$A$2:$A$288,0)),"") -> despacho / producción | I67: =IFERROR(INDEX(Prospectos!$N$2:$N$288,MATCH($A67,Prospectos!$A$2:$A$288,0)),"") -> Movimientos especiales de mantenimiento, repuestos pesados y mudanzas internas de equipos. | J67: =IFERROR(INDEX(Prospectos!$AJ$2:$AJ$288,MATCH($A67,Prospectos!$A$2:$A$288,0)),"") -> Media
A68: RT-048 | B68: =IFERROR(INDEX(Prospectos!$F$2:$F$288,MATCH($A68,Prospectos!$A$2:$A$288,0)),"") -> B | C68: =IFERROR(INDEX(Prospectos!$H$2:$H$288,MATCH($A68,Prospectos!$A$2:$A$288,0)),"") -> PROMETVA S.R.L. | D68: =IFERROR(INDEX(Prospectos!$J$2:$J$288,MATCH($A68,Prospectos!$A$2:$A$288,0)),"") -> Metalúrgica y fabricación | E68: =IFERROR(INDEX(Prospectos!$C$2:$C$288,MATCH($A68,Prospectos!$A$2:$A$288,0)),"") -> Base Río Tercero | F68: =IFERROR(INDEX(Prospectos!$E$2:$E$288,MATCH($A68,Prospectos!$A$2:$A$288,0)),"") -> Río Tercero | G68: =IFERROR(INDEX(Prospectos!$K$2:$K$288,MATCH($A68,Prospectos!$A$2:$A$288,0)),"") -> A relevar vía parque | H68: =IFERROR(INDEX(Prospectos!$M$2:$M$288,MATCH($A68,Prospectos!$A$2:$A$288,0)),"") -> despacho / producción | I68: =IFERROR(INDEX(Prospectos!$N$2:$N$288,MATCH($A68,Prospectos!$A$2:$A$288,0)),"") -> Movimientos especiales de mantenimiento, repuestos pesados y mudanzas internas de equipos. | J68: =IFERROR(INDEX(Prospectos!$AJ$2:$AJ$288,MATCH($A68,Prospectos!$A$2:$A$288,0)),"") -> Media
A69: RT-049 | B69: =IFERROR(INDEX(Prospectos!$F$2:$F$288,MATCH($A69,Prospectos!$A$2:$A$288,0)),"") -> B | C69: =IFERROR(INDEX(Prospectos!$H$2:$H$288,MATCH($A69,Prospectos!$A$2:$A$288,0)),"") -> Taller Sarmiento | D69: =IFERROR(INDEX(Prospectos!$J$2:$J$288,MATCH($A69,Prospectos!$A$2:$A$288,0)),"") -> Industria y mantenimiento | E69: =IFERROR(INDEX(Prospectos!$C$2:$C$288,MATCH($A69,Prospectos!$A$2:$A$288,0)),"") -> Base Río Tercero | F69: =IFERROR(INDEX(Prospectos!$E$2:$E$288,MATCH($A69,Prospectos!$A$2:$A$288,0)),"") -> Río Tercero | G69: =IFERROR(INDEX(Prospectos!$K$2:$K$288,MATCH($A69,Prospectos!$A$2:$A$288,0)),"") -> A relevar vía parque | H69: =IFERROR(INDEX(Prospectos!$M$2:$M$288,MATCH($A69,Prospectos!$A$2:$A$288,0)),"") -> mantenimiento / compras | I69: =IFERROR(INDEX(Prospectos!$N$2:$N$288,MATCH($A69,Prospectos!$A$2:$A$288,0)),"") -> Movimientos especiales de mantenimiento, repuestos pesados y mudanzas internas de equipos. | J69: =IFERROR(INDEX(Prospectos!$AJ$2:$AJ$288,MATCH($A69,Prospectos!$A$2:$A$288,0)),"") -> Media
A70: RT-050 | B70: =IFERROR(INDEX(Prospectos!$F$2:$F$288,MATCH($A70,Prospectos!$A$2:$A$288,0)),"") -> C | C70: =IFERROR(INDEX(Prospectos!$H$2:$H$288,MATCH($A70,Prospectos!$A$2:$A$288,0)),"") -> Grupo AVO S.A. | D70: =IFERROR(INDEX(Prospectos!$J$2:$J$288,MATCH($A70,Prospectos!$A$2:$A$288,0)),"") -> Agroindustria y alimentos | E70: =IFERROR(INDEX(Prospectos!$C$2:$C$288,MATCH($A70,Prospectos!$A$2:$A$288,0)),"") -> Base Río Tercero | F70: =IFERROR(INDEX(Prospectos!$E$2:$E$288,MATCH($A70,Prospectos!$A$2:$A$288,0)),"") -> Río Tercero | G70: =IFERROR(INDEX(Prospectos!$K$2:$K$288,MATCH($A70,Prospectos!$A$2:$A$288,0)),"") -> Portería parque: 03571 565662 | H70: =IFERROR(INDEX(Prospectos!$M$2:$M$288,MATCH($A70,Prospectos!$A$2:$A$288,0)),"") -> responsable de acopio / mantenimiento | I70: =IFERROR(INDEX(Prospectos!$N$2:$N$288,MATCH($A70,Prospectos!$A$2:$A$288,0)),"") -> Movimientos especiales de mantenimiento, repuestos pesados y mudanzas internas de equipos. | J70: =IFERROR(INDEX(Prospectos!$AJ$2:$AJ$288,MATCH($A70,Prospectos!$A$2:$A$288,0)),"") -> Baja / visitar solo por cercanía
A71: RT-051 | B71: =IFERROR(INDEX(Prospectos!$F$2:$F$288,MATCH($A71,Prospectos!$A$2:$A$288,0)),"") -> C | C71: =IFERROR(INDEX(Prospectos!$H$2:$H$288,MATCH($A71,Prospectos!$A$2:$A$288,0)),"") -> Transporte Sosa | D71: =IFERROR(INDEX(Prospectos!$J$2:$J$288,MATCH($A71,Prospectos!$A$2:$A$288,0)),"") -> Metalúrgica y fabricación | E71: =IFERROR(INDEX(Prospectos!$C$2:$C$288,MATCH($A71,Prospectos!$A$2:$A$288,0)),"") -> Base Río Tercero | F71: =IFERROR(INDEX(Prospectos!$E$2:$E$288,MATCH($A71,Prospectos!$A$2:$A$288,0)),"") -> Río Tercero | G71: =IFERROR(INDEX(Prospectos!$K$2:$K$288,MATCH($A71,Prospectos!$A$2:$A$288,0)),"") -> A relevar vía parque | H71: =IFERROR(INDEX(Prospectos!$M$2:$M$288,MATCH($A71,Prospectos!$A$2:$A$288,0)),"") -> dueño / taller | I71: =IFERROR(INDEX(Prospectos!$N$2:$N$288,MATCH($A71,Prospectos!$A$2:$A$288,0)),"") -> Movimientos especiales de mantenimiento, repuestos pesados y mudanzas internas de equipos. | J71: =IFERROR(INDEX(Prospectos!$AJ$2:$AJ$288,MATCH($A71,Prospectos!$A$2:$A$288,0)),"") -> Baja / visitar solo por cercanía
A72: RT-052 | B72: =IFERROR(INDEX(Prospectos!$F$2:$F$288,MATCH($A72,Prospectos!$A$2:$A$288,0)),"") -> C | C72: =IFERROR(INDEX(Prospectos!$H$2:$H$288,MATCH($A72,Prospectos!$A$2:$A$288,0)),"") -> Volonte Marcelo | D72: =IFERROR(INDEX(Prospectos!$J$2:$J$288,MATCH($A72,Prospectos!$A$2:$A$288,0)),"") -> Industria y mantenimiento | E72: =IFERROR(INDEX(Prospectos!$C$2:$C$288,MATCH($A72,Prospectos!$A$2:$A$288,0)),"") -> Base Río Tercero | F72: =IFERROR(INDEX(Prospectos!$E$2:$E$288,MATCH($A72,Prospectos!$A$2:$A$288,0)),"") -> Río Tercero | G72: =IFERROR(INDEX(Prospectos!$K$2:$K$288,MATCH($A72,Prospectos!$A$2:$A$288,0)),"") -> A relevar vía parque | H72: =IFERROR(INDEX(Prospectos!$M$2:$M$288,MATCH($A72,Prospectos!$A$2:$A$288,0)),"") -> operaciones / taller | I72: =IFERROR(INDEX(Prospectos!$N$2:$N$288,MATCH($A72,Prospectos!$A$2:$A$288,0)),"") -> Movimientos especiales de mantenimiento, repuestos pesados y mudanzas internas de equipos. | J72: =IFERROR(INDEX(Prospectos!$AJ$2:$AJ$288,MATCH($A72,Prospectos!$A$2:$A$288,0)),"") -> Baja / visitar solo por cercanía
A73: RT-053 | B73: =IFERROR(INDEX(Prospectos!$F$2:$F$288,MATCH($A73,Prospectos!$A$2:$A$288,0)),"") -> C | C73: =IFERROR(INDEX(Prospectos!$H$2:$H$288,MATCH($A73,Prospectos!$A$2:$A$288,0)),"") -> Áridos S.A. | D73: =IFERROR(INDEX(Prospectos!$J$2:$J$288,MATCH($A73,Prospectos!$A$2:$A$288,0)),"") -> Hormigón, áridos y materiales | E73: =IFERROR(INDEX(Prospectos!$C$2:$C$288,MATCH($A73,Prospectos!$A$2:$A$288,0)),"") -> Base Río Tercero | F73: =IFERROR(INDEX(Prospectos!$E$2:$E$288,MATCH($A73,Prospectos!$A$2:$A$288,0)),"") -> Río Tercero | G73: =IFERROR(INDEX(Prospectos!$K$2:$K$288,MATCH($A73,Prospectos!$A$2:$A$288,0)),"") -> A relevar | H73: =IFERROR(INDEX(Prospectos!$M$2:$M$288,MATCH($A73,Prospectos!$A$2:$A$288,0)),"") -> planta / mantenimiento | I73: =IFERROR(INDEX(Prospectos!$N$2:$N$288,MATCH($A73,Prospectos!$A$2:$A$288,0)),"") -> Movimiento de premoldeados, equipos de planta/cantera, bombas, moldes y cargas pesadas. | J73: =IFERROR(INDEX(Prospectos!$AJ$2:$AJ$288,MATCH($A73,Prospectos!$A$2:$A$288,0)),"") -> Baja / visitar solo por cercanía
A74: COR-001 | B74: =IFERROR(INDEX(Prospectos!$F$2:$F$288,MATCH($A74,Prospectos!$A$2:$A$288,0)),"") -> A | C74: =IFERROR(INDEX(Prospectos!$H$2:$H$288,MATCH($A74,Prospectos!$A$2:$A$288,0)),"") -> AGD — Planta de Acopio Corralito | D74: =IFERROR(INDEX(Prospectos!$J$2:$J$288,MATCH($A74,Prospectos!$A$2:$A$288,0)),"") -> Agroindustria y alimentos | E74: =IFERROR(INDEX(Prospectos!$C$2:$C$288,MATCH($A74,Prospectos!$A$2:$A$288,0)),"") -> Corralito / acceso secundario RN36 | F74: =IFERROR(INDEX(Prospectos!$E$2:$E$288,MATCH($A74,Prospectos!$A$2:$A$288,0)),"") -> Corralito | G74: =IFERROR(INDEX(Prospectos!$K$2:$K$288,MATCH($A74,Prospectos!$A$2:$A$288,0)),"") -> 03571 492144 / 492172 / 492228 | H74: =IFERROR(INDEX(Prospectos!$M$2:$M$288,MATCH($A74,Prospectos!$A$2:$A$288,0)),"") -> responsable de acopio / mantenimiento | I74: =IFERROR(INDEX(Prospectos!$N$2:$N$288,MATCH($A74,Prospectos!$A$2:$A$288,0)),"") -> Traslado de equipos de planta, silos, repuestos pesados, balanzas, implementos y cargas especiales. | J74: =IFERROR(INDEX(Prospectos!$AJ$2:$AJ$288,MATCH($A74,Prospectos!$A$2:$A$288,0)),"") -> Muy alta
A75: COR-002 | B75: =IFERROR(INDEX(Prospectos!$F$2:$F$288,MATCH($A75,Prospectos!$A$2:$A$288,0)),"") -> B | C75: =IFERROR(INDEX(Prospectos!$H$2:$H$288,MATCH($A75,Prospectos!$A$2:$A$288,0)),"") -> Trisoil S.A. | D75: =IFERROR(INDEX(Prospectos!$J$2:$J$288,MATCH($A75,Prospectos!$A$2:$A$288,0)),"") -> Agroindustria y alimentos | E75: =IFERROR(INDEX(Prospectos!$C$2:$C$288,MATCH($A75,Prospectos!$A$2:$A$288,0)),"") -> Corralito / acceso secundario RN36 | F75: =IFERROR(INDEX(Prospectos!$E$2:$E$288,MATCH($A75,Prospectos!$A$2:$A$288,0)),"") -> Corralito | G75: =IFERROR(INDEX(Prospectos!$K$2:$K$288,MATCH($A75,Prospectos!$A$2:$A$288,0)),"") -> 03571 502525 / 502526 | H75: =IFERROR(INDEX(Prospectos!$M$2:$M$288,MATCH($A75,Prospectos!$A$2:$A$288,0)),"") -> mantenimiento / compras | I75: =IFERROR(INDEX(Prospectos!$N$2:$N$288,MATCH($A75,Prospectos!$A$2:$A$288,0)),"") -> Traslado de equipos de planta, silos, repuestos pesados, balanzas, implementos y cargas especiales. | J75: =IFERROR(INDEX(Prospectos!$AJ$2:$AJ$288,MATCH($A75,Prospectos!$A$2:$A$288,0)),"") -> Alta
A76: TAN-001 | B76: =IFERROR(INDEX(Prospectos!$F$2:$F$288,MATCH($A76,Prospectos!$A$2:$A$288,0)),"") -> A | C76: =IFERROR(INDEX(Prospectos!$H$2:$H$288,MATCH($A76,Prospectos!$A$2:$A$288,0)),"") -> A&F / BRUNI Implementos Agrícolas | D76: =IFERROR(INDEX(Prospectos!$J$2:$J$288,MATCH($A76,Prospectos!$A$2:$A$288,0)),"") -> Maquinaria agrícola | E76: =IFERROR(INDEX(Prospectos!$C$2:$C$288,MATCH($A76,Prospectos!$A$2:$A$288,0)),"") -> Corralito / acceso secundario RN36 | F76: =IFERROR(INDEX(Prospectos!$E$2:$E$288,MATCH($A76,Prospectos!$A$2:$A$288,0)),"") -> Tancacha | G76: =IFERROR(INDEX(Prospectos!$K$2:$K$288,MATCH($A76,Prospectos!$A$2:$A$288,0)),"") -> +54 3571 576545 / +54 9 3571 314413 | H76: =IFERROR(INDEX(Prospectos!$M$2:$M$288,MATCH($A76,Prospectos!$A$2:$A$288,0)),"") -> logística / despacho / postventa | I76: =IFERROR(INDEX(Prospectos!$N$2:$N$288,MATCH($A76,Prospectos!$A$2:$A$288,0)),"") -> Traslado de maquinaria, implementos, equipos terminados y componentes de gran porte entre planta, cliente, obra o feria. | J76: =IFERROR(INDEX(Prospectos!$AJ$2:$AJ$288,MATCH($A76,Prospectos!$A$2:$A$288,0)),"") -> Muy alta
... A139: ONC-004 | B139: =IFERROR(INDEX(Prospectos!$F$2:$F$288,MATCH($A139,Prospectos!$A$2:$A$288,0)),"") -> A | C139: =IFERROR(INDEX(Prospectos!$H$2:$H$288,MATCH($A139,Prospectos!$A$2:$A$288,0)),"") -> Metalúrgica Cerquatti | D139: =IFERROR(INDEX(Prospectos!$J$2:$J$288,MATCH($A139,Prospectos!$A$2:$A$288,0)),"") -> Módulos y contenedores | E139: =IFERROR(INDEX(Prospectos!$C$2:$C$288,MATCH($A139,Prospectos!$A$2:$A$288,0)),"") -> Oncativo / RN9 | F139: =IFERROR(INDEX(Prospectos!$E$2:$E$288,MATCH($A139,Prospectos!$A$2:$A$288,0)),"") -> Oncativo | G139: =IFERROR(INDEX(Prospectos!$K$2:$K$288,MATCH($A139,Prospectos!$A$2:$A$288,0)),"") -> 03572 456573 / 03572 504462 | H139: =IFERROR(INDEX(Prospectos!$M$2:$M$288,MATCH($A139,Prospectos!$A$2:$A$288,0)),"") -> logística / despacho / postventa | I139: =IFERROR(INDEX(Prospectos!$N$2:$N$288,MATCH($A139,Prospectos!$A$2:$A$288,0)),"") -> Traslado de maquinaria, implementos, equipos terminados y componentes de gran porte entre planta, cliente, obra o feria. | J139: =IFERROR(INDEX(Prospectos!$AJ$2:$AJ$288,MATCH($A139,Prospectos!$A$2:$A$288,0)),"") -> Muy alta
A140: ONC-026 | B140: =IFERROR(INDEX(Prospectos!$F$2:$F$288,MATCH($A140,Prospectos!$A$2:$A$288,0)),"") -> A | C140: =IFERROR(INDEX(Prospectos!$H$2:$H$288,MATCH($A140,Prospectos!$A$2:$A$288,0)),"") -> Scaramuzza Maquinarias | D140: =IFERROR(INDEX(Prospectos!$J$2:$J$288,MATCH($A140,Prospectos!$A$2:$A$288,0)),"") -> Maquinaria agrícola | E140: =IFERROR(INDEX(Prospectos!$C$2:$C$288,MATCH($A140,Prospectos!$A$2:$A$288,0)),"") -> Oncativo / RN9 | F140: =IFERROR(INDEX(Prospectos!$E$2:$E$288,MATCH($A140,Prospectos!$A$2:$A$288,0)),"") -> Oncativo | G140: =IFERROR(INDEX(Prospectos!$K$2:$K$288,MATCH($A140,Prospectos!$A$2:$A$288,0)),"") -> 03572 583983 | H140: =IFERROR(INDEX(Prospectos!$M$2:$M$288,MATCH($A140,Prospectos!$A$2:$A$288,0)),"") -> logística / entregas / usados / postventa / gerente comercial | I140: =IFERROR(INDEX(Prospectos!$N$2:$N$288,MATCH($A140,Prospectos!$A$2:$A$288,0)),"") -> Entrega y retiro de tractores, cosechadoras, pulverizadoras, sembradoras e implementos; movimientos por ventas, canjes, usados, service, demostraciones y ferias. | J140: =IFERROR(INDEX(Prospectos!$AJ$2:$AJ$288,MATCH($A140,Prospectos!$A$2:$A$288,0)),"") -> Muy alta | K140: ANDRES SCARAMUZA
A141: ONC-005 | B141: =IFERROR(INDEX(Prospectos!$F$2:$F$288,MATCH($A141,Prospectos!$A$2:$A$288,0)),"") -> A | C141: =IFERROR(INDEX(Prospectos!$H$2:$H$288,MATCH($A141,Prospectos!$A$2:$A$288,0)),"") -> Scorza | D141: =IFERROR(INDEX(Prospectos!$J$2:$J$288,MATCH($A141,Prospectos!$A$2:$A$288,0)),"") -> Industria y mantenimiento | E141: =IFERROR(INDEX(Prospectos!$C$2:$C$288,MATCH($A141,Prospectos!$A$2:$A$288,0)),"") -> Oncativo / RN9 | F141: =IFERROR(INDEX(Prospectos!$E$2:$E$288,MATCH($A141,Prospectos!$A$2:$A$288,0)),"") -> Oncativo | G141: =IFERROR(INDEX(Prospectos!$K$2:$K$288,MATCH($A141,Prospectos!$A$2:$A$288,0)),"") -> 03572 466092 / 03572 665388 | H141: =IFERROR(INDEX(Prospectos!$M$2:$M$288,MATCH($A141,Prospectos!$A$2:$A$288,0)),"") -> logística / despacho / postventa | I141: =IFERROR(INDEX(Prospectos!$N$2:$N$288,MATCH($A141,Prospectos!$A$2:$A$288,0)),"") -> Traslado de maquinaria, implementos, equipos terminados y componentes de gran porte entre planta, cliente, obra o feria. | J141: =IFERROR(INDEX(Prospectos!$AJ$2:$AJ$288,MATCH($A141,Prospectos!$A$2:$A$288,0)),"") -> Muy alta
A142: ONC-029 | B142: =IFERROR(INDEX(Prospectos!$F$2:$F$288,MATCH($A142,Prospectos!$A$2:$A$288,0)),"") -> A | C142: =IFERROR(INDEX(Prospectos!$H$2:$H$288,MATCH($A142,Prospectos!$A$2:$A$288,0)),"") -> Ulla Maquinarias — Oncativo | D142: =IFERROR(INDEX(Prospectos!$J$2:$J$288,MATCH($A142,Prospectos!$A$2:$A$288,0)),"") -> Maquinaria agrícola | E142: =IFERROR(INDEX(Prospectos!$C$2:$C$288,MATCH($A142,Prospectos!$A$2:$A$288,0)),"") -> Oncativo / RN9 | F142: =IFERROR(INDEX(Prospectos!$E$2:$E$288,MATCH($A142,Prospectos!$A$2:$A$288,0)),"") -> Oncativo | G142: =IFERROR(INDEX(Prospectos!$K$2:$K$288,MATCH($A142,Prospectos!$A$2:$A$288,0)),"") -> 03572 460280 / 03572 437309 | H142: =IFERROR(INDEX(Prospectos!$M$2:$M$288,MATCH($A142,Prospectos!$A$2:$A$288,0)),"") -> logística / entregas / usados / postventa / gerente comercial | I142: =IFERROR(INDEX(Prospectos!$N$2:$N$288,MATCH($A142,Prospectos!$A$2:$A$288,0)),"") -> Entrega y retiro de tractores, cosechadoras, pulverizadoras, sembradoras e implementos; movimientos por ventas, canjes, usados, service, demostraciones y ferias. | J142: =IFERROR(INDEX(Prospectos!$AJ$2:$AJ$288,MATCH($A142,Prospectos!$A$2:$A$288,0)),"") -> Muy alta
A143: ONC-027 | B143: =IFERROR(INDEX(Prospectos!$F$2:$F$288,MATCH($A143,Prospectos!$A$2:$A$288,0)),"") -> A | C143: =IFERROR(INDEX(Prospectos!$H$2:$H$288,MATCH($A143,Prospectos!$A$2:$A$288,0)),"") -> Gallagro — Oncativo | D143: =IFERROR(INDEX(Prospectos!$J$2:$J$288,MATCH($A143,Prospectos!$A$2:$A$288,0)),"") -> Maquinaria agrícola | E143: =IFERROR(INDEX(Prospectos!$C$2:$C$288,MATCH($A143,Prospectos!$A$2:$A$288,0)),"") -> Oncativo / RN9 | F143: =IFERROR(INDEX(Prospectos!$E$2:$E$288,MATCH($A143,Prospectos!$A$2:$A$288,0)),"") -> Oncativo | G143: =IFERROR(INDEX(Prospectos!$K$2:$K$288,MATCH($A143,Prospectos!$A$2:$A$288,0)),"") -> 03572 516403 / +54 9 3584 11-3348 | H143: =IFERROR(INDEX(Prospectos!$M$2:$M$288,MATCH($A143,Prospectos!$A$2:$A$288,0)),"") -> logística / entregas / usados / postventa / gerente comercial | I143: =IFERROR(INDEX(Prospectos!$N$2:$N$288,MATCH($A143,Prospectos!$A$2:$A$288,0)),"") -> Entrega y retiro de tractores, cosechadoras, pulverizadoras, sembradoras e implementos; movimientos por ventas, canjes, usados, service, demostraciones y ferias. | J143: =IFERROR(INDEX(Prospectos!$AJ$2:$AJ$288,MATCH($A143,Prospectos!$A$2:$A$288,0)),"") -> Muy alta
A144: ONC-025 | B144: =IFERROR(INDEX(Prospectos!$F$2:$F$288,MATCH($A144,Prospectos!$A$2:$A$288,0)),"") -> A | C144: =IFERROR(INDEX(Prospectos!$H$2:$H$288,MATCH($A144,Prospectos!$A$2:$A$288,0)),"") -> Zuppa Hermanos — Oncativo | D144: =IFERROR(INDEX(Prospectos!$J$2:$J$288,MATCH($A144,Prospectos!$A$2:$A$288,0)),"") -> PRFV y plásticos | E144: =IFERROR(INDEX(Prospectos!$C$2:$C$288,MATCH($A144,Prospectos!$A$2:$A$288,0)),"") -> Oncativo / RN9 | F144: =IFERROR(INDEX(Prospectos!$E$2:$E$288,MATCH($A144,Prospectos!$A$2:$A$288,0)),"") -> Oncativo | G144: =IFERROR(INDEX(Prospectos!$K$2:$K$288,MATCH($A144,Prospectos!$A$2:$A$288,0)),"") -> 03572 455799 / +54 9 351 5646558 | H144: =IFERROR(INDEX(Prospectos!$M$2:$M$288,MATCH($A144,Prospectos!$A$2:$A$288,0)),"") -> logística / instalaciones / obras / ventas | I144: =IFERROR(INDEX(Prospectos!$N$2:$N$288,MATCH($A144,Prospectos!$A$2:$A$288,0)),"") -> Entrega de piscinas de fibra desde depósito/franquicia hasta domicilio y apoyo de grúa cuando el casco debe superar medianeras, techos o accesos angostos. | J144: =IFERROR(INDEX(Prospectos!$AJ$2:$AJ$288,MATCH($A144,Prospectos!$A$2:$A$288,0)),"") -> Muy alta | K144: ANAHI ZUPPA
A145: ONC-023 | B145: =IFERROR(INDEX(Prospectos!$F$2:$F$288,MATCH($A145,Prospectos!$A$2:$A$288,0)),"") -> A | C145: =IFERROR(INDEX(Prospectos!$H$2:$H$288,MATCH($A145,Prospectos!$A$2:$A$288,0)),"") -> Econovo Agrovial / Farmtrac | D145: =IFERROR(INDEX(Prospectos!$J$2:$J$288,MATCH($A145,Prospectos!$A$2:$A$288,0)),"") -> Maquinaria agrícola | E145: =IFERROR(INDEX(Prospectos!$C$2:$C$288,MATCH($A145,Prospectos!$A$2:$A$288,0)),"") -> Oncativo / RN9 | F145: =IFERROR(INDEX(Prospectos!$E$2:$E$288,MATCH($A145,Prospectos!$A$2:$A$288,0)),"") -> Oncativo | G145: =IFERROR(INDEX(Prospectos!$K$2:$K$288,MATCH($A145,Prospectos!$A$2:$A$288,0)),"") -> +54 3572 462665 | H145: =IFERROR(INDEX(Prospectos!$M$2:$M$288,MATCH($A145,Prospectos!$A$2:$A$288,0)),"") -> logística / ventas / postventa | I145: =IFERROR(INDEX(Prospectos!$N$2:$N$288,MATCH($A145,Prospectos!$A$2:$A$288,0)),"") -> Entrega y retiro de tractores, cosechadoras, pulverizadoras, sembradoras e implementos; movimientos por venta, service, canje, demostraciones o ferias. | J145: =IFERROR(INDEX(Prospectos!$AJ$2:$AJ$288,MATCH($A145,Prospectos!$A$2:$A$288,0)),"") -> Muy alta | K145: DUEÑO PUPI SCORZA O HIJOS GUILLERMO SORIA VENDEDOR
A146: ONC-024 | B146: =IFERROR(INDEX(Prospectos!$F$2:$F$288,MATCH($A146,Prospectos!$A$2:$A$288,0)),"") -> A | C146: =IFERROR(INDEX(Prospectos!$H$2:$H$288,MATCH($A146,Prospectos!$A$2:$A$288,0)),"") -> Quevedo Canavese | D146: =IFERROR(INDEX(Prospectos!$J$2:$J$288,MATCH($A146,Prospectos!$A$2:$A$288,0)),"") -> Maquinaria agrícola | E146: =IFERROR(INDEX(Prospectos!$C$2:$C$288,MATCH($A146,Prospectos!$A$2:$A$288,0)),"") -> Oncativo / RN9 | F146: =IFERROR(INDEX(Prospectos!$E$2:$E$288,MATCH($A146,Prospectos!$A$2:$A$288,0)),"") -> Oncativo | G146: =IFERROR(INDEX(Prospectos!$K$2:$K$288,MATCH($A146,Prospectos!$A$2:$A$288,0)),"") -> +54 9 3572 532536 / +54 9 3572 548804 | H146: =IFERROR(INDEX(Prospectos!$M$2:$M$288,MATCH($A146,Prospectos!$A$2:$A$288,0)),"") -> logística / ventas / postventa | I146: =IFERROR(INDEX(Prospectos!$N$2:$N$288,MATCH($A146,Prospectos!$A$2:$A$288,0)),"") -> Entrega y retiro de tractores, cosechadoras, pulverizadoras, sembradoras e implementos; movimientos por venta, service, canje, demostraciones o ferias. | J146: =IFERROR(INDEX(Prospectos!$AJ$2:$AJ$288,MATCH($A146,Prospectos!$A$2:$A$288,0)),"") -> Muy alta
A147: ONC-028 | B147: =IFERROR(INDEX(Prospectos!$F$2:$F$288,MATCH($A147,Prospectos!$A$2:$A$288,0)),"") -> A | C147: =IFERROR(INDEX(Prospectos!$H$2:$H$288,MATCH($A147,Prospectos!$A$2:$A$288,0)),"") -> Ramón A. Ramb Maquinaria | D147: =IFERROR(INDEX(Prospectos!$J$2:$J$288,MATCH($A147,Prospectos!$A$2:$A$288,0)),"") -> Maquinaria agrícola | E147: =IFERROR(INDEX(Prospectos!$C$2:$C$288,MATCH($A147,Prospectos!$A$2:$A$288,0)),"") -> Oncativo / RN9 | F147: =IFERROR(INDEX(Prospectos!$E$2:$E$288,MATCH($A147,Prospectos!$A$2:$A$288,0)),"") -> Oncativo | G147: =IFERROR(INDEX(Prospectos!$K$2:$K$288,MATCH($A147,Prospectos!$A$2:$A$288,0)),"") -> 03572 466841 | H147: =IFERROR(INDEX(Prospectos!$M$2:$M$288,MATCH($A147,Prospectos!$A$2:$A$288,0)),"") -> logística / entregas / usados / postventa / gerente comercial | I147: =IFERROR(INDEX(Prospectos!$N$2:$N$288,MATCH($A147,Prospectos!$A$2:$A$288,0)),"") -> Entrega y retiro de tractores, cosechadoras, pulverizadoras, sembradoras e implementos; movimientos por ventas, canjes, usados, service, demostraciones y ferias. | J147: =IFERROR(INDEX(Prospectos!$AJ$2:$AJ$288,MATCH($A147,Prospectos!$A$2:$A$288,0)),"") -> Alta
A148: ONC-006 | B148: =IFERROR(INDEX(Prospectos!$F$2:$F$288,MATCH($A148,Prospectos!$A$2:$A$288,0)),"") -> A | C148: =IFERROR(INDEX(Prospectos!$H$2:$H$288,MATCH($A148,Prospectos!$A$2:$A$288,0)),"") -> Agropartes S.A. | D148: =IFERROR(INDEX(Prospectos!$J$2:$J$288,MATCH($A148,Prospectos!$A$2:$A$288,0)),"") -> Maquinaria agrícola | E148: =IFERROR(INDEX(Prospectos!$C$2:$C$288,MATCH($A148,Prospectos!$A$2:$A$288,0)),"") -> Oncativo / RN9 | F148: =IFERROR(INDEX(Prospectos!$E$2:$E$288,MATCH($A148,Prospectos!$A$2:$A$288,0)),"") -> Oncativo | G148: =IFERROR(INDEX(Prospectos!$K$2:$K$288,MATCH($A148,Prospectos!$A$2:$A$288,0)),"") -> 03572 456204 / 03572 466314 | H148: =IFERROR(INDEX(Prospectos!$M$2:$M$288,MATCH($A148,Prospectos!$A$2:$A$288,0)),"") -> logística / despacho / postventa | I148: =IFERROR(INDEX(Prospectos!$N$2:$N$288,MATCH($A148,Prospectos!$A$2:$A$288,0)),"") -> Traslado de maquinaria, implementos, equipos terminados y componentes de gran porte entre planta, cliente, obra o feria. | J148: =IFERROR(INDEX(Prospectos!$AJ$2:$AJ$288,MATCH($A148,Prospectos!$A$2:$A$288,0)),"") -> Muy alta
A149: ONC-007 | B149: =IFERROR(INDEX(Prospectos!$F$2:$F$288,MATCH($A149,Prospectos!$A$2:$A$288,0)),"") -> A | C149: =IFERROR(INDEX(Prospectos!$H$2:$H$288,MATCH($A149,Prospectos!$A$2:$A$288,0)),"") -> Fertimaq | D149: =IFERROR(INDEX(Prospectos!$J$2:$J$288,MATCH($A149,Prospectos!$A$2:$A$288,0)),"") -> Industria y mantenimiento | E149: =IFERROR(INDEX(Prospectos!$C$2:$C$288,MATCH($A149,Prospectos!$A$2:$A$288,0)),"") -> Oncativo / RN9 | F149: =IFERROR(INDEX(Prospectos!$E$2:$E$288,MATCH($A149,Prospectos!$A$2:$A$288,0)),"") -> Oncativo | G149: =IFERROR(INDEX(Prospectos!$K$2:$K$288,MATCH($A149,Prospectos!$A$2:$A$288,0)),"") -> 03572 458660 | H149: =IFERROR(INDEX(Prospectos!$M$2:$M$288,MATCH($A149,Prospectos!$A$2:$A$288,0)),"") -> logística / entregas / postventa | I149: =IFERROR(INDEX(Prospectos!$N$2:$N$288,MATCH($A149,Prospectos!$A$2:$A$288,0)),"") -> Traslado de maquinaria agrícola o vial entre sucursal, cliente, taller, campo y eventos. | J149: =IFERROR(INDEX(Prospectos!$AJ$2:$AJ$288,MATCH($A149,Prospectos!$A$2:$A$288,0)),"") -> Muy alta
A150: ONC-009 | B150: =IFERROR(INDEX(Prospectos!$F$2:$F$288,MATCH($A150,Prospectos!$A$2:$A$288,0)),"") -> A | C150: =IFERROR(INDEX(Prospectos!$H$2:$H$288,MATCH($A150,Prospectos!$A$2:$A$288,0)),"") -> San Isidro Maquinarias | D150: =IFERROR(INDEX(Prospectos!$J$2:$J$288,MATCH($A150,Prospectos!$A$2:$A$288,0)),"") -> Maquinaria agrícola | E150: =IFERROR(INDEX(Prospectos!$C$2:$C$288,MATCH($A150,Prospectos!$A$2:$A$288,0)),"") -> Oncativo / RN9 | F150: =IFERROR(INDEX(Prospectos!$E$2:$E$288,MATCH($A150,Prospectos!$A$2:$A$288,0)),"") -> Oncativo | G150: =IFERROR(INDEX(Prospectos!$K$2:$K$288,MATCH($A150,Prospectos!$A$2:$A$288,0)),"") -> 03572 561450 | H150: =IFERROR(INDEX(Prospectos!$M$2:$M$288,MATCH($A150,Prospectos!$A$2:$A$288,0)),"") -> logística / entregas / postventa | I150: =IFERROR(INDEX(Prospectos!$N$2:$N$288,MATCH($A150,Prospectos!$A$2:$A$288,0)),"") -> Traslado de maquinaria agrícola o vial entre sucursal, cliente, taller, campo y eventos. | J150: =IFERROR(INDEX(Prospectos!$AJ$2:$AJ$288,MATCH($A150,Prospectos!$A$2:$A$288,0)),"") -> Muy alta | K150: OMAR SEGURA
A151: ONC-008 | B151: =IFERROR(INDEX(Prospectos!$F$2:$F$288,MATCH($A151,Prospectos!$A$2:$A$288,0)),"") -> A | C151: =IFERROR(INDEX(Prospectos!$H$2:$H$288,MATCH($A151,Prospectos!$A$2:$A$288,0)),"") -> SICA S.A. - Fabricación y Venta | D151: =IFERROR(INDEX(Prospectos!$J$2:$J$288,MATCH($A151,Prospectos!$A$2:$A$288,0)),"") -> Metalúrgica y fabricación | E151: =IFERROR(INDEX(Prospectos!$C$2:$C$288,MATCH($A151,Prospectos!$A$2:$A$288,0)),"") -> Oncativo / RN9 | F151: =IFERROR(INDEX(Prospectos!$E$2:$E$288,MATCH($A151,Prospectos!$A$2:$A$288,0)),"") -> Oncativo | G151: =IFERROR(INDEX(Prospectos!$K$2:$K$288,MATCH($A151,Prospectos!$A$2:$A$288,0)),"") -> 03572 460958 | H151: =IFERROR(INDEX(Prospectos!$M$2:$M$288,MATCH($A151,Prospectos!$A$2:$A$288,0)),"") -> mantenimiento / despacho | I151: =IFERROR(INDEX(Prospectos!$N$2:$N$288,MATCH($A151,Prospectos!$A$2:$A$288,0)),"") -> Movimientos especiales de mantenimiento, repuestos pesados, equipos y mudanzas internas o entre plantas. | J151: =IFERROR(INDEX(Prospectos!$AJ$2:$AJ$288,MATCH($A151,Prospectos!$A$2:$A$288,0)),"") -> Muy alta
A152: ONC-010 | B152: =IFERROR(INDEX(Prospectos!$F$2:$F$288,MATCH($A152,Prospectos!$A$2:$A$288,0)),"") -> A | C152: =IFERROR(INDEX(Prospectos!$H$2:$H$288,MATCH($A152,Prospectos!$A$2:$A$288,0)),"") -> Vial Truck S.A. | D152: =IFERROR(INDEX(Prospectos!$J$2:$J$288,MATCH($A152,Prospectos!$A$2:$A$288,0)),"") -> Industria y mantenimiento | E152: =IFERROR(INDEX(Prospectos!$C$2:$C$288,MATCH($A152,Prospectos!$A$2:$A$288,0)),"") -> Oncativo / RN9 | F152: =IFERROR(INDEX(Prospectos!$E$2:$E$288,MATCH($A152,Prospectos!$A$2:$A$288,0)),"") -> Oncativo | G152: =IFERROR(INDEX(Prospectos!$K$2:$K$288,MATCH($A152,Prospectos!$A$2:$A$288,0)),"") -> 03572 455688 | H152: =IFERROR(INDEX(Prospectos!$M$2:$M$288,MATCH($A152,Prospectos!$A$2:$A$288,0)),"") -> logística / despacho / postventa | I152: =IFERROR(INDEX(Prospectos!$N$2:$N$288,MATCH($A152,Prospectos!$A$2:$A$288,0)),"") -> Traslado de maquinaria, implementos, equipos terminados y componentes de gran porte entre planta, cliente, obra o feria. | J152: =IFERROR(INDEX(Prospectos!$AJ$2:$AJ$288,MATCH($A152,Prospectos!$A$2:$A$288,0)),"") -> Muy alta
A153: ONC-011 | B153: =IFERROR(INDEX(Prospectos!$F$2:$F$288,MATCH($A153,Prospectos!$A$2:$A$288,0)),"") -> B | C153: =IFERROR(INDEX(Prospectos!$H$2:$H$288,MATCH($A153,Prospectos!$A$2:$A$288,0)),"") -> Metalúrgica Rosas | D153: =IFERROR(INDEX(Prospectos!$J$2:$J$288,MATCH($A153,Prospectos!$A$2:$A$288,0)),"") -> Metalúrgica y fabricación | E153: =IFERROR(INDEX(Prospectos!$C$2:$C$288,MATCH($A153,Prospectos!$A$2:$A$288,0)),"") -> Oncativo / RN9 | F153: =IFERROR(INDEX(Prospectos!$E$2:$E$288,MATCH($A153,Prospectos!$A$2:$A$288,0)),"") -> Oncativo | G153: =IFERROR(INDEX(Prospectos!$K$2:$K$288,MATCH($A153,Prospectos!$A$2:$A$288,0)),"") -> +54 9 3572 549003 / 03572 15617489 | H153: =IFERROR(INDEX(Prospectos!$M$2:$M$288,MATCH($A153,Prospectos!$A$2:$A$288,0)),"") -> despacho / producción | I153: =IFERROR(INDEX(Prospectos!$N$2:$N$288,MATCH($A153,Prospectos!$A$2:$A$288,0)),"") -> Despacho de estructuras, piezas, equipos y conjuntos metalmecánicos de gran porte hacia obras o clientes. | J153: =IFERROR(INDEX(Prospectos!$AJ$2:$AJ$288,MATCH($A153,Prospectos!$A$2:$A$288,0)),"") -> Alta
A154: ONC-012 | B154: =IFERROR(INDEX(Prospectos!$F$2:$F$288,MATCH($A154,Prospectos!$A$2:$A$288,0)),"") -> B | C154: =IFERROR(INDEX(Prospectos!$H$2:$H$288,MATCH($A154,Prospectos!$A$2:$A$288,0)),"") -> Bartolomé Cerutti SRL | D154: =IFERROR(INDEX(Prospectos!$J$2:$J$288,MATCH($A154,Prospectos!$A$2:$A$288,0)),"") -> Maquinaria agrícola | E154: =IFERROR(INDEX(Prospectos!$C$2:$C$288,MATCH($A154,Prospectos!$A$2:$A$288,0)),"") -> Oncativo / RN9 | F154: =IFERROR(INDEX(Prospectos!$E$2:$E$288,MATCH($A154,Prospectos!$A$2:$A$288,0)),"") -> Oncativo | G154: =IFERROR(INDEX(Prospectos!$K$2:$K$288,MATCH($A154,Prospectos!$A$2:$A$288,0)),"") -> 03572 460754 | H154: =IFERROR(INDEX(Prospectos!$M$2:$M$288,MATCH($A154,Prospectos!$A$2:$A$288,0)),"") -> logística / entregas / postventa | I154: =IFERROR(INDEX(Prospectos!$N$2:$N$288,MATCH($A154,Prospectos!$A$2:$A$288,0)),"") -> Traslado de maquinaria agrícola o vial entre sucursal, cliente, taller, campo y eventos. | J154: =IFERROR(INDEX(Prospectos!$AJ$2:$AJ$288,MATCH($A154,Prospectos!$A$2:$A$288,0)),"") -> Alta
A155: ONC-013 | B155: =IFERROR(INDEX(Prospectos!$F$2:$F$288,MATCH($A155,Prospectos!$A$2:$A$288,0)),"") -> B | C155: =IFERROR(INDEX(Prospectos!$H$2:$H$288,MATCH($A155,Prospectos!$A$2:$A$288,0)),"") -> E Postacchini S.A.S. | D155: =IFERROR(INDEX(Prospectos!$J$2:$J$288,MATCH($A155,Prospectos!$A$2:$A$288,0)),"") -> Maquinaria agrícola | E155: =IFERROR(INDEX(Prospectos!$C$2:$C$288,MATCH($A155,Prospectos!$A$2:$A$288,0)),"") -> Oncativo / RN9 | F155: =IFERROR(INDEX(Prospectos!$E$2:$E$288,MATCH($A155,Prospectos!$A$2:$A$288,0)),"") -> Oncativo | G155: =IFERROR(INDEX(Prospectos!$K$2:$K$288,MATCH($A155,Prospectos!$A$2:$A$288,0)),"") -> A relevar | H155: =IFERROR(INDEX(Prospectos!$M$2:$M$288,MATCH($A155,Prospectos!$A$2:$A$288,0)),"") -> logística / entregas / postventa | I155: =IFERROR(INDEX(Prospectos!$N$2:$N$288,MATCH($A155,Prospectos!$A$2:$A$288,0)),"") -> Traslado de maquinaria agrícola o vial entre sucursal, cliente, taller, campo y eventos. | J155: =IFERROR(INDEX(Prospectos!$AJ$2:$AJ$288,MATCH($A155,Prospectos!$A$2:$A$288,0)),"") -> Media
A156: ONC-014 | B156: =IFERROR(INDEX(Prospectos!$F$2:$F$288,MATCH($A156,Prospectos!$A$2:$A$288,0)),"") -> B | C156: =IFERROR(INDEX(Prospectos!$H$2:$H$288,MATCH($A156,Prospectos!$A$2:$A$288,0)),"") -> Serra Obras y Redes | D156: =IFERROR(INDEX(Prospectos!$J$2:$J$288,MATCH($A156,Prospectos!$A$2:$A$288,0)),"") -> Construcción y obra vial | E156: =IFERROR(INDEX(Prospectos!$C$2:$C$288,MATCH($A156,Prospectos!$A$2:$A$288,0)),"") -> Oncativo / RN9 | F156: =IFERROR(INDEX(Prospectos!$E$2:$E$288,MATCH($A156,Prospectos!$A$2:$A$288,0)),"") -> Oncativo | G156: =IFERROR(INDEX(Prospectos!$K$2:$K$288,MATCH($A156,Prospectos!$A$2:$A$288,0)),"") -> 03572 436146 | H156: =IFERROR(INDEX(Prospectos!$M$2:$M$288,MATCH($A156,Prospectos!$A$2:$A$288,0)),"") -> jefe de obra / operaciones | I156: =IFERROR(INDEX(Prospectos!$N$2:$N$288,MATCH($A156,Prospectos!$A$2:$A$288,0)),"") -> Traslado de maquinaria, módulos de obrador, estructuras y equipos entre depósitos y frentes de obra. | J156: =IFERROR(INDEX(Prospectos!$AJ$2:$AJ$288,MATCH($A156,Prospectos!$A$2:$A$288,0)),"") -> Alta
A157: ONC-015 | B157: =IFERROR(INDEX(Prospectos!$F$2:$F$288,MATCH($A157,Prospectos!$A$2:$A$288,0)),"") -> B | C157: =IFERROR(INDEX(Prospectos!$H$2:$H$288,MATCH($A157,Prospectos!$A$2:$A$288,0)),"") -> Tantucci Construcciones | D157: =IFERROR(INDEX(Prospectos!$J$2:$J$288,MATCH($A157,Prospectos!$A$2:$A$288,0)),"") -> Construcción y obra vial | E157: =IFERROR(INDEX(Prospectos!$C$2:$C$288,MATCH($A157,Prospectos!$A$2:$A$288,0)),"") -> Oncativo / RN9 | F157: =IFERROR(INDEX(Prospectos!$E$2:$E$288,MATCH($A157,Prospectos!$A$2:$A$288,0)),"") -> Oncativo | G157: =IFERROR(INDEX(Prospectos!$K$2:$K$288,MATCH($A157,Prospectos!$A$2:$A$288,0)),"") -> 03572 402571 | H157: =IFERROR(INDEX(Prospectos!$M$2:$M$288,MATCH($A157,Prospectos!$A$2:$A$288,0)),"") -> jefe de obra / operaciones | I157: =IFERROR(INDEX(Prospectos!$N$2:$N$288,MATCH($A157,Prospectos!$A$2:$A$288,0)),"") -> Traslado de maquinaria, módulos de obrador, estructuras y equipos entre depósitos y frentes de obra. | J157: =IFERROR(INDEX(Prospectos!$AJ$2:$AJ$288,MATCH($A157,Prospectos!$A$2:$A$288,0)),"") -> Alta
A158: ONC-016 | B158: =IFERROR(INDEX(Prospectos!$F$2:$F$288,MATCH($A158,Prospectos!$A$2:$A$288,0)),"") -> B | C158: =IFERROR(INDEX(Prospectos!$H$2:$H$288,MATCH($A158,Prospectos!$A$2:$A$288,0)),"") -> Agro Repuestos Oncativo | D158: =IFERROR(INDEX(Prospectos!$J$2:$J$288,MATCH($A158,Prospectos!$A$2:$A$288,0)),"") -> Maquinaria agrícola | E158: =IFERROR(INDEX(Prospectos!$C$2:$C$288,MATCH($A158,Prospectos!$A$2:$A$288,0)),"") -> Oncativo / RN9 | F158: =IFERROR(INDEX(Prospectos!$E$2:$E$288,MATCH($A158,Prospectos!$A$2:$A$288,0)),"") -> Oncativo | G158: =IFERROR(INDEX(Prospectos!$K$2:$K$288,MATCH($A158,Prospectos!$A$2:$A$288,0)),"") -> 03572 466328 | H158: =IFERROR(INDEX(Prospectos!$M$2:$M$288,MATCH($A158,Prospectos!$A$2:$A$288,0)),"") -> logística / entregas / postventa | I158: =IFERROR(INDEX(Prospectos!$N$2:$N$288,MATCH($A158,Prospectos!$A$2:$A$288,0)),"") -> Traslado de maquinaria agrícola o vial entre sucursal, cliente, taller, campo y eventos. | J158: =IFERROR(INDEX(Prospectos!$AJ$2:$AJ$288,MATCH($A158,Prospectos!$A$2:$A$288,0)),"") -> Alta
A159: ONC-017 | B159: =IFERROR(INDEX(Prospectos!$F$2:$F$288,MATCH($A159,Prospectos!$A$2:$A$288,0)),"") -> C | C159: =IFERROR(INDEX(Prospectos!$H$2:$H$288,MATCH($A159,Prospectos!$A$2:$A$288,0)),"") -> Murature Oncativo S.A. | D159: =IFERROR(INDEX(Prospectos!$J$2:$J$288,MATCH($A159,Prospectos!$A$2:$A$288,0)),"") -> Agro, acopio y cooperativas | E159: =IFERROR(INDEX(Prospectos!$C$2:$C$288,MATCH($A159,Prospectos!$A$2:$A$288,0)),"") -> Oncativo / RN9 | F159: =IFERROR(INDEX(Prospectos!$E$2:$E$288,MATCH($A159,Prospectos!$A$2:$A$288,0)),"") -> Oncativo | G159: =IFERROR(INDEX(Prospectos!$K$2:$K$288,MATCH($A159,Prospectos!$A$2:$A$288,0)),"") -> A relevar | H159: =IFERROR(INDEX(Prospectos!$M$2:$M$288,MATCH($A159,Prospectos!$A$2:$A$288,0)),"") -> responsable de acopio / mantenimiento | I159: =IFERROR(INDEX(Prospectos!$N$2:$N$288,MATCH($A159,Prospectos!$A$2:$A$288,0)),"") -> Traslado de equipos de planta, silos, repuestos pesados, balanzas, implementos y cargas especiales. | J159: =IFERROR(INDEX(Prospectos!$AJ$2:$AJ$288,MATCH($A159,Prospectos!$A$2:$A$288,0)),"") -> Baja / visitar solo por cercanía
A160: ONC-018 | B160: =IFERROR(INDEX(Prospectos!$F$2:$F$288,MATCH($A160,Prospectos!$A$2:$A$288,0)),"") -> A | C160: =IFERROR(INDEX(Prospectos!$H$2:$H$288,MATCH($A160,Prospectos!$A$2:$A$288,0)),"") -> Cooperativa Agrícola Ganadera y de Consumo de Oncativo Ltda. | D160: =IFERROR(INDEX(Prospectos!$J$2:$J$288,MATCH($A160,Prospectos!$A$2:$A$288,0)),"") -> Agro, acopio y cooperativas | E160: =IFERROR(INDEX(Prospectos!$C$2:$C$288,MATCH($A160,Prospectos!$A$2:$A$288,0)),"") -> Oncativo / RN9-RP10 | F160: =IFERROR(INDEX(Prospectos!$E$2:$E$288,MATCH($A160,Prospectos!$A$2:$A$288,0)),"") -> Oncativo | G160: =IFERROR(INDEX(Prospectos!$K$2:$K$288,MATCH($A160,Prospectos!$A$2:$A$288,0)),"") -> 03572 456777 / 03572 15583757 | H160: =IFERROR(INDEX(Prospectos!$M$2:$M$288,MATCH($A160,Prospectos!$A$2:$A$288,0)),"") -> acopio / insumos / mantenimiento | I160: =IFERROR(INDEX(Prospectos!$N$2:$N$288,MATCH($A160,Prospectos!$A$2:$A$288,0)),"") -> Traslado de insumos, pallets, fertilizantes, repuestos pesados, silos/equipos y apoyo de mantenimiento en planta. | J160: =IFERROR(INDEX(Prospectos!$AJ$2:$AJ$288,MATCH($A160,Prospectos!$A$2:$A$288,0)),"") -> Muy alta
A161: ONC-019 | B161: =IFERROR(INDEX(Prospectos!$F$2:$F$288,MATCH($A161,Prospectos!$A$2:$A$288,0)),"") -> B | C161: =IFERROR(INDEX(Prospectos!$H$2:$H$288,MATCH($A161,Prospectos!$A$2:$A$288,0)),"") -> El Triunfo Oncativo | D161: =IFERROR(INDEX(Prospectos!$J$2:$J$288,MATCH($A161,Prospectos!$A$2:$A$288,0)),"") -> Agro, acopio y cooperativas | E161: =IFERROR(INDEX(Prospectos!$C$2:$C$288,MATCH($A161,Prospectos!$A$2:$A$288,0)),"") -> Oncativo / RN9-RP10 | F161: =IFERROR(INDEX(Prospectos!$E$2:$E$288,MATCH($A161,Prospectos!$A$2:$A$288,0)),"") -> Oncativo | G161: =IFERROR(INDEX(Prospectos!$K$2:$K$288,MATCH($A161,Prospectos!$A$2:$A$288,0)),"") -> 03572 466288 / +54 9 3572 408824 | H161: =IFERROR(INDEX(Prospectos!$M$2:$M$288,MATCH($A161,Prospectos!$A$2:$A$288,0)),"") -> acopio / logística / insumos | I161: =IFERROR(INDEX(Prospectos!$N$2:$N$288,MATCH($A161,Prospectos!$A$2:$A$288,0)),"") -> Traslado de insumos, pallets, fertilizantes, repuestos pesados, silos/equipos y apoyo de mantenimiento en planta. | J161: =IFERROR(INDEX(Prospectos!$AJ$2:$AJ$288,MATCH($A161,Prospectos!$A$2:$A$288,0)),"") -> Alta
A162: ONC-020 | B162: =IFERROR(INDEX(Prospectos!$F$2:$F$288,MATCH($A162,Prospectos!$A$2:$A$288,0)),"") -> B | C162: =IFERROR(INDEX(Prospectos!$H$2:$H$288,MATCH($A162,Prospectos!$A$2:$A$288,0)),"") -> IPC Oncativo / Piscinas IPC | D162: =IFERROR(INDEX(Prospectos!$J$2:$J$288,MATCH($A162,Prospectos!$A$2:$A$288,0)),"") -> PRFV y plásticos | E162: =IFERROR(INDEX(Prospectos!$C$2:$C$288,MATCH($A162,Prospectos!$A$2:$A$288,0)),"") -> Oncativo / RN9-RP10 | F162: =IFERROR(INDEX(Prospectos!$E$2:$E$288,MATCH($A162,Prospectos!$A$2:$A$288,0)),"") -> Oncativo | G162: =IFERROR(INDEX(Prospectos!$K$2:$K$288,MATCH($A162,Prospectos!$A$2:$A$288,0)),"") -> 3572 53-2233 | H162: =IFERROR(INDEX(Prospectos!$M$2:$M$288,MATCH($A162,Prospectos!$A$2:$A$288,0)),"") -> ventas / logística | I162: =IFERROR(INDEX(Prospectos!$N$2:$N$288,MATCH($A162,Prospectos!$A$2:$A$288,0)),"") -> Retiro, traslado y descarga de piletas/fibra o piezas voluminosas livianas, con cuidado de maniobra. | J162: =IFERROR(INDEX(Prospectos!$AJ$2:$AJ$288,MATCH($A162,Prospectos!$A$2:$A$288,0)),"") -> Alta
... A222: VA-003 | B222: =IFERROR(INDEX(Prospectos!$F$2:$F$288,MATCH($A222,Prospectos!$A$2:$A$288,0)),"") -> B | C222: =IFERROR(INDEX(Prospectos!$H$2:$H$288,MATCH($A222,Prospectos!$A$2:$A$288,0)),"") -> Construir Villa Ascasubi | D222: =IFERROR(INDEX(Prospectos!$J$2:$J$288,MATCH($A222,Prospectos!$A$2:$A$288,0)),"") -> Hormigón, áridos y materiales | E222: =IFERROR(INDEX(Prospectos!$C$2:$C$288,MATCH($A222,Prospectos!$A$2:$A$288,0)),"") -> Villa Ascasubi / RP6-E79 | F222: =IFERROR(INDEX(Prospectos!$E$2:$E$288,MATCH($A222,Prospectos!$A$2:$A$288,0)),"") -> Villa Ascasubi | G222: =IFERROR(INDEX(Prospectos!$K$2:$K$288,MATCH($A222,Prospectos!$A$2:$A$288,0)),"") -> 3571 577272 | H222: =IFERROR(INDEX(Prospectos!$M$2:$M$288,MATCH($A222,Prospectos!$A$2:$A$288,0)),"") -> dueño / compras / logística | I222: =IFERROR(INDEX(Prospectos!$N$2:$N$288,MATCH($A222,Prospectos!$A$2:$A$288,0)),"") -> Movimiento de áridos, premoldeados, equipos de planta/cantera, moldes, bolsones y materiales de obra. | J222: =IFERROR(INDEX(Prospectos!$AJ$2:$AJ$288,MATCH($A222,Prospectos!$A$2:$A$288,0)),"") -> Media
A223: VA-004 | B223: =IFERROR(INDEX(Prospectos!$F$2:$F$288,MATCH($A223,Prospectos!$A$2:$A$288,0)),"") -> B | C223: =IFERROR(INDEX(Prospectos!$H$2:$H$288,MATCH($A223,Prospectos!$A$2:$A$288,0)),"") -> La Vencedora — Sucursal Villa Ascasubi | D223: =IFERROR(INDEX(Prospectos!$J$2:$J$288,MATCH($A223,Prospectos!$A$2:$A$288,0)),"") -> Agro, acopio y cooperativas | E223: =IFERROR(INDEX(Prospectos!$C$2:$C$288,MATCH($A223,Prospectos!$A$2:$A$288,0)),"") -> Villa Ascasubi / RP6-E79 | F223: =IFERROR(INDEX(Prospectos!$E$2:$E$288,MATCH($A223,Prospectos!$A$2:$A$288,0)),"") -> Villa Ascasubi | G223: =IFERROR(INDEX(Prospectos!$K$2:$K$288,MATCH($A223,Prospectos!$A$2:$A$288,0)),"") -> A relevar | H223: =IFERROR(INDEX(Prospectos!$M$2:$M$288,MATCH($A223,Prospectos!$A$2:$A$288,0)),"") -> acopio / encargado de sucursal | I223: =IFERROR(INDEX(Prospectos!$N$2:$N$288,MATCH($A223,Prospectos!$A$2:$A$288,0)),"") -> Traslado de insumos, pallets, fertilizantes, repuestos pesados, silos/equipos y apoyo de mantenimiento en planta. | J223: ALTA
A224: ALM-003 | B224: =IFERROR(INDEX(Prospectos!$F$2:$F$288,MATCH($A224,Prospectos!$A$2:$A$288,0)),"") -> A | C224: =IFERROR(INDEX(Prospectos!$H$2:$H$288,MATCH($A224,Prospectos!$A$2:$A$288,0)),"") -> Servisol Piscinas | D224: =IFERROR(INDEX(Prospectos!$J$2:$J$288,MATCH($A224,Prospectos!$A$2:$A$288,0)),"") -> PRFV y plásticos | E224: =IFERROR(INDEX(Prospectos!$C$2:$C$288,MATCH($A224,Prospectos!$A$2:$A$288,0)),"") -> Villa María / RP6 | F224: =IFERROR(INDEX(Prospectos!$E$2:$E$288,MATCH($A224,Prospectos!$A$2:$A$288,0)),"") -> Almafuerte | G224: =IFERROR(INDEX(Prospectos!$K$2:$K$288,MATCH($A224,Prospectos!$A$2:$A$288,0)),"") -> +54 9 3571 696296 | H224: =IFERROR(INDEX(Prospectos!$M$2:$M$288,MATCH($A224,Prospectos!$A$2:$A$288,0)),"") -> logística / instalaciones / obras / ventas | I224: =IFERROR(INDEX(Prospectos!$N$2:$N$288,MATCH($A224,Prospectos!$A$2:$A$288,0)),"") -> Entrega de piscinas de fibra desde depósito/franquicia hasta domicilio y apoyo de grúa cuando el casco debe superar medianeras, techos o accesos angostos. | J224: =IFERROR(INDEX(Prospectos!$AJ$2:$AJ$288,MATCH($A224,Prospectos!$A$2:$A$288,0)),"") -> Muy alta
...

Sheet Prospectos
A1: ID | B1: Estado de contacto | C1: Corredor | D1: Microzona | E1: Ciudad | F1: Clase | G1: Puntaje operativo | H1: Empresa | I1: Sector | J1: Categoría comercial | K1: Teléfonos | L1: Calidad del teléfono | M1: Preguntar por | N1: Necesidad probable | O1: Oferta PRESOL | P1: Gancho comercial | Q1: Acción sugerida | R1: Responsable | S1: Nota Dirección | T1: Resultado | U1: Fecha de visita | V1: Próximo paso | W1: Notas de campo | X1: Teléfono principal (tel:) | Y1: Links telefónicos | Z1: Dato pendiente | AA1: Google Maps | AB1: Fuente | AC1: URL fuente | AD1: Evidencia | AE1: Calidad del dato | AF1: Origen del registro | AG1: Servicios PRESOL a ofrecer | AH1: Rubro foco enriquecimiento | AI1: Ciudad foco solicitada | AJ1: Prioridad visita sugerida | AK1: Observación servicio nuevo | AL1: Fuente unificación | AM1: Notas de unificación
A2: RT-054 | B2: Pendiente | C2: Base Río Tercero | D2: Río Tercero / zona industrial | E2: Río Tercero | F2: A | G2: 100 | H2: Ascanelli S.A. | I2: Fabricante de tolvas, sembradoras, mixers y embolsadoras | J2: Maquinaria agrícola | K2: 03571 423691 | L2: OK | M2: logística / ventas / postventa | N2: Despacho de implementos, tolvas, sembradoras, estructuras, equipos terminados y componentes de gran porte hacia concesionarios, clientes, ferias o campo. | O2: Plataforma 20 tn para maquinaria/implementos + malacate e hidrogrúa según maniobra + seguro de carga + trazabilidad GPS. | P2: Proponer a PRESOL como transporte tercerizado para entregas, picos de producción, ferias y movimientos especiales sin inmovilizar flota propia. | Q2: Llamada comercial prioritaria; pedir por logística/ventas/postventa y consultar próximo equipo a trasladar. | S2: =IFERROR(T(INDEX('Prospectos Resumen'!$K$9:$K$297,MATCH(A2,'Prospectos Resumen'!$A$9:$A$297,0))),"") -> SERGIO ASCANELLI | X2: tel:+543571423691 | Y2: tel:+543571423691 | Z2: Confirmar decisor y frecuencia de traslados. | AA2: https://www.google.com/maps/search/?api=1&query=Ascanelli+S.A.+R%C3%ADo+Tercero+C%C3%B3rdoba+Argentina | AB2: AFAMAC / CIMCC | AC2: https://afamac.com.ar/catalogo/asociados-afamac/ascanelli/ | AD2: Fabricante radicado en Río Tercero; produce tolvas autodescargables, sembradoras, mixers y embolsadoras. | AE2: Alta | AF2: Rastrillaje agro-maquinaria web 2026-09-07 | AG2: plataforma 20 tn para maquinaria/implementos | hidrogrúa para maniobras | malacate | seguro de carga | trazabilidad GPS | AH2: fabricante/concesionario/servicio maquinaria agrícola | AI2: Sí | AJ2: Muy alta | AK2: Perfil específico maquinaria agrícola: validar pesos/dimensiones, tipo de carga y disponibilidad de medios de izaje antes de cotizar. | AL2: Rastrillaje agro-maquinaria 2026-09-07 | AM2: Alta nueva luego de barrido específico de fabricantes, implementos, tractores, concesionarios y agropartes; cruzada contra la base maestra para evitar duplicados.
A3: RT-001 | B3: Pendiente | C3: Base Río Tercero | D3: Río Tercero | E3: Río Tercero | F3: A | G3: 100 | H3: Hormicor | I3: Hormigón elaborado | J3: Hormigón, áridos y materiales | K3: 03571 500888 / 03571 510066 | L3: OK | M3: planta / mantenimiento | N3: Movimiento de premoldeados, equipos de planta/cantera, bombas, moldes y cargas pesadas. | O3: Movimiento de equipos de cantera/planta; transporte de material suelto sujeto a confirmar unidad o esquema operativo. | P3: Ofrecer respaldo para picos de obra y traslados de equipos. | Q3: Visita o llamada de validación; pedir próximo traslado concreto. | S3: =IFERROR(T(INDEX('Prospectos Resumen'!$K$9:$K$297,MATCH(A3,'Prospectos Resumen'!$A$9:$A$297,0))),"") | X3: tel:+543571500888 | Y3: tel:+543571500888 | tel:+543571510066 | Z3: Validar contacto decisor y necesidad inmediata. | AA3: https://www.google.com/maps/search/?api=1&query=-32.178000,-64.111000 | AB3: hormigonelaborado.com / Hormicor | AD3: Registro curado en documento de dirección PRESOL 2026-09. | AE3: Alta | AF3: Base curada PDF dirección | AG3: transporte de áridos/materiales | hidrogrúa para carga/descarga | percha para pallets/bolsones | AH3: áridos/construcción/premoldeados | AI3: Sí | AJ3: Muy alta | AK3: Áridos/materiales: confirmar modalidad de carga/descarga y tipo de unidad requerida antes de cotizar. | AL3: GPT adjunto + Hermes | AM3: Fusionado con base Hermes para completar teléfonos/fuentes/servicios.
A4: RT-002 | B4: Pendiente | C4: Base Río Tercero | D4: Río Tercero / zona industrial | E4: Río Tercero | F4: A | G4: 100 | H4: Metalúrgica Monticelli | I4: Fabricación de implementos agrícolas | J4: Maquinaria agrícola | K4: +54 3571 613058 / +54 3571 613060 | L4: OK | M4: logística / despacho / postventa | N4: Traslado de maquinaria, implementos, equipos terminados y componentes de gran porte entre planta, cliente, obra o feria. | O4: Plataforma 20 tn + malacate/hidrogrúa según maniobra + seguro de carga + trazabilidad GPS. | P4: Fabricante con más de 30 años, ubicado en RP6 km 3,5; produce rastras, rolos, terraceadoras y otros implementos. | Q4: Llamada prioritaria; pedir próximo traslado concreto y, si hay encaje, coordinar visita. | S4: =IFERROR(T(INDEX('Prospectos Resumen'!$K$9:$K$297,MATCH(A4,'Prospectos Resumen'!$A$9:$A$297,0))),"") -> GUILLERMO GOÑI | X4: tel:+543571613058 | Y4: tel:+543571613058 | tel:+543571613060 | Z4: Confirmar decisor, frecuencia de movimientos y vigencia del contacto antes de cotizar. | AA4: https://www.google.com/maps/search/?api=1&query=Metal%C3%BArgica+Monticelli+R%C3%ADo+Tercero+C%C3%B3rdoba+Argentina | AB4: Web propia Metalúrgica Monticelli | AC4: https://www.metalmonticelli.site/ | AD4: Fabricante con más de 30 años, ubicado en RP6 km 3,5; produce rastras, rolos, terraceadoras y otros implementos. | AE4: Alta | AF4: Enriquecimiento web 2026-09-07 | AG4: transporte de áridos/materiales | hidrogrúa para carga/descarga | percha para pallets/bolsones | plataforma 20 tn para maquinaria/piezas | hidrogrúa para maniobras | percha para pallets | AH4: fabricante/servicio maquinaria agrícola | AI4: Sí | AJ4: Muy alta | AL4: GPT adjunto
A5: RT-003 | B5: Pendiente | C5: Base Río Tercero | D5: Río Tercero | E5: Río Tercero | F5: A | G5: 100 | H5: Metalúrgica Novaretti | I5: Recipientes y equipos metalmecánicos | J5: Metalúrgica y fabricación | K5: 03571 414282 / 03571 606930 | L5: OK | M5: despacho / producción | N5: Despacho seguro de estructuras, carrozados, tanques, piezas industriales y equipos sobre plataforma. | O5: Despacho de estructuras, tanques, transformadores, piezas de ingeniería y equipos sobre plataforma 20 tn. | P5: Cotizar despacho recurrente a plantas/obras. | Q5: Visita o llamada de validación; pedir próximo traslado concreto. | S5: =IFERROR(T(INDEX('Prospectos Resumen'!$K$9:$K$297,MATCH(A5,'Prospectos Resumen'!$A$9:$A$297,0))),"") -> CRISTIAN NOVARETTI | X5: tel:+543571414282 | Y5: tel:+543571414282 | tel:+543571606930 | Z5: Validar contacto decisor y necesidad inmediata. | AA5: https://www.google.com/maps/search/?api=1&query=-32.169000,-64.117000 | AB5: novaretti.com.ar | AD5: Registro curado en documento de dirección PRESOL 2026-09. | AE5: Alta | AF5: Base curada PDF dirección | AG5: plataforma 20 tn para maquinaria/piezas | hidrogrúa para maniobras | percha para pallets | AH5: otro rubro factible | AI5: Sí | AJ5: Muy alta | AL5: GPT adjunto + Hermes | AM5: Fusionado con base Hermes para completar teléfonos/fuentes/servicios.
A6: RT-004 | B6: Pendiente | C6: Base Río Tercero | D6: Parque Industrial Leonardo Da Vinci | E6: Río Tercero | F6: A | G6: 100 | H6: Metalúrgica Río Tercero S.A. | I6: Equipamiento minero, vial y agroindustrial / fundición | J6: Metalúrgica y fabricación | K6: 03571 430558 | L6: OK | M6: despacho / producción | N6: Traslado de equipos de planta, silos, repuestos pesados, balanzas, implementos y cargas especiales. | O6: Transporte de repuestos/equipos/silos/implementos + coordinación de retiro y descarga. | P6: Produce equipamiento e insumos para minería, vial y agroindustria; encaje directo con cargas pesadas. | Q6: Validar teléfono/contacto; si responde, pedir un caso concreto de traslado o próximo movimiento. | S6: =IFERROR(T(INDEX('Prospectos Resumen'!$K$9:$K$297,MATCH(A6,'Prospectos Resumen'!$A$9:$A$297,0))),"") -> FEDE SERRA | X6: tel:+543571430558 | Y6: tel:+543571430558 | Z6: Confirmar decisor y vigencia del dato antes de incluir en salida prioritaria. | AA6: https://www.google.com/maps/search/?api=1&query=Metal%C3%BArgica+R%C3%ADo+Tercero+S.A.+R%C3%ADo+Tercero+C%C3%B3rdoba+Argentina | AB6: Maquinac / Parque Industrial Río Tercero | AC6: https://maquinac.com/empresas/metalurgica-rio-tercero | AD6: Maquinac informa dirección en Parque Industrial, teléfono y rubro minero/vial/agroindustrial. | AE6: Alta | AF6: Nuevo enriquecimiento 2026-09-02 | AG6: plataforma 20 tn para maquinaria/piezas | hidrogrúa para maniobras | percha para pallets | AH6: otro rubro factible | AI6: Sí | AJ6: Muy alta | AK6: Percha pallets: útil para insumos, bolsones, repuestos y materiales palletizados. | AL6: GPT adjunto + Hermes | AM6: Fusionado con base Hermes para completar teléfonos/fuentes/servicios.
A7: RT-005 | B7: Pendiente | C7: Base Río Tercero | D7: Río Tercero / Av. Savio | E7: Río Tercero | F7: A | G7: 100 | H7: NT Construcciones | I7: Obras civiles industriales / montaje | J7: Construcción y obra vial | K7: +54 9 3571 597645 | L7: OK | M7: operaciones / jefe de obra | N7: Traslado de maquinaria, módulos de obrador, estructuras, equipos y cargas pesadas entre frentes. | O7: Transporte especial de equipos/obrador + apoyo de hidrogrúa según maniobra + seguro/GPS. | P7: Obras civiles industriales, montaje de naves y mantenimiento en complejos fabriles; clientes industriales regionales. | Q7: Validar teléfono/contacto; si responde, pedir un caso concreto de traslado o próximo movimiento. | S7: =IFERROR(T(INDEX('Prospectos Resumen'!$K$9:$K$297,MATCH(A7,'Prospectos Resumen'!$A$9:$A$297,0))),"") | X7: tel:+5493571597645 | Y7: tel:+5493571597645 | Z7: Confirmar decisor y vigencia del dato antes de incluir en salida prioritaria. | AA7: https://www.google.com/maps/search/?api=1&query=NT+Construcciones+R%C3%ADo+Tercero+C%C3%B3rdoba+Argentina | AB7: Web propia NT Construcciones | AC7: https://ntconstrucciones.com | AD7: Servicios: obras civiles industriales, estructuras de hormigón, montaje de naves; teléfono y oficina publicados. | AE7: Alta | AF7: Nuevo enriquecimiento 2026-09-02 | AG7: transporte de áridos/materiales | hidrogrúa para carga/descarga | percha para pallets/bolsones | AH7: otro rubro factible | AI7: Sí | AJ7: Muy alta | AL7: GPT adjunto + Hermes | AM7: Fusionado con base Hermes para completar teléfonos/fuentes/servicios.
A8: RT-064 | B8: Pendiente | C8: Base Río Tercero | D8: Río Tercero / corredor agro | E8: Río Tercero | F8: A | G8: 100 | H8: SALA / Agrotecnología Sala — Río Tercero | I8: Concesionario John Deere / PLA / maquinaria agrícola / postventa | J8: Maquinaria agrícola | K8: +54 9 358 4843387 | L8: OK | M8: logística / entregas / usados / postventa / gerente comercial | N8: Entrega y retiro de tractores, cosechadoras, pulverizadoras, sembradoras e implementos; movimientos por ventas, canjes, usados, service, demostraciones y ferias. | O8: Plataforma 20 tn para equipos e implementos + malacate/hidrogrúa según maniobra + seguro de carga + trazabilidad GPS + coordinación de entrega. | P8: Tercerizar entregas y retiros para no inmovilizar flota propia; absorber picos de campaña, ventas, canjes y service fuera de zona con un proveedor regional. | Q8: Llamada prioritaria; pedir por logística/ventas/postventa y consultar cómo resuelven hoy el próximo equipo a entregar o retirar. | S8: =IFERROR(T(INDEX('Prospectos Resumen'!$K$9:$K$297,MATCH(A8,'Prospectos Resumen'!$A$9:$A$297,0))),"") | X8: tel:+5493584843387 | Y8: tel:+5493584843387 | Z8: Confirmar decisor de logística/entregas y frecuencia mensual de movimientos de equipos. | AA8: https://www.google.com/maps/search/?api=1&query=SALA+%2F+Agrotecnolog%C3%ADa+Sala+%E2%80%94+R%C3%ADo+Tercero+R%C3%ADo+Tercero+C%C3%B3rdoba+Argentina | AB8: Asociación de Concesionarios John Deere / SALA | AC8: https://acjd.com.ar/concesionarios/ | AD8: La Asociación de Concesionarios John Deere publica a Agrotecnología Sala con sucursal en Río Tercero; punto local sobre RP6. | AE8: Alta | AF8: Rastrillaje concesionarios agro 2026-09-07 | AG8: plataforma 20 tn para maquinaria agrícola | hidrogrúa para maniobras | malacate | seguro de carga | trazabilidad GPS | coordinación de entregas | AH8: concesionario agro / maquinaria agrícola | AI8: Sí | AJ8: Muy alta | AK8: Concesionario: preguntar específicamente cómo resuelven entregas, retiros de usados, canjes, service fuera de zona y traslados a exposiciones. | AL8: Rastrillaje concesionarios agro 2026-09-07 | AM8: Alta nueva del barrido específico de concesionarios, sucursales y multimarca agro; cruzada contra la base maestra para evitar duplicados.
A9: RT-006 | B9: Pendiente | C9: Base Río Tercero | D9: Río Tercero / zona industrial | E9: Río Tercero | F9: A | G9: 100 | H9: Sinfix SAS | I9: Sinfines para agro e industria | J9: Metalúrgica y fabricación | K9: +54 9 3571 405077 | L9: OK | M9: despacho / producción | N9: Despacho de estructuras, piezas, equipos y conjuntos metalmecánicos de gran porte hacia obras o clientes. | O9: Plataforma 20 tn para piezas/estructuras + seguro de carga + trazabilidad GPS + apoyo de hidrogrúa según maniobra. | P9: Fabrica sinfines para sectores agrícola, ganadero, minero y alimenticio; despacho nacional de piezas y conjuntos. | Q9: Llamada prioritaria; pedir próximo traslado concreto y, si hay encaje, coordinar visita. | S9: =IFERROR(T(INDEX('Prospectos Resumen'!$K$9:$K$297,MATCH(A9,'Prospectos Resumen'!$A$9:$A$297,0))),"") | X9: tel:+5493571405077 | Y9: tel:+5493571405077 | Z9: Confirmar decisor, frecuencia de movimientos y vigencia del contacto antes de cotizar. | AA9: https://www.google.com/maps/search/?api=1&query=Sinfix+SAS+R%C3%ADo+Tercero+C%C3%B3rdoba+Argentina | AB9: Web propia SINFIX | AC9: https://sinfix.com.ar/ | AD9: Fabrica sinfines para sectores agrícola, ganadero, minero y alimenticio; despacho nacional de piezas y conjuntos. | AE9: Alta | AF9: Enriquecimiento web 2026-09-07 | AG9: transporte de áridos/materiales | hidrogrúa para carga/descarga | percha para pallets/bolsones | plataforma 20 tn para maquinaria/piezas | hidrogrúa para maniobras | percha para pallets | AH9: otro rubro factible | AI9: Sí | AJ9: Muy alta | AK9: Percha pallets: útil para insumos, bolsones, repuestos y materiales palletizados. | AL9: GPT adjunto
A10: RT-007 | B10: Pendiente | C10: Base Río Tercero | D10: Río Tercero / zona industrial | E10: Río Tercero | F10: A | G10: 100 | H10: Suragro - Implementos Agrícolas | I10: Fabricación de maquinaria agrícola | J10: Maquinaria agrícola | K10: 03571 424574 | L10: OK | M10: logística / despacho / postventa | N10: Traslado de maquinaria, implementos, equipos terminados y componentes de gran porte entre planta, cliente, obra o feria. | O10: Plataforma 20 tn + malacate/hidrogrúa según maniobra + seguro de carga + trazabilidad GPS. | P10: Fabricante local de maquinaria agrícola; alto potencial de despachos de equipos terminados. | Q10: Llamada prioritaria; pedir próximo traslado concreto y, si hay encaje, coordinar visita. | S10: =IFERROR(T(INDEX('Prospectos Resumen'!$K$9:$K$297,MATCH(A10,'Prospectos Resumen'!$A$9:$A$297,0))),"") | X10: tel:+543571424574 | Y10: tel:+543571424574 | Z10: Confirmar decisor, frecuencia de movimientos y vigencia del contacto antes de cotizar. | AA10: https://www.google.com/maps/search/?api=1&query=Suragro+-+Implementos+Agr%C3%ADcolas+R%C3%ADo+Tercero+C%C3%B3rdoba+Argentina | AB10: Google Maps / ficha pública | AC10: https://www.google.com/maps/search/?api=1&query=Suragro+Implementos+Agr%C3%ADcolas+R%C3%ADo+Tercero+C%C3%B3rdoba+Argentina | AD10: Fabricante local de maquinaria agrícola; alto potencial de despachos de equipos terminados. | AE10: Alta | AF10: Enriquecimiento web 2026-09-07 | AG10: transporte de áridos/materiales | hidrogrúa para carga/descarga | percha para pallets/bolsones | plataforma 20 tn para maquinaria/piezas | hidrogrúa para maniobras | percha para pallets | AH10: fabricante/servicio maquinaria agrícola | AI10: Sí | AJ10: Muy alta | AL10: GPT adjunto
A11: RT-008 | B11: Pendiente | C11: Base Río Tercero | D11: Río Tercero | E11: Río Tercero | F11: A | G11: 100 | H11: Tres Eme S.A. | I11: Silos y mecanización | J11: Agro, acopio y cooperativas | K11: 03571 432190 / 03571 637720 | L11: OK | M11: responsable de acopio / mantenimiento | N11: Traslado de equipos de planta, silos, repuestos pesados, balanzas, implementos y cargas especiales. | O11: Movimiento de equipos de planta, silos, balanzas, repuestos y cargas especiales para acopios/agroindustria. | P11: Ofrecer flete + descarga/posicionamiento en obra rural. | Q11: Visita o llamada de validación; pedir próximo traslado concreto. | S11: =IFERROR(T(INDEX('Prospectos Resumen'!$K$9:$K$297,MATCH(A11,'Prospectos Resumen'!$A$9:$A$297,0))),"") -> MATI MENGO | X11: tel:+543571432190 | Y11: tel:+543571432190 | tel:+543571637720 | Z11: Validar contacto decisor y necesidad inmediata. | AA11: https://www.google.com/maps/search/?api=1&query=-32.181000,-64.103000 | AB11: parqueindustrial.riotercero.gob.ar/empresa/Tres-Eme-S.A. | AD11: Registro curado en documento de dirección PRESOL 2026-09. | AE11: Alta | AF11: Base curada PDF dirección | AG11: plataforma 20 tn para maquinaria/piezas | hidrogrúa para maniobras | percha para pallets | percha para pallets de insumos | hidrogrúa para equipos/mantenimiento | barquilla para trabajos en altura | AH11: otro rubro factible | AI11: Sí | AJ11: Muy alta | AL11: GPT adjunto + Hermes | AM11: Fusionado con base Hermes para completar teléfonos/fuentes/servicios.
A12: RT-009 | B12: Pendiente | C12: Base Río Tercero | D12: Río Tercero | E12: Río Tercero | F12: A | G12: 100 | H12: Vial del Centro | I12: Obras de infraestructura vial | J12: Construcción y obra vial | K12: 0351 6411413 | L12: OK | M12: operaciones / entregas | N12: Traslado de maquinaria, módulos de obrador, estructuras, equipos y cargas pesadas entre frentes. | O12: Entrega y descarga de módulos/containers con plataforma, malacate e hidrogrúa según maniobra. | P12: Pedir próximo movimiento de maquinaria entre frentes. | Q12: Visita o llamada de validación; pedir próximo traslado concreto. | S12: =IFERROR(T(INDEX('Prospectos Resumen'!$K$9:$K$297,MATCH(A12,'Prospectos Resumen'!$A$9:$A$297,0))),"") | X12: tel:+543516411413 | Y12: tel:+543516411413 | Z12: Validar contacto decisor y necesidad inmediata. | AA12: https://www.google.com/maps/search/?api=1&query=-32.183000,-64.101000 | AB12: Parque Industrial Río Tercero | AD12: Registro curado en documento de dirección PRESOL 2026-09. | AE12: Alta | AF12: Base curada PDF dirección | AG12: transporte de áridos/materiales | hidrogrúa para carga/descarga | percha para pallets/bolsones | AH12: otro rubro factible | AI12: Sí | AJ12: Muy alta | AL12: GPT adjunto + Hermes | AM12: Fusionado con base Hermes para completar teléfonos/fuentes/servicios.
A13: RT-010 | B13: Pendiente | C13: Base Río Tercero | D13: Río Tercero / zona industrial | E13: Río Tercero | F13: A | G13: 96 | H13: HORMIWORK S.A. | I13: Premoldeados de hormigón pulido | J13: Hormigón, áridos y materiales | K13: 03571 565662 (portería parque) | L13: Verificar | M13: planta / despacho | N13: Movimiento de premoldeados, moldes, equipos de planta y cargas pesadas asociadas a obra. | O13: Transporte de premoldeados/equipos en plataforma + coordinación de descarga/posicionamiento con hidrogrúa cuando aplique. | P13: Empresa radicada para fabricar premoldeados de hormigón pulido; contacto por correo/parque. | Q13: Llamada prioritaria; pedir próximo traslado concreto y, si hay encaje, coordinar visita. | S13: =IFERROR(T(INDEX('Prospectos Resumen'!$K$9:$K$297,MATCH(A13,'Prospectos Resumen'!$A$9:$A$297,0))),"") | X13: tel:+543571565662 | Y13: tel:+543571565662 | Z13: Confirmar decisor, frecuencia de movimientos y vigencia del contacto antes de cotizar. | AA13: https://www.google.com/maps/search/?api=1&query=HORMIWORK+S.A.+R%C3%ADo+Tercero+C%C3%B3rdoba+Argentina | AB13: Parque Industrial Río Tercero | AC13: https://parqueindustrial.riotercero.gob.ar/empresa/HORMIWORK-S.A. | AD13: Empresa radicada para fabricar premoldeados de hormigón pulido; contacto por correo/parque. | Ficha del parque: fabricación de premoldeados de hormigón pulido; dirección E. del Campo 1271; contacto hormiwork@gmail.com. | AE13: Media | AF13: Enriquecimiento web 2026-09-07 | AG13: transporte de áridos/materiales | hidrogrúa para carga/descarga | percha para pallets/bolsones | AH13: áridos/construcción/premoldeados | AI13: Sí | AJ13: Alta | AK13: Áridos/materiales: confirmar modalidad de carga/descarga y tipo de unidad requerida antes de cotizar. | AL13: GPT adjunto + Hermes | AM13: Fusionado con base Hermes para completar teléfonos/fuentes/servicios. | ID fuente: RT-016
A14: RT-062 | B14: Pendiente | C14: Base Río Tercero | D14: Río Tercero / zona industrial | E14: Río Tercero | F14: A | G14: 95 | H14: Bartolomé Cerutti SRL — Río Tercero | I14: Concesionario New Holland / maquinaria agrícola y construcción | J14: Maquinaria agrícola | K14: 03571 644022 | L14: OK | M14: logística / ventas / postventa | N14: Entrega y retiro de tractores, cosechadoras, pulverizadoras, sembradoras e implementos; movimientos por venta, service, canje, demostraciones o ferias. | O14: Plataforma 20 tn para maquinaria agrícola + malacate/hidrogrúa según maniobra + seguro de carga + trazabilidad GPS. | P14: Ofrecer transporte tercerizado para entregas a clientes y retiros de usados/service, especialmente en picos de campaña y operaciones fuera de zona. | Q14: Llamada comercial prioritaria; pedir por logística/ventas/postventa y consultar próximo equipo a trasladar. | S14: =IFERROR(T(INDEX('Prospectos Resumen'!$K$9:$K$297,MATCH(A14,'Prospectos Resumen'!$A$9:$A$297,0))),"") | X14: tel:+543571644022 | Y14: tel:+543571644022 | Z14: Confirmar decisor y frecuencia de traslados. | AA14: https://www.google.com/maps/search/?api=1&query=Bartolom%C3%A9+Cerutti+SRL+%E2%80%94+R%C3%ADo+Tercero+R%C3%ADo+Tercero+C%C3%B3rdoba+Argentina | AB14: Web oficial Bartolomé Cerutti | AC14: https://bartolomecerutti.com.ar/empresa/ | AD14: Sucursal Río Tercero de concesionario New Holland; punto comercial para maquinaria y equipos. | AE14: Alta | AF14: Rastrillaje agro-maquinaria web 2026-09-07 | AG14: plataforma 20 tn para maquinaria/implementos | hidrogrúa para maniobras | malacate | seguro de carga | trazabilidad GPS | AH14: fabricante/concesionario/servicio maquinaria agrícola | AI14: Sí | AJ14: Muy alta | AK14: Perfil específico maquinaria agrícola: validar pesos/dimensiones, tipo de carga y disponibilidad de medios de izaje antes de cotizar. | AL14: Rastrillaje agro-maquinaria 2026-09-07 | AM14: Alta nueva luego de barrido específico de fabricantes, implementos, tractores, concesionarios y agropartes; cruzada contra la base maestra para evitar duplicados.
A15: RT-055 | B15: Pendiente | C15: Base Río Tercero | D15: Río Tercero / zona industrial | E15: Río Tercero | F15: A | G15: 95 | H15: Conax | I15: Venta e importación de tractores y maquinaria agrícola / vial | J15: Maquinaria agrícola | K15: +54 3571 348077 | L15: OK | M15: logística / ventas / postventa | N15: Entrega y retiro de tractores, cosechadoras, pulverizadoras, sembradoras e implementos; movimientos por venta, service, canje, demostraciones o ferias. | O15: Plataforma 20 tn para maquinaria agrícola + malacate/hidrogrúa según maniobra + seguro de carga + trazabilidad GPS. | P15: Ofrecer transporte tercerizado para entregas a clientes y retiros de usados/service, especialmente en picos de campaña y operaciones fuera de zona. | Q15: Llamada comercial prioritaria; pedir por logística/ventas/postventa y consultar próximo equipo a trasladar. | S15: =IFERROR(T(INDEX('Prospectos Resumen'!$K$9:$K$297,MATCH(A15,'Prospectos Resumen'!$A$9:$A$297,0))),"") -> GASPAR LOPEZ | X15: tel:+543571348077 | Y15: tel:+543571348077 | Z15: Confirmar decisor y frecuencia de traslados. | AA15: https://www.google.com/maps/search/?api=1&query=Conax+R%C3%ADo+Tercero+C%C3%B3rdoba+Argentina | AB15: Web oficial CONAX | AC15: https://conax.com.ar/ | AD15: Comercializa tractores, autoelevadores, minicargadoras y palas; centro de operaciones/showroom en Río Tercero. | AE15: Alta | AF15: Rastrillaje agro-maquinaria web 2026-09-07 | AG15: plataforma 20 tn para maquinaria/implementos | hidrogrúa para maniobras | malacate | seguro de carga | trazabilidad GPS | AH15: fabricante/concesionario/servicio maquinaria agrícola | AI15: Sí | AJ15: Muy alta | AK15: Perfil específico maquinaria agrícola: validar pesos/dimensiones, tipo de carga y disponibilidad de medios de izaje antes de cotizar. | AL15: Rastrillaje agro-maquinaria 2026-09-07 | AM15: Alta nueva luego de barrido específico de fabricantes, implementos, tractores, concesionarios y agropartes; cruzada contra la base maestra para evitar duplicados.
A16: RT-056 | B16: Pendiente | C16: Base Río Tercero | D16: Río Tercero / zona industrial | E16: Río Tercero | F16: A | G16: 95 | H16: RSA Repuestos y Servicios | I16: Concesionario Ascanelli / maquinaria, repuestos y servicio técnico | J16: Maquinaria agrícola | K16: +54 9 3571 538080 / +54 9 3571 578870 | L16: OK | M16: logística / ventas / postventa | N16: Entrega y retiro de tractores, cosechadoras, pulverizadoras, sembradoras e implementos; movimientos por venta, service, canje, demostraciones o ferias. | O16: Plataforma 20 tn para maquinaria agrícola + malacate/hidrogrúa según maniobra + seguro de carga + trazabilidad GPS. | P16: Ofrecer transporte tercerizado para entregas a clientes y retiros de usados/service, especialmente en picos de campaña y operaciones fuera de zona. | Q16: Llamada comercial prioritaria; pedir por logística/ventas/postventa y consultar próximo equipo a trasladar. | S16: =IFERROR(T(INDEX('Prospectos Resumen'!$K$9:$K$297,MATCH(A16,'Prospectos Resumen'!$A$9:$A$297,0))),"") | X16: tel:+5493571538080 | Y16: tel:+5493571538080 | Z16: Confirmar decisor y frecuencia de traslados. | AA16: https://www.google.com/maps/search/?api=1&query=RSA+Repuestos+y+Servicios+R%C3%ADo+Tercero+C%C3%B3rdoba+Argentina | AB16: Web oficial RSA | AC16: https://rsaservicios.com.ar/ | AD16: Concesionario oficial Ascanelli en Río Tercero; venta de máquinas e implementos, repuestos, servicio técnico y logística nacional. | AE16: Alta | AF16: Rastrillaje agro-maquinaria web 2026-09-07 | AG16: plataforma 20 tn para maquinaria/implementos | hidrogrúa para maniobras | malacate | seguro de carga | trazabilidad GPS | AH16: fabricante/concesionario/servicio maquinaria agrícola | AI16: Sí | AJ16: Muy alta | AK16: Perfil específico maquinaria agrícola: validar pesos/dimensiones, tipo de carga y disponibilidad de medios de izaje antes de cotizar. | AL16: Rastrillaje agro-maquinaria 2026-09-07 | AM16: Alta nueva luego de barrido específico de fabricantes, implementos, tractores, concesionarios y agropartes; cruzada contra la base maestra para evitar duplicados.
A17: RT-057 | B17: Pendiente | C17: Base Río Tercero | D17: Río Tercero / zona industrial | E17: Río Tercero | F17: A | G17: 90 | H17: Viejo Tala S.R.L. — Río Tercero | I17: Concesionario Pauny / tractores y maquinaria agrícola | J17: Maquinaria agrícola | K17: 03571 643332 / +54 9 353 4221837 | L17: OK | M17: logística / ventas / postventa | N17: Entrega y retiro de tractores, cosechadoras, pulverizadoras, sembradoras e implementos; movimientos por venta, service, canje, demostraciones o ferias. | O17: Plataforma 20 tn para maquinaria agrícola + malacate/hidrogrúa según maniobra + seguro de carga + trazabilidad GPS. | P17: Ofrecer transporte tercerizado para entregas a clientes y retiros de usados/service, especialmente en picos de campaña y operaciones fuera de zona. | Q17: Llamada comercial prioritaria; pedir por logística/ventas/postventa y consultar próximo equipo a trasladar. | S17: =IFERROR(T(INDEX('Prospectos Resumen'!$K$9:$K$297,MATCH(A17,'Prospectos Resumen'!$A$9:$A$297,0))),"") -> VISTOR SEIA (HERNANDO) WALTER PAYOLA (RIO 3) | X17: tel:+543571643332 | Y17: tel:+543571643332 | Z17: Confirmar decisor y frecuencia de traslados. | AA17: https://www.google.com/maps/search/?api=1&query=Viejo+Tala+S.R.L.+%E2%80%94+R%C3%ADo+Tercero+R%C3%ADo+Tercero+C%C3%B3rdoba+Argentina | AB17: Red de concesionarios Pauny | AC17: https://www.pauny.com.ar/ | AD17: Sucursal Río Tercero publicada en la red de concesionarios Pauny; perfil directo de tractores y maquinaria. | AE17: Alta | AF17: Rastrillaje agro-maquinaria web 2026-09-07 | AG17: plataforma 20 tn para maquinaria/implementos | hidrogrúa para maniobras | malacate | seguro de carga | trazabilidad GPS | AH17: fabricante/concesionario/servicio maquinaria agrícola | AI17: Sí | AJ17: Muy alta | AK17: Perfil específico maquinaria agrícola: validar pesos/dimensiones, tipo de carga y disponibilidad de medios de izaje antes de cotizar. | AL17: Rastrillaje agro-maquinaria 2026-09-07 | AM17: Alta nueva luego de barrido específico de fabricantes, implementos, tractores, concesionarios y agropartes; cruzada contra la base maestra para evitar duplicados.
A18: RT-065 | B18: Pendiente | C18: Base Río Tercero | D18: Río Tercero / corredor agro | E18: Río Tercero | F18: A | G18: 88 | H18: Rino Maquinaria | I18: Concesionario de tractores / maquinaria agrícola | J18: Maquinaria agrícola | K18: +54 9 3571 681323 | L18: OK | M18: logística / entregas / usados / postventa / gerente comercial | N18: Entrega y retiro de tractores, cosechadoras, pulverizadoras, sembradoras e implementos; movimientos por ventas, canjes, usados, service, demostraciones y ferias. | O18: Plataforma 20 tn para equipos e implementos + malacate/hidrogrúa según maniobra + seguro de carga + trazabilidad GPS + coordinación de entrega. | P18: Tercerizar entregas y retiros para no inmovilizar flota propia; absorber picos de campaña, ventas, canjes y service fuera de zona con un proveedor regional. | Q18: Llamada prioritaria; pedir por logística/ventas/postventa y consultar cómo resuelven hoy el próximo equipo a entregar o retirar. | S18: =IFERROR(T(INDEX('Prospectos Resumen'!$K$9:$K$297,MATCH(A18,'Prospectos Resumen'!$A$9:$A$297,0))),"") | X18: tel:+5493571681323 | Y18: tel:+5493571681323 | Z18: Confirmar decisor de logística/entregas y frecuencia mensual de movimientos de equipos. | AA18: https://www.google.com/maps/search/?api=1&query=Rino+Maquinaria+R%C3%ADo+Tercero+C%C3%B3rdoba+Argentina | AB18: Google Business / AgroCanje | AC18: https://www.google.com/maps/search/?api=1&query=Rino+Maquinaria+Rio+Tercero | AD18: Punto comercial de tractores en Río Tercero; perfil directo para entregas y retiros de equipos. | AE18: Alta | AF18: Rastrillaje concesionarios agro 2026-09-07 | AG18: plataforma 20 tn para maquinaria agrícola | hidrogrúa para maniobras | malacate | seguro de carga | trazabilidad GPS | coordinación de entregas | AH18: concesionario agro / maquinaria agrícola | AI18: Sí | AJ18: Alta | AK18: Concesionario: preguntar específicamente cómo resuelven entregas, retiros de usados, canjes, service fuera de zona y traslados a exposiciones. | AL18: Rastrillaje concesionarios agro 2026-09-07 | AM18: Alta nueva del barrido específico de concesionarios, sucursales y multimarca agro; cruzada contra la base maestra para evitar duplicados.
A19: RT-011 | B19: Pendiente | C19: Base Río Tercero | D19: Río Tercero / zona industrial | E19: Río Tercero | F19: A | G19: 85 | H19: Alpha Construcciones Industriales S.A. | I19: Construcción industrial / estructuras | J19: Construcción y obra vial | K19: A relevar | L19: A relevar | M19: jefe de obra / operaciones | N19: Traslado de maquinaria, módulos de obrador, estructuras y equipos entre depósitos y frentes de obra. | O19: Transporte especial de equipos/obrador + plataforma 20 tn + apoyo de hidrogrúa según maniobra + seguro/GPS. | P19: Ficha pública ubica fábrica/constructora industrial sobre Av. Savio en Río Tercero. | Q19: Llamada prioritaria; pedir próximo traslado concreto y, si hay encaje, coordinar visita. | S19: =IFERROR(T(INDEX('Prospectos Resumen'!$K$9:$K$297,MATCH(A19,'Prospectos Resumen'!$A$9:$A$297,0))),"") | Z19: Confirmar decisor, frecuencia de movimientos y vigencia del contacto antes de cotizar. | AA19: https://www.google.com/maps/search/?api=1&query=Alpha+Construcciones+Industriales+S.A.+R%C3%ADo+Tercero+C%C3%B3rdoba+Argentina | AB19: Google Maps / ficha pública | AC19: https://www.google.com/maps/search/?api=1&query=Alpha+Construcciones+Industriales+SA+R%C3%ADo+Tercero+C%C3%B3rdoba+Argentina | AD19: Ficha pública ubica fábrica/constructora industrial sobre Av. Savio en Río Tercero. | AE19: Media | AF19: Enriquecimiento web 2026-09-07 | AG19: transporte de áridos/materiales | hidrogrúa para carga/descarga | percha para pallets/bolsones | AH19: áridos/construcción/premoldeados | AI19: Sí | AJ19: Alta | AL19: GPT adjunto | AM19: ID fuente: RT-010
A20: RT-012 | B20: Pendiente | C20: Base Río Tercero | D20: Río Tercero / zona industrial | E20: Río Tercero | F20: A | G20: 85 | H20: Caon - Concesionario Oficial CASE IH | I20: Maquinaria agrícola / servicio técnico | J20: Maquinaria agrícola | K20: 03571 682141 | L20: OK | M20: logística / entregas / postventa | N20: Traslado de maquinaria agrícola o vial entre sucursal, cliente, taller, campo y eventos. | O20: Traslado de maquinaria en plataforma 20 tn, coordinación de retiro/entrega y apoyo de hidrogrúa si corresponde. | P20: Concesionario CASE IH en Río Tercero; posible traslado de maquinaria a clientes, ferias o servicio. | Q20: Llamada prioritaria; pedir próximo traslado concreto y, si hay encaje, coordinar visita. | S20: =IFERROR(T(INDEX('Prospectos Resumen'!$K$9:$K$297,MATCH(A20,'Prospectos Resumen'!$A$9:$A$297,0))),"") | X20: tel:+543571682141 | Y20: tel:+543571682141 | Z20: Confirmar decisor, frecuencia de movimientos y vigencia del contacto antes de cotizar. | AA20: https://www.google.com/maps/search/?api=1&query=Caon+-+Concesionario+Oficial+CASE+IH+R%C3%ADo+Tercero+C%C3%B3rdoba+Argentina | AB20: Google Maps / ficha pública | AC20: https://www.google.com/maps/search/?api=1&query=Caon+CASE+IH+R%C3%ADo+Tercero+C%C3%B3rdoba+Argentina | AD20: Concesionario CASE IH en Río Tercero; posible traslado de maquinaria a clientes, ferias o servicio. | AE20: Alta | AF20: Enriquecimiento web 2026-09-07 | AG20: plataforma 20 tn para maquinaria/piezas | hidrogrúa para maniobras | percha para pallets | AH20: fabricante/servicio maquinaria agrícola | AI20: Sí | AJ20: Muy alta | AL20: GPT adjunto | AM20: ID fuente: RT-011
A21: RT-013 | B21: Pendiente | C21: Base Río Tercero | D21: Río Tercero / zona industrial | E21: Río Tercero | F21: A | G21: 85 | H21: Cimat SRL | I21: Equipos y maquinaria agrícola | J21: Maquinaria agrícola | K21: 03571 422153 | L21: OK | M21: logística / entregas / postventa | N21: Traslado de maquinaria agrícola o vial entre sucursal, cliente, taller, campo y eventos. | O21: Traslado de maquinaria en plataforma 20 tn, coordinación de retiro/entrega y apoyo de hidrogrúa si corresponde. | P21: Ficha pública en Río Tercero: proveedor de equipos agrícolas, con teléfono y local comercial. | Q21: Llamada prioritaria; pedir próximo traslado concreto y, si hay encaje, coordinar visita. | S21: =IFERROR(T(INDEX('Prospectos Resumen'!$K$9:$K$297,MATCH(A21,'Prospectos Resumen'!$A$9:$A$297,0))),"") -> RAUL ARUTA | X21: tel:+543571422153 | Y21: tel:+543571422153 | Z21: Confirmar decisor, frecuencia de movimientos y vigencia del contacto antes de cotizar. | AA21: https://www.google.com/maps/search/?api=1&query=Cimat+SRL+R%C3%ADo+Tercero+C%C3%B3rdoba+Argentina | AB21: Google Maps / ficha pública | AC21: https://www.google.com/maps/search/?api=1&query=Cimat+SRL+R%C3%ADo+Tercero+C%C3%B3rdoba+Argentina | AD21: Ficha pública en Río Tercero: proveedor de equipos agrícolas, con teléfono y local comercial. | AE21: Alta | AF21: Enriquecimiento web 2026-09-07 | AG21: plataforma 20 tn para maquinaria/piezas | hidrogrúa para maniobras | percha para pallets | AH21: fabricante/servicio maquinaria agrícola | AI21: Sí | AJ21: Muy alta | AL21: GPT adjunto | AM21: ID fuente: RT-012
A22: RT-014 | B22: Pendiente | C22: Base Río Tercero | D22: Río Tercero / zona industrial | E22: Río Tercero | F22: A | G22: 85 | H22: D & M ESTRUCTURAS | I22: Estructuras metálicas | J22: Metalúrgica y fabricación | K22: A relevar | L22: A relevar | M22: despacho / producción | N22: Despacho de estructuras, piezas, equipos y conjuntos metalmecánicos de gran porte hacia obras o clientes. | O22: Plataforma 20 tn para piezas/estructuras + seguro de carga + trazabilidad GPS + apoyo de hidrogrúa según maniobra. | P22: Ficha pública local identifica empresa de construcciones metálicas. | Q22: Llamada prioritaria; pedir próximo traslado concreto y, si hay encaje, coordinar visita. | S22: =IFERROR(T(INDEX('Prospectos Resumen'!$K$9:$K$297,MATCH(A22,'Prospectos Resumen'!$A$9:$A$297,0))),"") -> PABLO PONCETI | Z22: Confirmar decisor, frecuencia de movimientos y vigencia del contacto antes de cotizar. | AA22: https://www.google.com/maps/search/?api=1&query=D+%26+M+ESTRUCTURAS+R%C3%ADo+Tercero+C%C3%B3rdoba+Argentina | AB22: Google Maps / ficha pública | AC22: https://www.google.com/maps/search/?api=1&query=D+%26+M+ESTRUCTURAS+R%C3%ADo+Tercero+C%C3%B3rdoba+Argentina | AD22: Ficha pública local identifica empresa de construcciones metálicas. | AE22: Media | AF22: Enriquecimiento web 2026-09-07 | AG22: transporte de áridos/materiales | hidrogrúa para carga/descarga | percha para pallets/bolsones | plataforma 20 tn para maquinaria/piezas | hidrogrúa para maniobras | percha para pallets | AH22: otro rubro factible | AI22: Sí | AJ22: Alta | AL22: GPT adjunto | AM22: ID fuente: RT-013
A23: RT-015 | B23: Pendiente | C23: Base Río Tercero | D23: Río Tercero / zona industrial | E23: Río Tercero | F23: A | G23: 85 | H23: Duter S.A. | I23: Fabricación de repuestos agrícolas | J23: Maquinaria agrícola | K23: 03571 565177 | L23: OK | M23: logística / despacho / postventa | N23: Traslado de maquinaria, implementos, equipos terminados y componentes de gran porte entre planta, cliente, obra o feria. | O23: Plataforma 20 tn + malacate/hidrogrúa según maniobra + seguro de carga + trazabilidad GPS. | P23: Empresa radicada en el Parque Industrial para fabricación de repuestos agrícolas; teléfono público local. | Q23: Llamada prioritaria; pedir próximo traslado concreto y, si hay encaje, coordinar visita. | S23: =IFERROR(T(INDEX('Prospectos Resumen'!$K$9:$K$297,MATCH(A23,'Prospectos Resumen'!$A$9:$A$297,0))),"") | X23: tel:+543571565177 | Y23: tel:+543571565177 | Z23: Confirmar decisor, frecuencia de movimientos y vigencia del contacto antes de cotizar. | AA23: https://www.google.com/maps/search/?api=1&query=Duter+S.A.+R%C3%ADo+Tercero+C%C3%B3rdoba+Argentina | AB23: Parque Industrial Río Tercero / ficha pública | AC23: https://parqueindustrial.riotercero.gob.ar/empresas | AD23: Empresa radicada en el Parque Industrial para fabricación de repuestos agrícolas; teléfono público local. | AE23: Alta | AF23: Enriquecimiento web 2026-09-07 | AG23: transporte de áridos/materiales | hidrogrúa para carga/descarga | percha para pallets/bolsones | plataforma 20 tn para maquinaria/piezas | hidrogrúa para maniobras | percha para pallets | AH23: otro rubro factible | AI23: Sí | AJ23: Muy alta | AK23: Percha pallets: útil para insumos, bolsones, repuestos y materiales palletizados. | AL23: GPT adjunto | AM23: ID fuente: RT-014
A24: RT-016 | B24: Pendiente | C24: Base Río Tercero | D24: Río Tercero | E24: Río Tercero | F24: A | G24: 85 | H24: ESISA | I24: Viviendas/módulos industrializados | J24: Módulos y contenedores | K24: Portería parque: 03571 565662; mail esisaservicios@gmail.com | L24: Verificar | M24: operaciones / entregas | N24: Entrega, descarga y posicionamiento de módulos/containers en obra o cliente final. | O24: Entrega y descarga de módulos/containers con plataforma, malacate e hidrogrúa según maniobra. | P24: Socio natural para entregas de módulos a obra. | Q24: Visita o llamada de validación; pedir próximo traslado concreto. | S24: =IFERROR(T(INDEX('Prospectos Resumen'!$K$9:$K$297,MATCH(A24,'Prospectos Resumen'!$A$9:$A$297,0))),"") | X24: tel:+543571565662 | Y24: tel:+543571565662 | Z24: Validar contacto decisor y necesidad inmediata. | AA24: https://www.google.com/maps/search/?api=1&query=-32.182000,-64.107000 | AB24: Parque Industrial Río Tercero | AD24: Registro curado en documento de dirección PRESOL 2026-09. | AE24: Media | AF24: Base curada PDF dirección | AG24: transporte de áridos/materiales | hidrogrúa para carga/descarga | percha para pallets/bolsones | AH24: otro rubro factible | AI24: Sí | AJ24: Muy alta | AL24: GPT adjunto + Hermes | AM24: Fusionado con base Hermes para completar teléfonos/fuentes/servicios. | ID fuente: RT-015
A25: RT-017 | B25: Pendiente | C25: Base Río Tercero | D25: Río Tercero / zona industrial | E25: Río Tercero | F25: A | G25: 85 | H25: ISECO Construcción | I25: Construcción industrial | J25: Construcción y obra vial | K25: +54 9 3571 551917 | L25: OK | M25: jefe de obra / operaciones | N25: Traslado de maquinaria, módulos de obrador, estructuras y equipos entre depósitos y frentes de obra. | O25: Transporte especial de equipos/obrador + plataforma 20 tn + apoyo de hidrogrúa según maniobra + seguro/GPS. | P25: Constructora localizada en el Parque Industrial; posible movimiento de estructuras, equipos y obradores. | Q25: Llamada prioritaria; pedir próximo traslado concreto y, si hay encaje, coordinar visita. | S25: =IFERROR(T(INDEX('Prospectos Resumen'!$K$9:$K$297,MATCH(A25,'Prospectos Resumen'!$A$9:$A$297,0))),"") -> BETO | X25: tel:+5493571551917 | Y25: tel:+5493571551917 | Z25: Confirmar decisor, frecuencia de movimientos y vigencia del contacto antes de cotizar. | AA25: https://www.google.com/maps/search/?api=1&query=ISECO+Construcci%C3%B3n+R%C3%ADo+Tercero+C%C3%B3rdoba+Argentina | AB25: Google Maps / ficha pública | AC25: https://www.google.com/maps/search/?api=1&query=ISECO+Construcci%C3%B3n+R%C3%ADo+Tercero+C%C3%B3rdoba+Argentina | AD25: Constructora localizada en el Parque Industrial; posible movimiento de estructuras, equipos y obradores. | AE25: Alta | AF25: Enriquecimiento web 2026-09-07 | AG25: transporte de áridos/materiales | hidrogrúa para carga/descarga | percha para pallets/bolsones | AH25: áridos/construcción/premoldeados | AI25: Sí | AJ25: Muy alta | AL25: GPT adjunto
A26: RT-018 | B26: Pendiente | C26: Base Río Tercero | D26: Río Tercero / zona industrial | E26: Río Tercero | F26: A | G26: 85 | H26: Luzenti Hnos S.A. | I26: Montaje industrial / construcciones metálicas | J26: Construcción y obra vial | K26: 03584 860532 | L26: Verificar | M26: jefe de obra / operaciones | N26: Traslado de maquinaria, módulos de obrador, estructuras y equipos entre depósitos y frentes de obra. | O26: Transporte especial de equipos/obrador + plataforma 20 tn + apoyo de hidrogrúa según maniobra + seguro/GPS. | P26: Empresa de construcciones metálicas y montaje industrial radicada en Río Tercero. | Q26: Llamada prioritaria; pedir próximo traslado concreto y, si hay encaje, coordinar visita. | S26: =IFERROR(T(INDEX('Prospectos Resumen'!$K$9:$K$297,MATCH(A26,'Prospectos Resumen'!$A$9:$A$297,0))),"") -> JORGE LUCENTI | X26: tel:+543584860532 | Y26: tel:+543584860532 | Z26: Confirmar decisor, frecuencia de movimientos y vigencia del contacto antes de cotizar. | AA26: https://www.google.com/maps/search/?api=1&query=Luzenti+Hnos+S.A.+R%C3%ADo+Tercero+C%C3%B3rdoba+Argentina | AB26: Google Maps / Parque Industrial | AC26: https://www.google.com/maps/search/?api=1&query=Luzenti+Hnos+SA+R%C3%ADo+Tercero+C%C3%B3rdoba+Argentina | AD26: Empresa de construcciones metálicas y montaje industrial radicada en Río Tercero. | AE26: Media | AF26: Enriquecimiento web 2026-09-07 | AG26: transporte de áridos/materiales | hidrogrúa para carga/descarga | percha para pallets/bolsones | plataforma 20 tn para maquinaria/piezas | hidrogrúa para maniobras | percha para pallets | AH26: áridos/construcción/premoldeados | AI26: Sí | AJ26: Muy alta | AL26: GPT adjunto
A27: RT-019 | B27: Pendiente | C27: Base Río Tercero | D27: Río Tercero / zona industrial | E27: Río Tercero | F27: A | G27: 85 | H27: NEMETAL S.A.S | I27: Fabricación metalúrgica / reparación de maquinaria agrícola | J27: Maquinaria agrícola | K27: 03571 550608 | L27: OK | M27: despacho / producción | N27: Despacho de estructuras, piezas, equipos y conjuntos metalmecánicos de gran porte hacia obras o clientes. | O27: Plataforma 20 tn para piezas/estructuras + seguro de carga + trazabilidad GPS + apoyo de hidrogrúa según maniobra. | P27: Ficha pública en zona industrial; el listado del parque identifica NE Metalúrgica vinculada a reparación de maquinaria agrícola. | Q27: Llamada prioritaria; pedir próximo traslado concreto y, si hay encaje, coordinar visita. | S27: =IFERROR(T(INDEX('Prospectos Resumen'!$K$9:$K$297,MATCH(A27,'Prospectos Resumen'!$A$9:$A$297,0))),"") | X27: tel:+543571550608 | Y27: tel:+543571550608 | Z27: Confirmar decisor, frecuencia de movimientos y vigencia del contacto antes de cotizar. | AA27: https://www.google.com/maps/search/?api=1&query=NEMETAL+S.A.S+R%C3%ADo+Tercero+C%C3%B3rdoba+Argentina | AB27: Google Maps / Parque Industrial Río Tercero | AC27: https://www.google.com/maps/search/?api=1&query=NEMETAL+SAS+R%C3%ADo+Tercero+C%C3%B3rdoba+Argentina | AD27: Ficha pública en zona industrial; el listado del parque identifica NE Metalúrgica vinculada a reparación de maquinaria agrícola. | AE27: Alta | AF27: Enriquecimiento web 2026-09-07 | AG27: transporte de áridos/materiales | hidrogrúa para carga/descarga | percha para pallets/bolsones | plataforma 20 tn para maquinaria/piezas | hidrogrúa para maniobras | percha para pallets | AH27: fabricante/servicio maquinaria agrícola | AI27: Sí | AJ27: Muy alta | AL27: GPT adjunto
A28: RT-058 | B28: Pendiente | C28: Base Río Tercero | D28: Río Tercero / zona industrial | E28: Río Tercero | F28: A | G28: 85 | H28: Paulucci Máquinas Agrícolas | I28: Venta de maquinaria e implementos agrícolas | J28: Maquinaria agrícola | K28: 03571 424384 | L28: OK | M28: logística / ventas / postventa | N28: Entrega y retiro de tractores, cosechadoras, pulverizadoras, sembradoras e implementos; movimientos por venta, service, canje, demostraciones o ferias. | O28: Plataforma 20 tn para maquinaria agrícola + malacate/hidrogrúa según maniobra + seguro de carga + trazabilidad GPS. | P28: Ofrecer transporte tercerizado para entregas a clientes y retiros de usados/service, especialmente en picos de campaña y operaciones fuera de zona. | Q28: Llamada comercial prioritaria; pedir por logística/ventas/postventa y consultar próximo equipo a trasladar. | S28: =IFERROR(T(INDEX('Prospectos Resumen'!$K$9:$K$297,MATCH(A28,'Prospectos Resumen'!$A$9:$A$297,0))),"") -> WALTER PAULUCCI | X28: tel:+543571424384 | Y28: tel:+543571424384 | Z28: Confirmar decisor y frecuencia de traslados. | AA28: https://www.google.com/maps/search/?api=1&query=Paulucci+M%C3%A1quinas+Agr%C3%ADcolas+R%C3%ADo+Tercero+C%C3%B3rdoba+Argentina | AB28: Red de concesionarios Conese | AC28: https://conese.com.ar/ | AD28: Punto comercial de maquinaria agrícola en Av. Fuerza Aérea, Río Tercero. | AE28: Alta | AF28: Rastrillaje agro-maquinaria web 2026-09-07 | AG28: plataforma 20 tn para maquinaria/implementos | hidrogrúa para maniobras | malacate | seguro de carga | trazabilidad GPS | AH28: fabricante/concesionario/servicio maquinaria agrícola | AI28: Sí | AJ28: Alta | AK28: Perfil específico maquinaria agrícola: validar pesos/dimensiones, tipo de carga y disponibilidad de medios de izaje antes de cotizar. | AL28: Rastrillaje agro-maquinaria 2026-09-07 | AM28: Alta nueva luego de barrido específico de fabricantes, implementos, tractores, concesionarios y agropartes; cruzada contra la base maestra para evitar duplicados.
A29: RT-059 | B29: Pendiente | C29: Base Río Tercero | D29: Río Tercero / zona industrial | E29: Río Tercero | F29: A | G29: 85 | H29: SAEMMA | I29: Maquinaria agrícola, construcción y minería / repuestos | J29: Maquinaria agrícola | K29: 03571 432338 | L29: Verificar | M29: logística / ventas / postventa | N29: Entrega y retiro de tractores, cosechadoras, pulverizadoras, sembradoras e implementos; movimientos por venta, service, canje, demostraciones o ferias. | O29: Plataforma 20 tn para maquinaria agrícola + malacate/hidrogrúa según maniobra + seguro de carga + trazabilidad GPS. | P29: Ofrecer transporte tercerizado para entregas a clientes y retiros de usados/service, especialmente en picos de campaña y operaciones fuera de zona. | Q29: Llamada comercial prioritaria; pedir por logística/ventas/postventa y consultar próximo equipo a trasladar. | S29: =IFERROR(T(INDEX('Prospectos Resumen'!$K$9:$K$297,MATCH(A29,'Prospectos Resumen'!$A$9:$A$297,0))),"") | X29: tel:+543571432338 | Y29: tel:+543571432338 | Z29: Confirmar teléfono, decisor y vigencia del punto de venta. | AA29: https://www.google.com/maps/search/?api=1&query=SAEMMA+R%C3%ADo+Tercero+C%C3%B3rdoba+Argentina | AB29: SAEMMA / directorios empresariales | AC29: https://www.saemma.com/ | AD29: Empresa de Río Tercero vinculada a maquinaria especializada para agro, construcción y minería; validar contacto comercial actual. | AE29: Alta | AF29: Rastrillaje agro-maquinaria web 2026-09-07 | AG29: plataforma 20 tn para maquinaria/implementos | hidrogrúa para maniobras | malacate | seguro de carga | trazabilidad GPS | AH29: fabricante/concesionario/servicio maquinaria agrícola | AI29: Sí | AJ29: Alta | AK29: Perfil específico maquinaria agrícola: validar pesos/dimensiones, tipo de carga y disponibilidad de medios de izaje antes de cotizar. | AL29: Rastrillaje agro-maquinaria 2026-09-07 | AM29: Alta nueva luego de barrido específico de fabricantes, implementos, tractores, concesionarios y agropartes; cruzada contra la base maestra para evitar duplicados.
A30: RT-020 | B30: Pendiente | C30: Base Río Tercero | D30: Río Tercero / zona industrial | E30: Río Tercero | F30: A | G30: 85 | H30: Sclauzero Metalúrgica | I30: Fabricación y provisión de máquinas / metalurgia | J30: Metalúrgica y fabricación | K30: 03571 414014 | L30: OK | M30: despacho / producción | N30: Despacho de estructuras, piezas, equipos y conjuntos metalmecánicos de gran porte hacia obras o clientes. | O30: Plataforma 20 tn para piezas/estructuras + seguro de carga + trazabilidad GPS + apoyo de hidrogrúa según maniobra. | P30: Ficha pública local: proveedor de máquinas de metal, con teléfono. | Q30: Llamada prioritaria; pedir próximo traslado concreto y, si hay encaje, coordinar visita. | S30: =IFERROR(T(INDEX('Prospectos Resumen'!$K$9:$K$297,MATCH(A30,'Prospectos Resumen'!$A$9:$A$297,0))),"") -> GUILLERMO SCLAUSERO | X30: tel:+543571414014 | Y30: tel:+543571414014 | Z30: Confirmar decisor, frecuencia de movimientos y vigencia del contacto antes de cotizar. | AA30: https://www.google.com/maps/search/?api=1&query=Sclauzero+Metal%C3%BArgica+R%C3%ADo+Tercero+C%C3%B3rdoba+Argentina | AB30: Google Maps / ficha pública | AC30: https://www.google.com/maps/search/?api=1&query=Sclauzero+Metal%C3%BArgica+R%C3%ADo+Tercero+C%C3%B3rdoba+Argentina | AD30: Ficha pública local: proveedor de máquinas de metal, con teléfono. | AE30: Alta | AF30: Enriquecimiento web 2026-09-07 | AG30: transporte de áridos/materiales | hidrogrúa para carga/descarga | percha para pallets/bolsones | plataforma 20 tn para maquinaria/piezas | hidrogrúa para maniobras | percha para pallets | AH30: otro rubro factible | AI30: Sí | AJ30: Muy alta | AL30: GPT adjunto
A31: RT-060 | B31: Pendiente | C31: Base Río Tercero | D31: Río Tercero / zona industrial | E31: Río Tercero | F31: A | G31: 82 | H31: Barrax Argentina S.A. | I31: Fabricante de sistemas de corte y agropartes para cosechadoras | J31: Maquinaria agrícola | K31: 03571 421774 / 03571 420576 | L31: OK | M31: logística / ventas / postventa | N31: Movimiento de agropartes, repuestos pesados, conjuntos y eventualmente implementos/equipos entre planta, concesionarios y clientes. | O31: Plataforma e hidrogrúa para conjuntos pesados + percha/pallets para repuestos + seguro y trazabilidad. | P31: Ofrecer respaldo flexible para despachos voluminosos y cargas que exceden el transporte convencional de repuestos. | Q31: Llamada comercial prioritaria; pedir por logística/ventas/postventa y consultar próximo equipo a trasladar. | S31: =IFERROR(T(INDEX('Prospectos Resumen'!$K$9:$K$297,MATCH(A31,'Prospectos Resumen'!$A$9:$A$297,0))),"") | X31: tel:+543571421774 | Y31: tel:+543571421774 | Z31: Confirmar decisor y frecuencia de traslados. | AA31: https://www.google.com/maps/search/?api=1&query=Barrax+Argentina+S.A.+R%C3%ADo+Tercero+C%C3%B3rdoba+Argentina | AB31: Web oficial Barrax | AC31: https://www.barraxweb.com/ | AD31: Fabricante local de sistemas de corte y componentes para cosechadoras; despacho de conjuntos y agropartes. | AE31: Alta | AF31: Rastrillaje agro-maquinaria web 2026-09-07 | AG31: plataforma 20 tn para maquinaria/implementos | hidrogrúa para maniobras | malacate | seguro de carga | trazabilidad GPS | AH31: fabricante/concesionario/servicio maquinaria agrícola | AI31: Sí | AJ31: Alta | AK31: Perfil específico maquinaria agrícola: validar pesos/dimensiones, tipo de carga y disponibilidad de medios de izaje antes de cotizar. | AL31: Rastrillaje agro-maquinaria 2026-09-07 | AM31: Alta nueva luego de barrido específico de fabricantes, implementos, tractores, concesionarios y agropartes; cruzada contra la base maestra para evitar duplicados.
A32: RT-021 | B32: Pendiente | C32: Base Río Tercero | D32: Río Tercero | E32: Río Tercero | F32: A | G32: 75 | H32: IMBAL S.A. | I32: Estructuras metálicas / montaje | J32: Metalúrgica y fabricación | K32: A relevar en terreno | L32: A relevar | M32: despacho / producción | N32: Despacho seguro de estructuras, carrozados, tanques, piezas industriales y equipos sobre plataforma. | O32: Despacho de estructuras, tanques, transformadores, piezas de ingeniería y equipos sobre plataforma 20 tn. | P32: Fabrican y montan; pedir responsable de despacho/montaje. | Q32: Visita o llamada de validación; pedir próximo traslado concreto. | S32: =IFERROR(T(INDEX('Prospectos Resumen'!$K$9:$K$297,MATCH(A32,'Prospectos Resumen'!$A$9:$A$297,0))),"") -> DANIEL BALATORE | Z32: Validar contacto decisor y necesidad inmediata. | AA32: https://www.google.com/maps/search/?api=1&query=-32.180000,-64.106000 | AB32: Parque Industrial Río Tercero / LinkedIn comercial | AD32: Registro curado en documento de dirección PRESOL 2026-09. | AE32: Media | AF32: Base curada PDF dirección | AG32: plataforma 20 tn para maquinaria/piezas | hidrogrúa para maniobras | percha para pallets | AH32: otro rubro factible | AI32: Sí | AJ32: Alta | AL32: GPT adjunto + Hermes | AM32: Fusionado con base Hermes para completar teléfonos/fuentes/servicios.
A33: RT-022 | B33: Pendiente | C33: Base Río Tercero | D33: Parque Industrial / PRFV | E33: Río Tercero | F33: B | G33: 85 | H33: J.A.F. Plásticos Reforzados | I33: Plástico reforzado con fibra de vidrio / PRFV / piezas industriales y piletas | J33: PRFV y plásticos | K33: 3571 533624 / 3571 579801 / portería parque 03571 565662 | L33: OK | M33: producción / logística | N33: Retiro, traslado y descarga de piletas/fibra o piezas voluminosas livianas, con cuidado de maniobra. | O33: Plataforma + hidrogrúa para trasladar y descargar piletas/piezas PRFV; coordinar maniobra sin golpes. | P33: PRFV con aplicaciones industriales, tanques, piletones y piletas; piezas voluminosas de bajo peso con necesidad de cuidado en maniobra. | Q33: Pedir por producción/logística y consultar si tercerizan traslados de piezas PRFV o entregas especiales. | S33: =IFERROR(T(INDEX('Prospectos Resumen'!$K$9:$K$297,MATCH(A33,'Prospectos Resumen'!$A$9:$A$297,0))),"") | X33: tel:+543571533624 | Y33: tel:+543571533624 | tel:+543571579801 | tel:+543571565662 | Z33: Confirmar punto operativo: ficha del parque Río Tercero y web con domicilio en Almafuerte. | AA33: https://www.google.com/maps/search/?api=1&query=J.A.F.+Pl%C3%A1sticos+Reforzados+R%C3%ADo+Tercero+C%C3%B3rdoba+Argentina | AB33: Web propia + Parque Industrial Río Tercero | AC33: https://jafplasticosreforzados.com | AD33: Web informa PRFV, piletas/piezas, transporte/logística propia y teléfonos 3571 533624 / 3571 579801; ficha parque lista J.A.F. Plásticos Reforzados. | AE33: Alta | AF33: Nuevo enriquecimiento zonas priorizadas 2026-09 | AG33: plataforma para piletas/fibra | hidrogrúa para descarga/posicionamiento | AH33: piletas/plástico/PRFV | AI33: Sí | AJ33: Alta | AL33: Hermes único | AM33: Alta única desde base Hermes; no estaba en el Excel GPT adjunto. | ID fuente: PRESOL-120
A34: RT-023 | B34: Pendiente | C34: Base Río Tercero | D34: Río Tercero / piletas y PRFV | E34: Río Tercero | F34: B | G34: 85 | H34: Tecnipiscinas | I34: Piletas de fibra / piscinas / accesorios | J34: PRFV y plásticos | K34: +54 3571 412563 | L34: OK | M34: ventas / logística / dueño | N34: Retiro, traslado y descarga de piletas/fibra o piezas voluminosas livianas, con cuidado de maniobra. | O34: Plataforma + hidrogrúa para trasladar y descargar piletas/piezas PRFV; coordinar maniobra sin golpes. | P34: Piletas de fibra y equipamiento; traslado y descarga de cascos/piezas voluminosas puede tercerizarse por temporada. | Q34: Llamar y preguntar por entregas fuera de Río Tercero y si tercerizan traslado/descarga de cascos. | S34: =IFERROR(T(INDEX('Prospectos Resumen'!$K$9:$K$297,MATCH(A34,'Prospectos Resumen'!$A$9:$A$297,0))),"") | X34: tel:+543571412563 | Y34: tel:+543571412563 | Z34: Confirmar si fabrica localmente o actúa como punto de venta y volumen mensual de entregas. | AA34: https://www.google.com/maps/search/?api=1&query=Tecnipiscinas+R%C3%ADo+Tercero+C%C3%B3rdoba+Argentina | AB34: Web propia / Moldear | AC34: https://www.tecnipiscinas.com.ar | AD34: Contacto publicado: Av. Pío X 485, Río Tercero; teléfono +54 3571 412563; rubro piscinas. | AE34: Alta | AF34: Nuevo enriquecimiento zonas priorizadas 2026-09 | AG34: plataforma para piletas/fibra | hidrogrúa para descarga/posicionamiento | AH34: piletas/plástico/PRFV | AI34: Sí | AJ34: Alta | AL34: Hermes único | AM34: Alta única desde base Hermes; no estaba en el Excel GPT adjunto. | ID fuente: PRESOL-118
A35: RT-024 | B35: Pendiente | C35: Base Río Tercero | D35: Río Tercero / piletas y PRFV | E35: Río Tercero | F35: B | G35: 81 | H35: Indusplast Río Tercero | I35: Piletas de fibra / plástico reforzado | J35: PRFV y plásticos | K35: +54 3571 57-5556 | L35: Verificar | M35: ventas / dueño | N35: Retiro, traslado y descarga de piletas/fibra o piezas voluminosas livianas, con cuidado de maniobra. | O35: Plataforma + hidrogrúa para trasladar y descargar piletas/piezas PRFV; coordinar maniobra sin golpes. | P35: Fabricación/venta de piscinas de fibra; encaje para plataforma e hidrogrúa en temporada. | Q35: Verificar teléfono por llamado corto y preguntar por entregas a clientes finales. | S35: =IFERROR(T(INDEX('Prospectos Resumen'!$K$9:$K$297,MATCH(A35,'Prospectos Resumen'!$A$9:$A$297,0))),"") | X35: tel:+543571575556 | Y35: tel:+543571575556 | Z35: Confirmar dirección operativa y si mueve cascos completos. | AA35: https://www.google.com/maps/search/?api=1&query=Indusplast+R%C3%ADo+Tercero+R%C3%ADo+Tercero+C%C3%B3rdoba+Argentina | AB35: Facebook público / resultado de búsqueda | AC35: https://www.facebook.com/indusplastrio3?locale=es_LA | AD35: Resultado público informa Indusplast Río Tercero y contacto +54 3571 57-5556; rubro piscinas de fibra. | AE35: Media | AF35: Nuevo enriquecimiento zonas priorizadas 2026-09 | AG35: plataforma para piletas/fibra | hidrogrúa para descarga/posicionamiento | AH35: piletas/plástico/PRFV | AI35: Sí | AJ35: Alta | AL35: Hermes único | AM35: Alta única desde base Hermes; no estaba en el Excel GPT adjunto. | ID fuente: PRESOL-119
A36: RT-025 | B36: Pendiente | C36: Base Río Tercero | D36: Río Tercero / zona industrial | E36: Río Tercero | F36: B | G36: 75 | H36: AGROTRAZIONE S.A.S | I36: Maquinaria e implementos agrícolas | J36: Maquinaria agrícola | K36: 03571 528350 | L36: OK | M36: logística / entregas / postventa | N36: Traslado de maquinaria agrícola o vial entre sucursal, cliente, taller, campo y eventos. | O36: Traslado de maquinaria en plataforma 20 tn, coordinación de retiro/entrega y apoyo de hidrogrúa si corresponde. | P36: Listado de servicios del sector agrícola ubica AGROTRAZIONE en 2 de Abril 1638, Río Tercero, con teléfono. | Q36: Llamar para validar necesidad y frecuencia; visitar si confirma movimientos de equipos/cargas. | S36: =IFERROR(T(INDEX('Prospectos Resumen'!$K$9:$K$297,MATCH(A36,'Prospectos Resumen'!$A$9:$A$297,0))),"") | X36: tel:+543571528350 | Y36: tel:+543571528350 | Z36: Confirmar decisor, frecuencia de movimientos y vigencia del contacto antes de cotizar. | AA36: https://www.google.com/maps/search/?api=1&query=AGROTRAZIONE+S.A.S+R%C3%ADo+Tercero+C%C3%B3rdoba+Argentina | AB36: Red de servicios Piersanti | AC36: https://piersanti.com.ar/en/en_services/ | AD36: Listado de servicios del sector agrícola ubica AGROTRAZIONE en 2 de Abril 1638, Río Tercero, con teléfono. | AE36: Alta | AF36: Enriquecimiento web 2026-09-07 | AG36: plataforma 20 tn para maquinaria/piezas | hidrogrúa para maniobras | percha para pallets | AH36: fabricante/servicio maquinaria agrícola | AI36: Sí | AJ36: Alta | AL36: GPT adjunto | AM36: ID fuente: RT-022
A37: RT-026 | B37: Pendiente | C37: Base Río Tercero | D37: Río Tercero / zona industrial | E37: Río Tercero | F37: B | G37: 75 | H37: Cementados Juan Nadalin e Hijos S.A. | I37: Cementados / reparación de piezas agroindustriales | J37: Agroindustria y alimentos | K37: 03571 420931 | L37: OK | M37: logística / despacho / postventa | N37: Traslado de maquinaria, implementos, equipos terminados y componentes de gran porte entre planta, cliente, obra o feria. | O37: Plataforma 20 tn + malacate/hidrogrúa según maniobra + seguro de carga + trazabilidad GPS. | P37: Planta industrial local con actividad de cementados; teléfono público. | Q37: Llamar para validar necesidad y frecuencia; visitar si confirma movimientos de equipos/cargas. | S37: =IFERROR(T(INDEX('Prospectos Resumen'!$K$9:$K$297,MATCH(A37,'Prospectos Resumen'!$A$9:$A$297,0))),"") -> JUANJO NADALIN | X37: tel:+543571420931 | Y37: tel:+543571420931 | Z37: Confirmar decisor, frecuencia de movimientos y vigencia del contacto antes de cotizar. | AA37: https://www.google.com/maps/search/?api=1&query=Cementados+Juan+Nadalin+e+Hijos+S.A.+R%C3%ADo+Tercero+C%C3%B3rdoba+Argentina | AB37: Google Maps / Parque Industrial | AC37: https://www.google.com/maps/search/?api=1&query=Cementados+Juan+Nadalin+e+Hijos+R%C3%ADo+Tercero+C%C3%B3rdoba+Argentina | AD37: Planta industrial local con actividad de cementados; teléfono público. | AE37: Alta | AF37: Enriquecimiento web 2026-09-07 | AG37: transporte de áridos/materiales | hidrogrúa para carga/descarga | percha para pallets/bolsones | plataforma 20 tn para maquinaria/piezas | hidrogrúa para maniobras | percha para pallets | AH37: otro rubro factible | AI37: Sí | AJ37: Alta | AK37: Percha pallets: útil para insumos, bolsones, repuestos y materiales palletizados. | AL37: GPT adjunto | AM37: ID fuente: RT-023
A38: RT-027 | B38: Pendiente | C38: Base Río Tercero | D38: Río Tercero / zona industrial | E38: Río Tercero | F38: B | G38: 75 | H38: Cementados Río Tercero | I38: Cementado agroindustrial | J38: Agroindustria y alimentos | K38: 03571 319490 | L38: OK | M38: logística / despacho / postventa | N38: Traslado de maquinaria, implementos, equipos terminados y componentes de gran porte entre planta, cliente, obra o feria. | O38: Plataforma 20 tn + malacate/hidrogrúa según maniobra + seguro de carga + trazabilidad GPS. | P38: Empresa local de cementados vinculados al agro; potencial traslado de piezas, sinfines e implementos. | Q38: Llamar para validar necesidad y frecuencia; visitar si confirma movimientos de equipos/cargas. | S38: =IFERROR(T(INDEX('Prospectos Resumen'!$K$9:$K$297,MATCH(A38,'Prospectos Resumen'!$A$9:$A$297,0))),"") | X38: tel:+543571319490 | Y38: tel:+543571319490 | Z38: Confirmar decisor, frecuencia de movimientos y vigencia del contacto antes de cotizar. | AA38: https://www.google.com/maps/search/?api=1&query=Cementados+R%C3%ADo+Tercero+R%C3%ADo+Tercero+C%C3%B3rdoba+Argentina | AB38: Parque Industrial / Google Maps | AC38: https://parqueindustrial.riotercero.gob.ar/empresas | AD38: Empresa local de cementados vinculados al agro; potencial traslado de piezas, sinfines e implementos. | AE38: Alta | AF38: Enriquecimiento web 2026-09-07 | AG38: transporte de áridos/materiales | hidrogrúa para carga/descarga | percha para pallets/bolsones | plataforma 20 tn para maquinaria/piezas | hidrogrúa para maniobras | percha para pallets | AH38: otro rubro factible | AI38: Sí | AJ38: Alta | AK38: Percha pallets: útil para insumos, bolsones, repuestos y materiales palletizados. | AL38: GPT adjunto | AM38: ID fuente: RT-024
A39: RT-028 | B39: Pendiente | C39: Base Río Tercero | D39: Río Tercero | E39: Río Tercero | F39: B | G39: 75 | H39: Hidrobull | I39: Accesorios para minicargadoras | J39: Industria y mantenimiento | K39: 03571 549612 | L39: OK | M39: responsable de logística/compras | N39: Movimientos especiales de mantenimiento, repuestos pesados y mudanzas internas de equipos. | O39: Detectar el próximo movimiento pesado y convertirlo en cotización concreta. | P39: Preguntar si entregan accesorios con terceros. | Q39: Visita o llamada de validación; pedir próximo traslado concreto. | S39: =IFERROR(T(INDEX('Prospectos Resumen'!$K$9:$K$297,MATCH(A39,'Prospectos Resumen'!$A$9:$A$297,0))),"") -> DAVID BELAZQUE | X39: tel:+543571549612 | Y39: tel:+543571549612 | Z39: Validar contacto decisor y necesidad inmediata. | AA39: https://www.google.com/maps/search/?api=1&query=-32.171500,-64.116500 | AB39: Facebook Hidrobull | AD39: Registro curado en documento de dirección PRESOL 2026-09. | AE39: Alta | AF39: Base curada PDF dirección | AG39: plataforma 20 tn para maquinaria/piezas | hidrogrúa para maniobras | percha para pallets | AH39: otro rubro factible | AI39: Sí | AJ39: Alta | AL39: GPT adjunto + Hermes | AM39: Fusionado con base Hermes para completar teléfonos/fuentes/servicios. | ID fuente: RT-025
A40: RT-029 | B40: Pendiente | C40: Base Río Tercero | D40: Río Tercero | E40: Río Tercero | F40: B | G40: 75 | H40: MetalMec S.R.L. | I40: Implementos y accesorios | J40: Industria y mantenimiento | K40: 03571 681577 / 03571 506656 | L40: OK | M40: despacho / producción | N40: Movimientos especiales de mantenimiento, repuestos pesados y mudanzas internas de equipos. | O40: Despacho de estructuras, tanques, transformadores, piezas de ingeniería y equipos sobre plataforma 20 tn. | P40: Ofrecer retiro/entrega con monitoreo GPS. | Q40: Visita o llamada de validación; pedir próximo traslado concreto. | S40: =IFERROR(T(INDEX('Prospectos Resumen'!$K$9:$K$297,MATCH(A40,'Prospectos Resumen'!$A$9:$A$297,0))),"") -> FEDE SERRA | X40: tel:+543571681577 | Y40: tel:+543571681577 | tel:+543571506656 | Z40: Validar contacto decisor y necesidad inmediata. | AA40: https://www.google.com/maps/search/?api=1&query=-32.170500,-64.118500 | AB40: Facebook MetalMec | AD40: Registro curado en documento de dirección PRESOL 2026-09. | AE40: Alta | AF40: Base curada PDF dirección | AG40: plataforma 20 tn para maquinaria/piezas | hidrogrúa para maniobras | percha para pallets | AH40: fabricante/servicio maquinaria agrícola | AI40: Sí | AJ40: Alta | AL40: GPT adjunto + Hermes | AM40: Fusionado con base Hermes para completar teléfonos/fuentes/servicios. | ID fuente: RT-026
A41: RT-030 | B41: Pendiente | C41: Base Río Tercero | D41: Río Tercero | E41: Río Tercero | F41: B | G41: 75 | H41: Oleos San José S.R.L. | I41: Extrusado/aceite de soja | J41: Agroindustria y alimentos | K41: 03571 692471 / 03571 640630 | L41: OK | M41: responsable de acopio / mantenimiento | N41: Movimientos especiales de mantenimiento, repuestos pesados y mudanzas internas de equipos. | O41: Movimiento de equipos de planta, silos, balanzas, repuestos y cargas especiales para acopios/agroindustria. | P41: Entrar por mantenimiento/planta. | Q41: Visita o llamada de validación; pedir próximo traslado concreto. | S41: =IFERROR(T(INDEX('Prospectos Resumen'!$K$9:$K$297,MATCH(A41,'Prospectos Resumen'!$A$9:$A$297,0))),"") | X41: tel:+543571692471 | Y41: tel:+543571692471 | tel:+543571640630 | Z41: Validar contacto decisor y necesidad inmediata. | AA41: https://www.google.com/maps/search/?api=1&query=-32.182600,-64.102500 | AB41: Parque Industrial Río Tercero | AD41: Registro curado en documento de dirección PRESOL 2026-09. | AE41: Alta | AF41: Base curada PDF dirección | AG41: plataforma 20 tn para maquinaria/piezas | hidrogrúa para maniobras | percha para pallets | percha para pallets de insumos | hidrogrúa para equipos/mantenimiento | barquilla para trabajos en altura | AH41: otro rubro factible | AI41: Sí | AJ41: Alta | AL41: GPT adjunto + Hermes | AM41: Fusionado con base Hermes para completar teléfonos/fuentes/servicios. | ID fuente: RT-027
A42: RT-031 | B42: Pendiente | C42: Base Río Tercero | D42: Río Tercero / zona industrial | E42: Río Tercero | F42: B | G42: 75 | H42: Premolfran Premoldeados by d'Eco | I42: Premoldeados de hormigón | J42: Hormigón, áridos y materiales | K42: 03571 327594 | L42: OK | M42: planta / despacho | N42: Movimiento de premoldeados, moldes, equipos de planta y cargas pesadas asociadas a obra. | O42: Transporte de premoldeados/equipos en plataforma + coordinación de descarga/posicionamiento con hidrogrúa cuando aplique. | P42: Ficha pública local identifica actividad de premoldeados y teléfono. | Q42: Llamar para validar necesidad y frecuencia; visitar si confirma movimientos de equipos/cargas. | S42: =IFERROR(T(INDEX('Prospectos Resumen'!$K$9:$K$297,MATCH(A42,'Prospectos Resumen'!$A$9:$A$297,0))),"") | X42: tel:+543571327594 | Y42: tel:+543571327594 | Z42: Confirmar decisor, frecuencia de movimientos y vigencia del contacto antes de cotizar. | AA42: https://www.google.com/maps/search/?api=1&query=Premolfran+Premoldeados+by+d%27Eco+R%C3%ADo+Tercero+C%C3%B3rdoba+Argentina | AB42: Google Maps / ficha pública | AC42: https://www.google.com/maps/search/?api=1&query=Premolfran+Premoldeados+by+d%27Eco+R%C3%ADo+Tercero+C%C3%B3rdoba+Argentina | AD42: Ficha pública local identifica actividad de premoldeados y teléfono. | AE42: Alta | AF42: Enriquecimiento web 2026-09-07 | AG42: transporte de áridos/materiales | hidrogrúa para carga/descarga | percha para pallets/bolsones | AH42: áridos/construcción/premoldeados | AI42: Sí | AJ42: Alta | AK42: Áridos/materiales: confirmar modalidad de carga/descarga y tipo de unidad requerida antes de cotizar. | AL42: GPT adjunto | AM42: ID fuente: RT-028
A43: RT-032 | B43: Pendiente | C43: Base Río Tercero | D43: Parque Industrial Leonardo Da Vinci | E43: Río Tercero | F43: B | G43: 75 | H43: Río Metal | I43: Estructuras metálicas | J43: Metalúrgica y fabricación | K43: +54 9 3571 52-9444 | L43: OK | M43: despacho / producción | N43: Despacho seguro de estructuras, carrozados, tanques, piezas industriales y equipos sobre plataforma. | O43: Plataforma 20 tn para piezas/estructuras + seguro de carga + trazabilidad GPS. | P43: Fabricación de estructuras metálicas: posible salida de piezas a obra. | Q43: Validar teléfono/contacto; si responde, pedir un caso concreto de traslado o próximo movimiento. | S43: =IFERROR(T(INDEX('Prospectos Resumen'!$K$9:$K$297,MATCH(A43,'Prospectos Resumen'!$A$9:$A$297,0))),"") | X43: tel:+5493571529444 | Y43: tel:+5493571529444 | Z43: Confirmar decisor y vigencia del dato antes de incluir en salida prioritaria. | AA43: https://www.google.com/maps/search/?api=1&query=R%C3%ADo+Metal+R%C3%ADo+Tercero+C%C3%B3rdoba+Argentina | AB43: Parque Industrial Río Tercero / Facebook público | AC43: https://parqueindustrial.riotercero.gob.ar/empresas | AD43: Listado del parque + ficha social pública con teléfono informado. | AE43: Alta | AF43: Nuevo enriquecimiento 2026-09-02 | AG43: plataforma 20 tn para maquinaria/piezas | hidrogrúa para maniobras | percha para pallets | AH43: otro rubro factible | AI43: Sí | AJ43: Alta | AL43: GPT adjunto + Hermes | AM43: Fusionado con base Hermes para completar teléfonos/fuentes/servicios. | ID fuente: RT-029
A44: RT-033 | B44: Pendiente | C44: Base Río Tercero | D44: Río Tercero / zona industrial | E44: Río Tercero | F44: B | G44: 75 | H44: SILMAR Industrial | I44: Fabricación industrial | J44: Metalúrgica y fabricación | K44: 03571 411073 | L44: OK | M44: mantenimiento / despacho | N44: Movimientos especiales de mantenimiento, repuestos pesados, equipos y mudanzas internas o entre plantas. | O44: Traslados especiales de equipos y repuestos con plataforma 20 tn, seguro/GPS y apoyo de hidrogrúa. | P44: Fábrica local con teléfono público; validar tipo de piezas/equipos y frecuencia de despachos. | Q44: Llamar para validar necesidad y frecuencia; visitar si confirma movimientos de equipos/cargas. | S44: =IFERROR(T(INDEX('Prospectos Resumen'!$K$9:$K$297,MATCH(A44,'Prospectos Resumen'!$A$9:$A$297,0))),"") | X44: tel:+543571411073 | Y44: tel:+543571411073 | Z44: Confirmar decisor, frecuencia de movimientos y vigencia del contacto antes de cotizar. | AA44: https://www.google.com/maps/search/?api=1&query=SILMAR+Industrial+R%C3%ADo+Tercero+C%C3%B3rdoba+Argentina | AB44: Google Maps / ficha pública | AC44: https://www.google.com/maps/search/?api=1&query=SILMAR+Industrial+R%C3%ADo+Tercero+C%C3%B3rdoba+Argentina | AD44: Fábrica local con teléfono público; validar tipo de piezas/equipos y frecuencia de despachos. | AE44: Alta | AF44: Enriquecimiento web 2026-09-07 | AG44: plataforma 20 tn para maquinaria/piezas | hidrogrúa para maniobras | percha para pallets | AH44: otro rubro factible | AI44: Sí | AJ44: Alta | AL44: GPT adjunto | AM44: ID fuente: RT-030
A45: RT-034 | B45: Pendiente | C45: Base Río Tercero | D45: Río Tercero / zona industrial | E45: Río Tercero | F45: B | G45: 75 | H45: TALFUND S.A. | I45: Tornería, matricería y fundición de aluminio | J45: Metalúrgica y fabricación | K45: 03571 690418 / 03571 642555 | L45: OK | M45: despacho / producción | N45: Despacho de estructuras, piezas, equipos y conjuntos metalmecánicos de gran porte hacia obras o clientes. | O45: Plataforma 20 tn para piezas/estructuras + seguro de carga + trazabilidad GPS + apoyo de hidrogrúa según maniobra. | P45: Produce componentes metálicos para agroindustria y exportación; teléfonos publicados por el parque. | Q45: Llamar para validar necesidad y frecuencia; visitar si confirma movimientos de equipos/cargas. | S45: =IFERROR(T(INDEX('Prospectos Resumen'!$K$9:$K$297,MATCH(A45,'Prospectos Resumen'!$A$9:$A$297,0))),"") | X45: tel:+543571690418 | Y45: tel:+543571690418 | tel:+543571642555 | Z45: Confirmar decisor, frecuencia de movimientos y vigencia del contacto antes de cotizar. | AA45: https://www.google.com/maps/search/?api=1&query=TALFUND+S.A.+R%C3%ADo+Tercero+C%C3%B3rdoba+Argentina | AB45: Parque Industrial Río Tercero | AC45: https://parqueindustrial.riotercero.gob.ar/empresa/TALFUND-S.A. | AD45: Produce componentes metálicos para agroindustria y exportación; teléfonos publicados por el parque. | AE45: Alta | AF45: Enriquecimiento web 2026-09-07 | AG45: transporte de áridos/materiales | hidrogrúa para carga/descarga | percha para pallets/bolsones | plataforma 20 tn para maquinaria/piezas | hidrogrúa para maniobras | percha para pallets | AH45: otro rubro factible | AI45: Sí | AJ45: Alta | AL45: GPT adjunto | AM45: ID fuente: RT-031
A46: RT-035 | B46: Pendiente | C46: Base Río Tercero | D46: Río Tercero / zona industrial | E46: Río Tercero | F46: B | G46: 75 | H46: Tello SRL Premoldeados de Hormigón | I46: Premoldeados de hormigón | J46: Hormigón, áridos y materiales | K46: 0351 4576859 | L46: OK | M46: planta / despacho | N46: Movimiento de premoldeados, moldes, equipos de planta y cargas pesadas asociadas a obra. | O46: Transporte de premoldeados/equipos en plataforma + coordinación de descarga/posicionamiento con hidrogrúa cuando aplique. | P46: Ficha pública ubica proveedor/contratista de premoldeados en Av. Savio, Río Tercero. | Q46: Llamar para validar necesidad y frecuencia; visitar si confirma movimientos de equipos/cargas. | S46: =IFERROR(T(INDEX('Prospectos Resumen'!$K$9:$K$297,MATCH(A46,'Prospectos Resumen'!$A$9:$A$297,0))),"") | X46: tel:+543514576859 | Y46: tel:+543514576859 | Z46: Confirmar decisor, frecuencia de movimientos y vigencia del contacto antes de cotizar. | AA46: https://www.google.com/maps/search/?api=1&query=Tello+SRL+Premoldeados+de+Hormig%C3%B3n+R%C3%ADo+Tercero+C%C3%B3rdoba+Argentina | AB46: Google Maps / ficha pública | AC46: https://www.google.com/maps/search/?api=1&query=Tello+SRL+Premoldeados+de+Hormig%C3%B3n+R%C3%ADo+Tercero+C%C3%B3rdoba+Argentina | AD46: Ficha pública ubica proveedor/contratista de premoldeados en Av. Savio, Río Tercero. | AE46: Alta | AF46: Enriquecimiento web 2026-09-07 | AG46: transporte de áridos/materiales | hidrogrúa para carga/descarga | percha para pallets/bolsones | AH46: áridos/construcción/premoldeados | AI46: Sí | AJ46: Alta | AK46: Áridos/materiales: confirmar modalidad de carga/descarga y tipo de unidad requerida antes de cotizar. | AL46: GPT adjunto | AM46: ID fuente: RT-032
A47: RT-061 | B47: Pendiente | C47: Base Río Tercero | D47: Río Tercero / zona industrial | E47: Río Tercero | F47: B | G47: 72 | H47: Formia Repuestos | I47: Repuestos para tractores y maquinaria agrícola | J47: Maquinaria agrícola | K47: 03571 422102 | L47: Verificar | M47: logística / ventas / postventa | N47: Movimiento de agropartes, repuestos pesados, conjuntos y eventualmente implementos/equipos entre planta, concesionarios y clientes. | O47: Plataforma e hidrogrúa para conjuntos pesados + percha/pallets para repuestos + seguro y trazabilidad. | P47: Ofrecer respaldo flexible para despachos voluminosos y cargas que exceden el transporte convencional de repuestos. | Q47: Validar contacto y volumen de movimientos; si hay encaje, pedir un traslado concreto para cotizar. | S47: =IFERROR(T(INDEX('Prospectos Resumen'!$K$9:$K$297,MATCH(A47,'Prospectos Resumen'!$A$9:$A$297,0))),"") | X47: tel:+543571422102 | Y47: tel:+543571422102 | Z47: Confirmar teléfono, decisor y vigencia del punto de venta. | AA47: https://www.google.com/maps/search/?api=1&query=Formia+Repuestos+R%C3%ADo+Tercero+C%C3%B3rdoba+Argentina | AB47: Guía Urbana / ficha comercial | AC47: https://www.guiaurbana.com.ar/empresas/formia-repuestos-rio-tercero | AD47: Comercio de repuestos para tractores y líneas Deutz, AGCO, Valtra y Massey Ferguson. | AE47: Media | AF47: Rastrillaje agro-maquinaria web 2026-09-07 | AG47: plataforma 20 tn para maquinaria/implementos | hidrogrúa para maniobras | malacate | seguro de carga | trazabilidad GPS | AH47: fabricante/concesionario/servicio maquinaria agrícola | AI47: Sí | AJ47: Media | AK47: Perfil específico maquinaria agrícola: validar pesos/dimensiones, tipo de carga y disponibilidad de medios de izaje antes de cotizar. | AL47: Rastrillaje agro-maquinaria 2026-09-07 | AM47: Alta nueva luego de barrido específico de fabricantes, implementos, tractores, concesionarios y agropartes; cruzada contra la base maestra para evitar duplicados.
A48: RT-063 | B48: Pendiente | C48: Base Río Tercero | D48: Río Tercero / zona industrial | E48: Río Tercero | F48: B | G48: 68 | H48: Hidráulica Río Tercero | I48: Hidráulica y repuestos para maquinaria agrícola | J48: Maquinaria agrícola | K48: 03571 432041 | L48: Verificar | M48: logística / ventas / postventa | N48: Movimiento de agropartes, repuestos pesados, conjuntos y eventualmente implementos/equipos entre planta, concesionarios y clientes. | O48: Plataforma e hidrogrúa para conjuntos pesados + percha/pallets para repuestos + seguro y trazabilidad. | P48: Ofrecer respaldo flexible para despachos voluminosos y cargas que exceden el transporte convencional de repuestos. | Q48: Validar contacto y volumen de movimientos; si hay encaje, pedir un traslado concreto para cotizar. | S48: =IFERROR(T(INDEX('Prospectos Resumen'!$K$9:$K$297,MATCH(A48,'Prospectos Resumen'!$A$9:$A$297,0))),"") | X48: tel:+543571432041 | Y48: tel:+543571432041 | Z48: Confirmar teléfono, decisor y vigencia del punto de venta. | AA48: https://www.google.com/maps/search/?api=1&query=Hidr%C3%A1ulica+R%C3%ADo+Tercero+R%C3%ADo+Tercero+C%C3%B3rdoba+Argentina | AB48: Directorio comercial / Google Maps | AC48: https://www.google.com/maps/search/?api=1&query=Hidr%C3%A1ulica+R%C3%ADo+Tercero+R%C3%ADo+Tercero+C%C3%B3rdoba+Argentina | AD48: Taller/comercio hidráulico asociado a reparación y repuestos de maquinaria agrícola; validar vigencia. | AE48: Media | AF48: Rastrillaje agro-maquinaria web 2026-09-07 | AG48: plataforma 20 tn para maquinaria/implementos | hidrogrúa para maniobras | malacate | seguro de carga | trazabilidad GPS | AH48: fabricante/concesionario/servicio maquinaria agrícola | AI48: Sí | AJ48: Media | AK48: Perfil específico maquinaria agrícola: validar pesos/dimensiones, tipo de carga y disponibilidad de medios de izaje antes de cotizar. | AL48: Rastrillaje agro-maquinaria 2026-09-07 | AM48: Alta nueva luego de barrido específico de fabricantes, implementos, tractores, concesionarios y agropartes; cruzada contra la base maestra para evitar duplicados.
A49: RT-036 | B49: Pendiente | C49: Base Río Tercero | D49: Río Tercero | E49: Río Tercero | F49: B | G49: 60 | H49: Baudino Hnos. | I49: Estructuras metálicas | J49: Metalúrgica y fabricación | K49: 03571 15600693 / 3571 457279 / 3571 458732 | L49: Verificar | M49: despacho / producción | N49: Despacho seguro de estructuras, carrozados, tanques, piezas industriales y equipos sobre plataforma. | O49: Plataforma 20 tn para piezas/estructuras + seguro de carga + trazabilidad GPS. | P49: Estructuras metálicas locales; buen encaje para transporte de piezas y montaje. | Q49: Validar teléfono/contacto; si responde, pedir un caso concreto de traslado o próximo movimiento. | S49: =IFERROR(T(INDEX('Prospectos Resumen'!$K$9:$K$297,MATCH(A49,'Prospectos Resumen'!$A$9:$A$297,0))),"") -> DIEGO BAUDINO | X49: tel:+5493571600693 | Y49: tel:+5493571600693 | tel:+543571457279 | tel:+543571458732 | Z49: Confirmar decisor y vigencia del dato antes de incluir en salida prioritaria. | AA49: https://www.google.com/maps/search/?api=1&query=Baudino+Hnos.+R%C3%ADo+Tercero+C%C3%B3rdoba+Argentina | AB49: Web pública Baudino Hnos. / resultado de búsqueda | AC49: https://baudinohnos.wixsite.com/baudinohnos | AD49: Resultado público indica dirección y teléfonos; verificar vigencia antes de visita. | AE49: Media | AF49: Nuevo enriquecimiento 2026-09-02 | AG49: plataforma 20 tn para maquinaria/piezas | hidrogrúa para maniobras | percha para pallets | AH49: otro rubro factible | AI49: Sí | AJ49: Media | AL49: GPT adjunto + Hermes | AM49: Fusionado con base Hermes para completar teléfonos/fuentes/servicios. | ID fuente: RT-033
A50: RT-037 | B50: Pendiente | C50: Base Río Tercero | D50: Río Tercero | E50: Río Tercero | F50: B | G50: 60 | H50: Charrúa Implementos Agrícolas | I50: Implementos agrícolas | J50: Maquinaria agrícola | K50: 03571 619149 / 03571 503663 (a confirmar) / +54 9 3571 61 9149 / +54 9 3571 31 0086 | L50: OK | M50: responsable de acopio / mantenimiento | N50: Movimientos especiales de mantenimiento, repuestos pesados y mudanzas internas de equipos. | O50: Movimiento de equipos de planta, silos, balanzas, repuestos y cargas especiales para acopios/agroindustria. | P50: Pedir frecuencia de entregas a concesionarios/campos. | Q50: Visita o llamada de validación; pedir próximo traslado concreto. | S50: =IFERROR(T(INDEX('Prospectos Resumen'!$K$9:$K$297,MATCH(A50,'Prospectos Resumen'!$A$9:$A$297,0))),"") | X50: tel:+543571619149 | Y50: tel:+543571619149 | tel:+543571503663 | tel:+5493571619149 | tel:+5493571310086 | Z50: Validar contacto decisor y necesidad inmediata. | AA50: https://www.google.com/maps/search/?api=1&query=-32.168609,-64.118792 | AB50: Web/Facebook Charrúa | Web propia Charrúa Implementos Agrícolas | AC50: https://charruaimplementosagricolas.com.ar | AD50: Registro curado en documento de dirección PRESOL 2026-09. | Sitio propio: Catamarca 2167, Parque Industrial Río Tercero; teléfonos +54 9 3571 61-9149 / 31-0086; implementos agrícolas. | AE50: Media | AF50: Base curada PDF dirección | AG50: plataforma 20 tn para maquinaria/piezas | hidrogrúa para maniobras | percha para pallets | percha para pallets de insumos | hidrogrúa para equipos/mantenimiento | barquilla para trabajos en altura | AH50: fabricante/servicio maquinaria agrícola | AI50: Sí | AJ50: Media | AL50: GPT adjunto + Hermes | AM50: Fusionado con base Hermes para completar teléfonos/fuentes/servicios. | ID fuente: RT-034
A51: RT-038 | B51: Pendiente | C51: Base Río Tercero | D51: Río Tercero | E51: Río Tercero | F51: B | G51: 60 | H51: HIDROSERVIS | I51: Cilindros hidráulicos | J51: Metalúrgica y fabricación | K51: Portería parque: 03571 565662 | L51: Verificar | M51: responsable de logística/compras | N51: Movimientos especiales de mantenimiento, repuestos pesados y mudanzas internas de equipos. | O51: Detectar el próximo movimiento pesado y convertirlo en cotización concreta. | P51: Ofrecer servicio de retiro/entrega de equipos pesados. | Q51: Visita o llamada de validación; pedir próximo traslado concreto. | S51: =IFERROR(T(INDEX('Prospectos Resumen'!$K$9:$K$297,MATCH(A51,'Prospectos Resumen'!$A$9:$A$297,0))),"") | X51: tel:+543571565662 | Y51: tel:+543571565662 | Z51: Validar contacto decisor y necesidad inmediata. | AA51: https://www.google.com/maps/search/?api=1&query=-32.181800,-64.104800 | AB51: Parque Industrial Río Tercero | AD51: Registro curado en documento de dirección PRESOL 2026-09. | AE51: Media | AF51: Base curada PDF dirección | AG51: plataforma 20 tn para maquinaria/piezas | hidrogrúa para maniobras | percha para pallets | AH51: otro rubro factible | AI51: Sí | AJ51: Media | AL51: GPT adjunto + Hermes | AM51: Fusionado con base Hermes para completar teléfonos/fuentes/servicios. | ID fuente: RT-035
A52: RT-039 | B52: Pendiente | C52: Base Río Tercero | D52: Río Tercero | E52: Río Tercero | F52: B | G52: 60 | H52: Hormilas S.A. | I52: Hormigón elaborado | J52: Hormigón, áridos y materiales | K52: 03571 573231 (a confirmar) | L52: Verificar | M52: operaciones / planta | N52: Movimiento de premoldeados, equipos de planta/cantera, bombas, moldes y cargas pesadas. | O52: Traslado de equipos de planta, bombas, premoldeados y apoyo a picos de obra. | P52: Visita breve: detectar si tercerizan fletes de planta. | Q52: Visita o llamada de validación; pedir próximo traslado concreto. | S52: =IFERROR(T(INDEX('Prospectos Resumen'!$K$9:$K$297,MATCH(A52,'Prospectos Resumen'!$A$9:$A$297,0))),"") | X52: tel:+543571573231 | Y52: tel:+543571573231 | Z52: Validar contacto decisor y necesidad inmediata. | AA52: https://www.google.com/maps/search/?api=1&query=-32.163876,-64.106999 | AB52: Parque Industrial Río Tercero / búsqueda web | AD52: Registro curado en documento de dirección PRESOL 2026-09. | AE52: Media | AF52: Base curada PDF dirección | AG52: transporte de áridos/materiales | hidrogrúa para carga/descarga | percha para pallets/bolsones | AH52: áridos/construcción/premoldeados | AI52: Sí | AJ52: Media | AK52: Áridos/materiales: confirmar modalidad de carga/descarga y tipo de unidad requerida antes de cotizar. | AL52: GPT adjunto + Hermes | AM52: Fusionado con base Hermes para completar teléfonos/fuentes/servicios. | ID fuente: RT-036
A53: RT-040 | B53: Pendiente | C53: Base Río Tercero | D53: Río Tercero / zona industrial | E53: Río Tercero | F53: B | G53: 60 | H53: MoliCor | I53: Accesorios para industrias molineras | J53: Metalúrgica y fabricación | K53: A relevar vía parque | L53: A relevar | M53: despacho / producción | N53: Despacho de estructuras, piezas, equipos y conjuntos metalmecánicos de gran porte hacia obras o clientes. | O53: Plataforma 20 tn para piezas/estructuras + seguro de carga + trazabilidad GPS + apoyo de hidrogrúa según maniobra. | P53: Listado oficial del parque: accesorios para industrias molineras; contacto directo pendiente. | Q53: Llamar para validar necesidad y frecuencia; visitar si confirma movimientos de equipos/cargas. | S53: =IFERROR(T(INDEX('Prospectos Resumen'!$K$9:$K$297,MATCH(A53,'Prospectos Resumen'!$A$9:$A$297,0))),"") | Z53: Confirmar decisor, frecuencia de movimientos y vigencia del contacto antes de cotizar. | AA53: https://www.google.com/maps/search/?api=1&query=MoliCor+R%C3%ADo+Tercero+C%C3%B3rdoba+Argentina | AB53: Parque Industrial Río Tercero | AC53: https://parqueindustrial.riotercero.gob.ar/empresas | AD53: Listado oficial del parque: accesorios para industrias molineras; contacto directo pendiente. | AE53: Media | AF53: Enriquecimiento web 2026-09-07 | AG53: transporte de áridos/materiales | hidrogrúa para carga/descarga | percha para pallets/bolsones | plataforma 20 tn para maquinaria/piezas | hidrogrúa para maniobras | percha para pallets | AH53: otro rubro factible | AI53: Sí | AJ53: Media | AL53: GPT adjunto | AM53: ID fuente: RT-037
A54: RT-041 | B54: Pendiente | C54: Base Río Tercero | D54: Río Tercero / zona industrial | E54: Río Tercero | F54: B | G54: 60 | H54: Taller RS S.A. | I54: Mantenimiento y calibración de válvulas industriales | J54: Industria y mantenimiento | K54: 03571 422065 | L54: OK | M54: mantenimiento / despacho | N54: Movimientos especiales de mantenimiento, repuestos pesados, equipos y mudanzas internas o entre plantas. | O54: Traslados especiales de equipos y repuestos con plataforma 20 tn, seguro/GPS y apoyo de hidrogrúa. | P54: Empresa del parque dedicada a válvulas industriales; potencial de movimientos de equipos y repuestos. | Q54: Llamar para validar necesidad y frecuencia; visitar si confirma movimientos de equipos/cargas. | S54: =IFERROR(T(INDEX('Prospectos Resumen'!$K$9:$K$297,MATCH(A54,'Prospectos Resumen'!$A$9:$A$297,0))),"") | X54: tel:+543571422065 | Y54: tel:+543571422065 | Z54: Confirmar decisor, frecuencia de movimientos y vigencia del contacto antes de cotizar. | AA54: https://www.google.com/maps/search/?api=1&query=Taller+RS+S.A.+R%C3%ADo+Tercero+C%C3%B3rdoba+Argentina | AB54: Parque Industrial / Google Maps | AC54: https://parqueindustrial.riotercero.gob.ar/empresas | AD54: Empresa del parque dedicada a válvulas industriales; potencial de movimientos de equipos y repuestos. | AE54: Alta | AF54: Enriquecimiento web 2026-09-07 | AG54: plataforma 20 tn para maquinaria/piezas | hidrogrúa para maniobras | percha para pallets | AH54: otro rubro factible | AI54: Sí | AJ54: Alta | AL54: GPT adjunto | AM54: ID fuente: RT-038
A55: RT-042 | B55: Pendiente | C55: Base Río Tercero | D55: Río Tercero | E55: Río Tercero | F55: B | G55: 50 | H55: Atanor / Albaugh | I55: Química / agroquímicos | J55: Agro, acopio y cooperativas | K55: A relevar | L55: A relevar | M55: responsable de acopio / mantenimiento | N55: Traslado de equipos de planta, silos, repuestos pesados, balanzas, implementos y cargas especiales. | O55: Movimiento de equipos de planta, silos, balanzas, repuestos y cargas especiales para acopios/agroindustria. | P55: No vender por puerta fría baja; pedir compras/mantenimiento. | Q55: Visita o llamada de validación; pedir próximo traslado concreto. | S55: =IFERROR(T(INDEX('Prospectos Resumen'!$K$9:$K$297,MATCH(A55,'Prospectos Resumen'!$A$9:$A$297,0))),"") -> MARCOS PALOMBARINI (GERENTE DE MANTENIMIENTO) JOSE ROSSO (JEFE DE PLANTA CLORO SODA) | Z55: Validar contacto decisor y necesidad inmediata. | AA55: https://www.google.com/maps/search/?api=1&query=-32.173000,-64.110000 | AB55: Albaugh / noticias sectoriales | AD55: Registro curado en documento de dirección PRESOL 2026-09. | AE55: Media | AF55: Base curada PDF dirección | AG55: plataforma 20 tn para maquinaria/piezas | hidrogrúa para maniobras | percha para pallets | percha para pallets de insumos | hidrogrúa para equipos/mantenimiento | barquilla para trabajos en altura | AH55: otro rubro factible | AI55: Sí | AJ55: Media | AK55: Percha pallets: útil para insumos, bolsones, repuestos y materiales palletizados. | AL55: GPT adjunto + Hermes | AM55: Fusionado con base Hermes para completar teléfonos/fuentes/servicios. | ID fuente: RT-039
A56: RT-043 | B56: Pendiente | C56: Base Río Tercero | D56: Parque Industrial Leonardo Da Vinci | E56: Río Tercero | F56: B | G56: 50 | H56: Bravo Gustavo y Guillermo | I56: Premoldeados | J56: Hormigón, áridos y materiales | K56: A relevar vía parque | L56: A relevar | M56: planta / despacho | N56: Movimiento de premoldeados, equipos de planta/cantera, bombas, moldes y cargas pesadas. | O56: Transporte de premoldeados/equipos; áridos sueltos solo sujeto a validar caja volcadora o tercerización. | P56: Premoldeados locales: potencial de transporte de piezas y reparto pesado regional. | Q56: Validar teléfono/contacto; si responde, pedir un caso concreto de traslado o próximo movimiento. | S56: =IFERROR(T(INDEX('Prospectos Resumen'!$K$9:$K$297,MATCH(A56,'Prospectos Resumen'!$A$9:$A$297,0))),"") | Z56: Confirmar decisor y vigencia del dato antes de incluir en salida prioritaria. | AA56: https://www.google.com/maps/search/?api=1&query=Bravo+Gustavo+y+Guillermo+R%C3%ADo+Tercero+C%C3%B3rdoba+Argentina | AB56: Parque Industrial Río Tercero | AC56: https://parqueindustrial.riotercero.gob.ar/empresas | AD56: Listado del parque indica fabricación de premoldeados. | AE56: Media | AF56: Nuevo enriquecimiento 2026-09-02 | AG56: transporte de áridos/materiales | hidrogrúa para carga/descarga | percha para pallets/bolsones | AH56: áridos/construcción/premoldeados | AI56: Sí | AJ56: Media | AL56: GPT adjunto + Hermes | AM56: Fusionado con base Hermes para completar teléfonos/fuentes/servicios. | ID fuente: RT-040
A57: RT-044 | B57: Pendiente | C57: Base Río Tercero | D57: Parque Industrial Leonardo Da Vinci | E57: Río Tercero | F57: B | G57: 50 | H57: Construcciones Sermanter S.R.L. | I57: Construcción, montaje y mantenimiento | J57: Metalúrgica y fabricación | K57: A relevar vía parque | L57: A relevar | M57: jefe de obra / mantenimiento | N57: Despacho seguro de estructuras, carrozados, tanques, piezas industriales y equipos sobre plataforma. | O57: Plataforma 20 tn para piezas/estructuras + seguro de carga + trazabilidad GPS. | P57: Constructor/montajista local: puede demandar traslado de equipos, estructuras y materiales pesados. | Q57: Validar teléfono/contacto; si responde, pedir un caso concreto de traslado o próximo movimiento. | S57: =IFERROR(T(INDEX('Prospectos Resumen'!$K$9:$K$297,MATCH(A57,'Prospectos Resumen'!$A$9:$A$297,0))),"") -> ROLANDO RAMELLO | Z57: Confirmar decisor y vigencia del dato antes de incluir en salida prioritaria. | AA57: https://www.google.com/maps/search/?api=1&query=Construcciones+Sermanter+S.R.L.+R%C3%ADo+Tercero+C%C3%B3rdoba+Argentina | AB57: Parque Industrial Río Tercero | AC57: https://parqueindustrial.riotercero.gob.ar/empresas | AD57: Empresa listada en Parque Industrial como construcción, montaje y mantenimiento. | AE57: Media | AF57: Nuevo enriquecimiento 2026-09-02 | AG57: transporte de áridos/materiales | hidrogrúa para carga/descarga | percha para pallets/bolsones | AH57: áridos/construcción/premoldeados | AI57: Sí | AJ57: Media | AL57: GPT adjunto + Hermes | AM57: Fusionado con base Hermes para completar teléfonos/fuentes/servicios. | ID fuente: RT-041
